Workbook

Sheet Saldos Iniciales
A1: Empresa | B1: Cuenta Bancaria | C1: Mes/Año inicio | D1: Saldo Inicial
A2: CFT Group | B2: Bank of America - CFT Group - 4415-USD | C2: 2026-07 | D2: 132689.05 | E2: 2026-05
A3: CFT Group | B3: Amerant Bank - CFT Group - 1906-USD | C3: 2026-07 | D3: 62799.53 | E3: 2026-05
A4: CFT Group | B4: Northern Trust - CFT Group - 1355-USD | C4: 2026-07 | D4: 5274.85 | E4: 2026-05
A5: M1B | B5: Amerant Bank - M1B - 0906-USD | C5: 2026-07 | D5: 39539.54 | E5: 2026-05
A6: M1B | B6: Amerant Bank DACA - M1B - 8231-USD | C6: 2026-07 | D6: 5000 | E6: 2026-05
A7: Durand | B7: Amerant Bank - Durand - 0106-USD | C7: 2026-07 | D7: 1669.89 | E7: 2026-05
A8: A&M Imports | B8: Bank of America - A&M Imports - 3797-USD | C8: 2026-07 | D8: 177088.59 | E8: 2026-05
A9: SSP Capital | B9: Bank of America - SSP Capital - 2580-USD | C9: 2026-07 | D9: 12379.18 | E9: 2026-05
A10: SSP Capital | B10: Bank of America - SSP Capital - 1655-USD | C10: 2026-07 | D10: 759.07 | E10: 2026-05
A11: SSP Capital | B11: EFG - SSP Capital - 21.0-USD | C11: 2026-07 | E11: 2026-05
A12: SSP Capital | B12: Amerant Bank - SSP Capital - 4706-USD | C12: 2026-07 | D12: 219857.82 | E12: 2026-05
A13: SSP Capital | B13: Northern Trust - SSP Capital - 1452-USD | C13: 2026-07 | D13: 4870.11 | E13: 2026-05
A14: SSP Capital | B14: Amerant Bank Money Market - SSP Capital - 1006-USD | C14: 2026-07 | D14: 747521.2 | E14: 2026-05
A15: SSP Capital | B15: Amerant Bank DACA - SSP Capital - 9873-USD | C15: 2026-07 | D15: 5000 | E15: 2026-05
A16: Cross Family Trust | B16: Ocean Bank - Cross Family Trust - 3405-USD | C16: 2026-07 | D16: 57206.89 | E16: 2026-05
A17: Cross Family Trust | B17: Northern Trust - Cross Family Trust - 9263-USD | C17: 2026-07 | D17: 6365 | E17: 2026-05
A18: Cross Family Trust | B18: Bank of America - Cross Family Trust - 3124-USD | C18: 2026-07 | D18: 13221.89 | E18: 2026-05
A19: Cross Family Trust | B19: Amerant Bank - Cross Family Trust - 4706-USD | C19: 2026-07 | D19: 65717.6 | E19: 2026-05
A20: Cross Security Trust | B20: Bank of America - Cross Security Trust - 6642-USD | C20: 2026-07 | D20: 13088.59 | E20: 2026-05
A21: Electrama | B21: Chase Bank - Electrama - 6520-USD | C21: 2026-07 | D21: 92.02 | E21: 2026-06
A22: Sacred Valley Capital | B22: Bank of America - Sacred Valley Capital - 4376-USD | C22: 2026-07 | D22: 144.25 | E22: 2026-05
A23: YWC Capital | B23: Bank of America - YWC Capital - 0282-USD | C23: 2026-07 | D23: 2297.67 | E23: 2026-05
... A35: Go Blue | B35: Amerant Bank - Go Blue - 1557-USD | C35: 2026-07 | D35: 5293.35 | E35: 2026-07
A36: Pacha Ventures LLC | B36: Amerant Bank - Pacha Ventures LLC - 0206-USD | C36: 2026-09 | D36: 301167.45
A37: CFT1 Residence | B37: Amerant Bank - CFT 1 residence LLC - 0573-USD | C37: 2026-09 | D37: 1855.87
A38: CFT1 Residence | B38: Amerant Bank - CFT 1 residence LLC - 6607-USD | C38: 2026-09 | D38: 49579.06
A39: Carmen Cross Irrevocable Trust | B39: Amerant Bank - Carmen Cross Irrevocable Trust - 3406-USD | C39: 2026-09 | D39: 3631.96
A40: SIYP LLC | B40: Amerant Bank - SIYP LLC - 7820-USD | C40: 2026-09 | D40: 2301.3
A41: Prendamas SRL | B41: Amerant Bank - Prendamas SRL - 8160-USD | C41: 2026-09 | D41: 92394.88
A42: 360 Harbor Lane LLC | B42: Amerant Bank - 360 Harbor Lane LLC - 9306-USD | C42: 2026-09 | D42: 794.01
A43: Five Capital | B43: Bank of America - Five Capital - 3094-USD | C43: 2026-09 | D43: 5445.57
A44: SIYP LLC | B44: Bank of America - SIYP LLC - 2179-USD | C44: 2026-09 | D44: 18.13
A45: Nobe Aparments | B45: Bank of America - Nobe Aparments - 2113-USD | C45: 2026-09 | D45: 206959.21
A46: Nobe Aparments | B46: Bank of America - Nobe Aparments - 8047-USD | C46: 2026-09 | D46: 31093.71
A47: Don Cross Life | B47: Bank of America - Don Cross Life Trust - 9372-USD | C47: 2026-09 | D47: 303874.72

Sheet Listas
A1: Empresas | B1: Cuentas Bancarias | C1: Banco | D1: Tipos | E1: Concepto | F1: Categoria | G1: Ext/Int
A2: CFT Group | B2: Bank of America - CFT Group - 4415-USD | C2: Bank of America | D2: Ingreso | E2: Eg.Gastos Operativos (Proveedor) | F2: Operativo | G2: Externo
A3: CFT Group | B3: Amerant Bank - CFT Group - 1906-USD | C3: Amerant Bank | D3: Egreso | E3: Eg.Gastos Operativos (Tarjeta credito) | F3: Operativo | G3: Externo
A4: CFT Group | B4: Northern Trust - CFT Group - 1355-USD | C4: Northern Trust | E4: Eg.Gastos Personal (Nomina, bono, etc) | F4: Operativo | G4: Externo
A5: M1B | B5: Amerant Bank - M1B - 0906-USD | C5: Amerant Bank | E5: Eg.Gastos Personal (Seguro Medico) | F5: Operativo | G5: Externo
A6: M1B | B6: Amerant Bank DACA - M1B - 8231-USD | C6: Amerant Bank DACA | E6: Eg.Gastos Personal (Taxes) | F6: Operativo | G6: Externo
A7: Durand | B7: Amerant Bank - Durand - 0106-USD | C7: Amerant Bank | E7: Eg.Gastos Personal (Trustee) | F7: Operativo | G7: Externo
A8: A&M Imports | B8: Bank of America - A&M Imports - 3797-USD | C8: Bank of America | E8: Eg.Gastos Bancarios | F8: Operativo | G8: Externo
A9: SSP Capital | B9: Bank of America - SSP Capital - 2580-USD | C9: Bank of America | E9: Eg.Impuestos | F9: Operativo | G9: Externo
A10: SSP Capital | B10: Bank of America - SSP Capital - 1655-USD | C10: Bank of America | E10: Eg.Deuda Terceros (Intereses) | F10: Financiamiento | G10: Externo
A11: SSP Capital | B11: EFG - SSP Capital - 21.0-USD | C11: EFG | E11: Eg.Deuda Terceros (Capital) | F11: Financiamiento | G11: Externo
A12: SSP Capital | B12: Amerant Bank - SSP Capital - 4706-USD | C12: Amerant Bank | E12: Eg.Deuda Terceros (Intereses+Capital) | F12: Financiamiento | G12: Externo
A13: SSP Capital | B13: Northern Trust - SSP Capital - 1452-USD | C13: Northern Trust | E13: Eg.Deuda Relacionadas (Intereses) | F13: Financiamiento | G13: Externo
A14: SSP Capital | B14: Amerant Bank Money Market - SSP Capital - 1006-USD | C14: Amerant Bank Money Market | E14: Eg.Deuda Relacionadas (Capital) | F14: Financiamiento | G14: Externo
A15: SSP Capital | B15: Amerant Bank DACA - SSP Capital - 9873-USD | C15: Amerant Bank DACA | E15: Eg.Deuda Relacionadas (Intereses+Capital) | F15: Financiamiento | G15: Externo
... A29: 2515 Overbrook | B29: Bank of America - 2515 Overbrook - 4648-USD | C29: Bank of America | E29: Eg.Otros egresos operativos | F29: Operativo | G29: Externo
A30: 2515 Overbrook | B30: Bank of America - 2515 Overbrook - 9923-USD | C30: Bank of America
A31: 112 Florida Ave | B31: Bank of America - 112 Florida Ave - 3259-USD | C31: Bank of America | E31: Ing.Dividendos Recibidos de Unidades de Negocio | F31: Inversion | G31: Externo
A32: 3628 Thomas Ave | B32: Bank of America - 3628 Thomas Ave - 4406-USD | C32: Bank of America | E32: Ing.Dividendos Recibidos de Empresas Relacionadas | F32: Inversion | G32: Interno
A33: Green Harbor Trust | B33: Amerant Bank - Green Harbor Trust - 7253-USD | C33: Amerant Bank | E33: Ing.Intereses Recibidos de Unidad de Negocio | F33: Operativo | G33: Externo
A34: Go Blue | B34: Amerant Bank - Go Blue - 8206-USD | C34: Amerant Bank | E34: Ing.Intereses Recibidos de Empresas Relacionadas | F34: Operativo | G34: Interno
A35: EC AUTO LLC (no existe) | B35: Amerant Bank - EC AUTO LLC (no existe) - 0509-USD | C35: Amerant Bank | E35: Ing.Capital Recibido de Unidad de Negocio | F35: Operativo | G35: Externo
A36: Go Blue | B36: Amerant Bank - Go Blue - 1557-USD | C36: Amerant Bank | E36: Ing.Capital Recibido de Empresas Relacionadas | F36: Operativo | G36: Interno
A37: Pacha Ventures LLC | B37: Amerant Bank - Pacha Ventures LLC - 0206-USD | C37: Amerant Bank | E37: Ing.Interes+Capital Recibido de Unidad de Negocio | F37: Operativo | G37: Externo
A38: CFT1 Residence | B38: Amerant Bank - CFT 1 residence LLC - 0573-USD | C38: Amerant Bank | E38: Ing.Interes+Capital Recibido de Empresas Relacionadas | F38: Operativo | G38: Interno
A39: CFT1 Residence | B39: Amerant Bank - CFT 1 residence LLC - 6607-USD | C39: Amerant Bank | E39: Ing.Deuda Recibida de Unidades de negocio | F39: Financiamiento | G39: Externo
A40: Carmen Cross Irrevocable Trust | B40: Amerant Bank - Carmen Cross Irrevocable Trust - 3406-USD | C40: Amerant Bank | E40: Ing.Deuda Recibida de Empresas relacionadas | F40: Financiamiento | G40: Interno
A41: SIYP LLC | B41: Amerant Bank - SIYP LLC - 7820-USD | C41: Amerant Bank | E41: Ing.Deuda Recibida de Terceros | F41: Financiamiento | G41: Externo
A42: Prendamas SRL | B42: Amerant Bank - Prendamas SRL - 8160-USD | C42: Amerant Bank | E42: Ing.Recibe Aporte de Capital de Empresas relacionadas | F42: Inversion | G42: Interno
... A48: Don Cross Life | B48: Bank of America - Don Cross Life Trust - 9372-USD | C48: Bank of America | E48: Ing.Devolucion de Aporte de Capital | F48: Inversion | G48: Interno
E49: Ing.Interes bancario | F49: Operativo | G49: Externo
E50: Ing.Transferencias entre cuentas (Misma entidad legal) | F50: Operativo | G50: Interno
E51: Ing.Otros Ingresos Inversion | F51: Inversion | G51: Externo
E52: Ing.Otros Ingresos Operativos | F52: Operativo | G52: Externo

Sheet Cuentas
A1: Grupo | B1: Subsidiaria | C1: Cuenta bancaria
A2: SSP Group | C2: Bank of America - CFT Group - 4415-USD
A3: SSP Group | C3: Amerant Bank - CFT Group - 1906-USD
A4: SSP Group | C4: Northern Trust - CFT Group - 1355-USD
A5: SSP Group | C5: Amerant Bank - M1B - 0906-USD
A6: SSP Group | C6: Amerant Bank DACA - M1B - 8231-USD
A7: SSP Group | C7: Amerant Bank - Durand - 0106-USD
A8: SSP Group | C8: Bank of America - A&M Imports - 3797-USD
A9: SSP Group | C9: Bank of America - SSP Capital - 2580-USD
A10: SSP Group | C10: Bank of America - SSP Capital - 1655-USD
A11: SSP Group | C11: Amerant Bank - SSP Capital - 4706-USD
A12: SSP Group | C12: Northern Trust - SSP Capital - 1452-USD
A13: SSP Group | C13: Amerant Bank Money Market - SSP Capital - 1006-USD
... A44: Unidades de Negocio | C44: Amerant Bank - Prendamas SRL - 8160-USD
B45: Trust | C45: Bank of America - Cross Family Trust - 3124-USD
B46: Trust | C46: Northern Trust - Cross Family Trust - 9263-USD
B47: Trust | C47: Ocean Bank - Cross Family Trust - 3405-USD
B48: Trust | C48: Amerant Bank - Cross Family Trust - 4706-USD
B49: Trust | C49: Bank of America - Cross Security Trust - 6642-USD
B50: Trust | C50: Amerant Bank - Carmen Cross Irrevocable Trust - 3406-USD
B51: Trust | C51: Bank of America - Green Stone Trust - 3632-USD
B52: Trust | C52: Amerant Bank - Green Harbor Trust - 7253-USD
B53: Trust | C53: Bank of America - Don Cross Life Trust - 9372-USD

Sheet Movimientos
A1: ID | B1: Fecha | C1: Empresa | D1: Cuenta Bancaria | E1: Banco | F1: Tipo de Movimiento | G1: Categoria / Concepto | H1: Descripcion | I1: Ext/Int | J1: Monto (S/) | K1: Monto con signo | L1: Mes/Año | M1: Saldo del dia (acumulado) | N1: Ingreso | O1: Egreso | P1: Variación | Q1: Grupo | R1: Subsidiaria
B2: 46143 | C2: =_xlfn.XLOOKUP(tblMovimientos[[#This Row],[Cuenta Bancaria]],Listas!$B:$B,Listas!$A:$A,"") -> A&M Imports | D2: Bank of America - A&M Imports - 3797-USD | E2: =_xlfn.XLOOKUP(tblMovimientos[[#This Row],[Cuenta Bancaria]],Listas!$B:$B,Listas!$C:$C,"") -> Bank of America | F2: Ingreso | G2: Ing.Exportacion de oro de Unidad de Negocio | H2: =IFERROR(_xlfn.XLOOKUP(G2,Listas!E:E,Listas!F:F,""),"") -> Operativo | I2: Externo | J2: 400000 | K2: =IF(F2="Ingreso",J2,-J2) -> 400000 | L2: 2026-05 | M2: =SUMIFS('Saldos Iniciales'!$D:$D,'Saldos Iniciales'!$A:$A,C2,'Saldos Iniciales'!$B:$B,D2)+SUMIFS($K$1:$K$1324,$C$1:$C$1324,C2,$D$1:$D$1324,D2,$B$1:$B$1324,"<="&B2) -> 589990.3 | N2: =IF(tblMovimientos[[#This Row],[Tipo de Movimiento]]="Ingreso",tblMovimientos[[#This Row],[Monto (S/)]],"0") -> 400000 | O2: =IF(tblMovimientos[[#This Row],[Tipo de Movimiento]]="Egreso",tblMovimientos[[#This Row],[Monto (S/)]],"0") -> 0 | P2: =IF(tblMovimientos[[#This Row],[Tipo de Movimiento]]="Ingreso",tblMovimientos[[#This Row],[Ingreso]],-tblMovimientos[[#This Row],[Egreso]]) -> 400000 | Q2: =_xlfn.XLOOKUP(tblMovimientos[[#This Row],[Cuenta Bancaria]],Cuentas!$C:$C,Cuentas!$A:$A,"")&"" -> SSP Group | R2: =_xlfn.XLOOKUP(tblMovimientos[[#This Row],[Cuenta Bancaria]],Cuentas!$C:$C,Cuentas!$B:$B,"",0,-1)&""
B3: 46143 | C3: =_xlfn.XLOOKUP(tblMovimientos[[#This Row],[Cuenta Bancaria]],Listas!$B:$B,Listas!$A:$A,"") -> A&M Imports | D3: Bank of America - A&M Imports - 3797-USD | E3: =_xlfn.XLOOKUP(tblMovimientos[[#This Row],[Cuenta Bancaria]],Listas!$B:$B,Listas!$C:$C,"") -> Bank of America | F3: Ingreso | G3: Ing.Intereses Recibidos de Unidad de Negocio | H3: =IFERROR(_xlfn.XLOOKUP(G3,Listas!E:E,Listas!F:F,""),"") -> Operativo | I3: Externo | J3: 12901.71 | K3: =IF(F3="Ingreso",J3,-J3) -> 12901.71 | L3: 2026-05 | M3: =SUMIFS('Saldos Iniciales'!$D:$D,'Saldos Iniciales'!$A:$A,C3,'Saldos Iniciales'!$B:$B,D3)+SUMIFS($K$1:$K$1324,$C$1:$C$1324,C3,$D$1:$D$1324,D3,$B$1:$B$1324,"<="&B3) -> 589990.3 | N3: =IF(tblMovimientos[[#This Row],[Tipo de Movimiento]]="Ingreso",tblMovimientos[[#This Row],[Monto (S/)]],"0") -> 12901.71 | O3: =IF(tblMovimientos[[#This Row],[Tipo de Movimiento]]="Egreso",tblMovimientos[[#This Row],[Monto (S/)]],"0") -> 0 | P3: =IF(tblMovimientos[[#This Row],[Tipo de Movimiento]]="Ingreso",tblMovimientos[[#This Row],[Ingreso]],-tblMovimientos[[#This Row],[Egreso]]) -> 12901.71 | Q3: =_xlfn.XLOOKUP(tblMovimientos[[#This Row],[Cuenta Bancaria]],Cuentas!$C:$C,Cuentas!$A:$A,"")&"" -> SSP Group | R3: =_xlfn.XLOOKUP(tblMovimientos[[#This Row],[Cuenta Bancaria]],Cuentas!$C:$C,Cuentas!$B:$B,"",0,-1)&""
B4: 46143 | C4: =_xlfn.XLOOKUP(tblMovimientos[[#This Row],[Cuenta Bancaria]],Listas!$B:$B,Listas!$A:$A,"") -> Sacred Valley Capital | D4: Bank of America - Sacred Valley Capital - 4376-USD | E4: =_xlfn.XLOOKUP(tblMovimientos[[#This Row],[Cuenta Bancaria]],Listas!$B:$B,Listas!$C:$C,"") -> Bank of America | F4: Egreso | G4: Eg.Gastos Bancarios | H4: =IFERROR(_xlfn.XLOOKUP(G4,Listas!E:E,Listas!F:F,""),"") -> Operativo | I4: =IFERROR(_xlfn.XLOOKUP(G4,Listas!E:E,Listas!G:G,""),"") -> Externo | J4: 29.95 | K4: =IF(F4="Ingreso",J4,-J4) -> -29.95 | L4: 2026-05 | M4: =SUMIFS('Saldos Iniciales'!$D:$D,'Saldos Iniciales'!$A:$A,C4,'Saldos Iniciales'!$B:$B,D4)+SUMIFS($K$1:$K$1324,$C$1:$C$1324,C4,$D$1:$D$1324,D4,$B$1:$B$1324,"<="&B4) -> 114.3 | N4: =IF(tblMovimientos[[#This Row],[Tipo de Movimiento]]="Ingreso",tblMovimientos[[#This Row],[Monto (S/)]],"0") -> 0 | O4: =IF(tblMovimientos[[#This Row],[Tipo de Movimiento]]="Egreso",tblMovimientos[[#This Row],[Monto (S/)]],"0") -> 29.95 | P4: =IF(tblMovimientos[[#This Row],[Tipo de Movimiento]]="Ingreso",tblMovimientos[[#This Row],[Ingreso]],-tblMovimientos[[#This Row],[Egreso]]) -> -29.95 | Q4: =_xlfn.XLOOKUP(tblMovimientos[[#This Row],[Cuenta Bancaria]],Cuentas!$C:$C,Cuentas!$A:$A,"")&"" -> SSP Group | R4: =_xlfn.XLOOKUP(tblMovimientos[[#This Row],[Cuenta Bancaria]],Cuentas!$C:$C,Cuentas!$B:$B,"",0,-1)&""
B5: 46143 | C5: =_xlfn.XLOOKUP(tblMovimientos[[#This Row],[Cuenta Bancaria]],Listas!$B:$B,Listas!$A:$A,"") -> YWC Capital | D5: Bank of America - YWC Capital - 0282-USD | E5: =_xlfn.XLOOKUP(tblMovimientos[[#This Row],[Cuenta Bancaria]],Listas!$B:$B,Listas!$C:$C,"") -> Bank of America | F5: Egreso | G5: Eg.Gastos Bancarios | H5: =IFERROR(_xlfn.XLOOKUP(G5,Listas!E:E,Listas!F:F,""),"") -> Operativo | I5: =IFERROR(_xlfn.XLOOKUP(G5,Listas!E:E,Listas!G:G,""),"") -> Externo | J5: 29.95 | K5: =IF(F5="Ingreso",J5,-J5) -> -29.95 | L5: 2026-05 | M5: =SUMIFS('Saldos Iniciales'!$D:$D,'Saldos Iniciales'!$A:$A,C5,'Saldos Iniciales'!$B:$B,D5)+SUMIFS($K$1:$K$1324,$C$1:$C$1324,C5,$D$1:$D$1324,D5,$B$1:$B$1324,"<="&B5) -> 2267.72 | N5: =IF(tblMovimientos[[#This Row],[Tipo de Movimiento]]="Ingreso",tblMovimientos[[#This Row],[Monto (S/)]],"0") -> 0 | O5: =IF(tblMovimientos[[#This Row],[Tipo de Movimiento]]="Egreso",tblMovimientos[[#This Row],[Monto (S/)]],"0") -> 29.95 | P5: =IF(tblMovimientos[[#This Row],[Tipo de Movimiento]]="Ingreso",tblMovimientos[[#This Row],[Ingreso]],-tblMovimientos[[#This Row],[Egreso]]) -> -29.95 | Q5: =_xlfn.XLOOKUP(tblMovimientos[[#This Row],[Cuenta Bancaria]],Cuentas!$C:$C,Cuentas!$A:$A,"")&"" -> SSP Group | R5: =_xlfn.XLOOKUP(tblMovimientos[[#This Row],[Cuenta Bancaria]],Cuentas!$C:$C,Cuentas!$B:$B,"",0,-1)&""
B6: 46143 | C6: =_xlfn.XLOOKUP(tblMovimientos[[#This Row],[Cuenta Bancaria]],Listas!$B:$B,Listas!$A:$A,"") -> Arbor Capital Properties | D6: Bank of America - Arbor Capital Properties - 3262-USD | E6: =_xlfn.XLOOKUP(tblMovimientos[[#This Row],[Cuenta Bancaria]],Listas!$B:$B,Listas!$C:$C,"") -> Bank of America | F6: Egreso | G6: Eg.Gastos Bancarios | H6: =IFERROR(_xlfn.XLOOKUP(G6,Listas!E:E,Listas!F:F,""),"") -> Operativo | I6: =IFERROR(_xlfn.XLOOKUP(G6,Listas!E:E,Listas!G:G,""),"") -> Externo | J6: 16 | K6: =IF(F6="Ingreso",J6,-J6) -> -16 | L6: 2026-05 | M6: =SUMIFS('Saldos Iniciales'!$D:$D,'Saldos Iniciales'!$A:$A,C6,'Saldos Iniciales'!$B:$B,D6)+SUMIFS($K$1:$K$1324,$C$1:$C$1324,C6,$D$1:$D$1324,D6,$B$1:$B$1324,"<="&B6) -> 1444.08 | N6: =IF(tblMovimientos[[#This Row],[Tipo de Movimiento]]="Ingreso",tblMovimientos[[#This Row],[Monto (S/)]],"0") -> 0 | O6: =IF(tblMovimientos[[#This Row],[Tipo de Movimiento]]="Egreso",tblMovimientos[[#This Row],[Monto (S/)]],"0") -> 16 | P6: =IF(tblMovimientos[[#This Row],[Tipo de Movimiento]]="Ingreso",tblMovimientos[[#This Row],[Ingreso]],-tblMovimientos[[#This Row],[Egreso]]) -> -16 | Q6: =_xlfn.XLOOKUP(tblMovimientos[[#This Row],[Cuenta Bancaria]],Cuentas!$C:$C,Cuentas!$A:$A,"")&"" -> SSP Group | R6: =_xlfn.XLOOKUP(tblMovimientos[[#This Row],[Cuenta Bancaria]],Cuentas!$C:$C,Cuentas!$B:$B,"",0,-1)&""
B7: 46143 | C7: =_xlfn.XLOOKUP(tblMovimientos[[#This Row],[Cuenta Bancaria]],Listas!$B:$B,Listas!$A:$A,"") -> 2515 Overbrook | D7: Bank of America - 2515 Overbrook - 4648-USD | E7: =_xlfn.XLOOKUP(tblMovimientos[[#This Row],[Cuenta Bancaria]],Listas!$B:$B,Listas!$C:$C,"") -> Bank of America | F7: Ingreso | G7: Ing.Cobro de Renta (Real State) | H7: =IFERROR(_xlfn.XLOOKUP(G7,Listas!E:E,Listas!F:F,""),"") -> Operativo | I7: =IFERROR(_xlfn.XLOOKUP(G7,Listas!E:E,Listas!G:G,""),"") -> Externo | J7: 5250 | K7: =IF(F7="Ingreso",J7,-J7) -> 5250 | L7: 2026-05 | M7: =SUMIFS('Saldos Iniciales'!$D:$D,'Saldos Iniciales'!$A:$A,C7,'Saldos Iniciales'!$B:$B,D7)+SUMIFS($K$1:$K$1324,$C$1:$C$1324,C7,$D$1:$D$1324,D7,$B$1:$B$1324,"<="&B7) -> 22922.18 | N7: =IF(tblMovimientos[[#This Row],[Tipo de Movimiento]]="Ingreso",tblMovimientos[[#This Row],[Monto (S/)]],"0") -> 5250 | O7: =IF(tblMovimientos[[#This Row],[Tipo de Movimiento]]="Egreso",tblMovimientos[[#This Row],[Monto (S/)]],"0") -> 0 | P7: =IF(tblMovimientos[[#This Row],[Tipo de Movimiento]]="Ingreso",tblMovimientos[[#This Row],[Ingreso]],-tblMovimientos[[#This Row],[Egreso]]) -> 5250 | Q7: =_xlfn.XLOOKUP(tblMovimientos[[#This Row],[Cuenta Bancaria]],Cuentas!$C:$C,Cuentas!$A:$A,"")&"" -> SSP Group | R7: =_xlfn.XLOOKUP(tblMovimientos[[#This Row],[Cuenta Bancaria]],Cuentas!$C:$C,Cuentas!$B:$B,"",0,-1)&""
B8: 46143 | C8: =_xlfn.XLOOKUP(tblMovimientos[[#This Row],[Cuenta Bancaria]],Listas!$B:$B,Listas!$A:$A,"") -> 2515 Overbrook | D8: Bank of America - 2515 Overbrook - 4648-USD | E8: =_xlfn.XLOOKUP(tblMovimientos[[#This Row],[Cuenta Bancaria]],Listas!$B:$B,Listas!$C:$C,"") -> Bank of America | F8: Egreso | G8: Eg.Deuda Terceros (Intereses+Capital) | H8: =IFERROR(_xlfn.XLOOKUP(G8,Listas!E:E,Listas!F:F,""),"") -> Financiamiento | I8: =IFERROR(_xlfn.XLOOKUP(G8,Listas!E:E,Listas!G:G,""),"") -> Externo | J8: 8578.33 | K8: =IF(F8="Ingreso",J8,-J8) -> -8578.33 | L8: 2026-05 | M8: =SUMIFS('Saldos Iniciales'!$D:$D,'Saldos Iniciales'!$A:$A,C8,'Saldos Iniciales'!$B:$B,D8)+SUMIFS($K$1:$K$1324,$C$1:$C$1324,C8,$D$1:$D$1324,D8,$B$1:$B$1324,"<="&B8) -> 22922.18 | N8: =IF(tblMovimientos[[#This Row],[Tipo de Movimiento]]="Ingreso",tblMovimientos[[#This Row],[Monto (S/)]],"0") -> 0 | O8: =IF(tblMovimientos[[#This Row],[Tipo de Movimiento]]="Egreso",tblMovimientos[[#This Row],[Monto (S/)]],"0") -> 8578.33 | P8: =IF(tblMovimientos[[#This Row],[Tipo de Movimiento]]="Ingreso",tblMovimientos[[#This Row],[Ingreso]],-tblMovimientos[[#This Row],[Egreso]]) -> -8578.33 | Q8: =_xlfn.XLOOKUP(tblMovimientos[[#This Row],[Cuenta Bancaria]],Cuentas!$C:$C,Cuentas!$A:$A,"")&"" -> SSP Group | R8: =_xlfn.XLOOKUP(tblMovimientos[[#This Row],[Cuenta Bancaria]],Cuentas!$C:$C,Cuentas!$B:$B,"",0,-1)&""
B9: 46143 | C9: =_xlfn.XLOOKUP(tblMovimientos[[#This Row],[Cuenta Bancaria]],Listas!$B:$B,Listas!$A:$A,"") -> 2515 Overbrook | D9: Bank of America - 2515 Overbrook - 4648-USD | E9: =_xlfn.XLOOKUP(tblMovimientos[[#This Row],[Cuenta Bancaria]],Listas!$B:$B,Listas!$C:$C,"") -> Bank of America | F9: Egreso | G9: Eg.Gastos Bancarios | H9: =IFERROR(_xlfn.XLOOKUP(G9,Listas!E:E,Listas!F:F,""),"") -> Operativo | I9: =IFERROR(_xlfn.XLOOKUP(G9,Listas!E:E,Listas!G:G,""),"") -> Externo | J9: 16 | K9: =IF(F9="Ingreso",J9,-J9) -> -16 | L9: 2026-05 | M9: =SUMIFS('Saldos Iniciales'!$D:$D,'Saldos Iniciales'!$A:$A,C9,'Saldos Iniciales'!$B:$B,D9)+SUMIFS($K$1:$K$1324,$C$1:$C$1324,C9,$D$1:$D$1324,D9,$B$1:$B$1324,"<="&B9) -> 22922.18 | N9: =IF(tblMovimientos[[#This Row],[Tipo de Movimiento]]="Ingreso",tblMovimientos[[#This Row],[Monto (S/)]],"0") -> 0 | O9: =IF(tblMovimientos[[#This Row],[Tipo de Movimiento]]="Egreso",tblMovimientos[[#This Row],[Monto (S/)]],"0") -> 16 | P9: =IF(tblMovimientos[[#This Row],[Tipo de Movimiento]]="Ingreso",tblMovimientos[[#This Row],[Ingreso]],-tblMovimientos[[#This Row],[Egreso]]) -> -16 | Q9: =_xlfn.XLOOKUP(tblMovimientos[[#This Row],[Cuenta Bancaria]],Cuentas!$C:$C,Cuentas!$A:$A,"")&"" -> SSP Group | R9: =_xlfn.XLOOKUP(tblMovimientos[[#This Row],[Cuenta Bancaria]],Cuentas!$C:$C,Cuentas!$B:$B,"",0,-1)&""
B10: 46143 | C10: =_xlfn.XLOOKUP(tblMovimientos[[#This Row],[Cuenta Bancaria]],Listas!$B:$B,Listas!$A:$A,"") -> 2515 Overbrook | D10: Bank of America - 2515 Overbrook - 9923-USD | E10: =_xlfn.XLOOKUP(tblMovimientos[[#This Row],[Cuenta Bancaria]],Listas!$B:$B,Listas!$C:$C,"") -> Bank of America | F10: Egreso | G10: Eg.Gastos Bancarios | H10: =IFERROR(_xlfn.XLOOKUP(G10,Listas!E:E,Listas!F:F,""),"") -> Operativo | I10: =IFERROR(_xlfn.XLOOKUP(G10,Listas!E:E,Listas!G:G,""),"") -> Externo | J10: 10 | K10: =IF(F10="Ingreso",J10,-J10) -> -10 | L10: 2026-05 | M10: =SUMIFS('Saldos Iniciales'!$D:$D,'Saldos Iniciales'!$A:$A,C10,'Saldos Iniciales'!$B:$B,D10)+SUMIFS($K$1:$K$1324,$C$1:$C$1324,C10,$D$1:$D$1324,D10,$B$1:$B$1324,"<="&B10) -> 340.42 | N10: =IF(tblMovimientos[[#This Row],[Tipo de Movimiento]]="Ingreso",tblMovimientos[[#This Row],[Monto (S/)]],"0") -> 0 | O10: =IF(tblMovimientos[[#This Row],[Tipo de Movimiento]]="Egreso",tblMovimientos[[#This Row],[Monto (S/)]],"0") -> 10 | P10: =IF(tblMovimientos[[#This Row],[Tipo de Movimiento]]="Ingreso",tblMovimientos[[#This Row],[Ingreso]],-tblMovimientos[[#This Row],[Egreso]]) -> -10 | Q10: =_xlfn.XLOOKUP(tblMovimientos[[#This Row],[Cuenta Bancaria]],Cuentas!$C:$C,Cuentas!$A:$A,"")&"" -> SSP Group | R10: =_xlfn.XLOOKUP(tblMovimientos[[#This Row],[Cuenta Bancaria]],Cuentas!$C:$C,Cuentas!$B:$B,"",0,-1)&""
B11: 46143 | C11: =_xlfn.XLOOKUP(tblMovimientos[[#This Row],[Cuenta Bancaria]],Listas!$B:$B,Listas!$A:$A,"") -> 112 Florida Ave | D11: Bank of America - 112 Florida Ave - 3259-USD | E11: =_xlfn.XLOOKUP(tblMovimientos[[#This Row],[Cuenta Bancaria]],Listas!$B:$B,Listas!$C:$C,"") -> Bank of America | F11: Ingreso | G11: Ing.Cobro de Renta (Real State) | H11: =IFERROR(_xlfn.XLOOKUP(G11,Listas!E:E,Listas!F:F,""),"") -> Operativo | I11: =IFERROR(_xlfn.XLOOKUP(G11,Listas!E:E,Listas!G:G,""),"") -> Externo | J11: 6750 | K11: =IF(F11="Ingreso",J11,-J11) -> 6750 | L11: 2026-05 | M11: =SUMIFS('Saldos Iniciales'!$D:$D,'Saldos Iniciales'!$A:$A,C11,'Saldos Iniciales'!$B:$B,D11)+SUMIFS($K$1:$K$1324,$C$1:$C$1324,C11,$D$1:$D$1324,D11,$B$1:$B$1324,"<="&B11) -> 6853.91 | N11: =IF(tblMovimientos[[#This Row],[Tipo de Movimiento]]="Ingreso",tblMovimientos[[#This Row],[Monto (S/)]],"0") -> 6750 | O11: =IF(tblMovimientos[[#This Row],[Tipo de Movimiento]]="Egreso",tblMovimientos[[#This Row],[Monto (S/)]],"0") -> 0 | P11: =IF(tblMovimientos[[#This Row],[Tipo de Movimiento]]="Ingreso",tblMovimientos[[#This Row],[Ingreso]],-tblMovimientos[[#This Row],[Egreso]]) -> 6750 | Q11: =_xlfn.XLOOKUP(tblMovimientos[[#This Row],[Cuenta Bancaria]],Cuentas!$C:$C,Cuentas!$A:$A,"")&"" -> SSP Group | R11: =_xlfn.XLOOKUP(tblMovimientos[[#This Row],[Cuenta Bancaria]],Cuentas!$C:$C,Cuentas!$B:$B,"",0,-1)&""
B12: 46143 | C12: =_xlfn.XLOOKUP(tblMovimientos[[#This Row],[Cuenta Bancaria]],Listas!$B:$B,Listas!$A:$A,"") -> 112 Florida Ave | D12: Bank of America - 112 Florida Ave - 3259-USD | E12: =_xlfn.XLOOKUP(tblMovimientos[[#This Row],[Cuenta Bancaria]],Listas!$B:$B,Listas!$C:$C,"") -> Bank of America | F12: Egreso | G12: Eg.Deuda Terceros (Intereses+Capital) | H12: =IFERROR(_xlfn.XLOOKUP(G12,Listas!E:E,Listas!F:F,""),"") -> Financiamiento | I12: =IFERROR(_xlfn.XLOOKUP(G12,Listas!E:E,Listas!G:G,""),"") -> Externo | J12: 9798.63 | K12: =IF(F12="Ingreso",J12,-J12) -> -9798.63 | L12: 2026-05 | M12: =SUMIFS('Saldos Iniciales'!$D:$D,'Saldos Iniciales'!$A:$A,C12,'Saldos Iniciales'!$B:$B,D12)+SUMIFS($K$1:$K$1324,$C$1:$C$1324,C12,$D$1:$D$1324,D12,$B$1:$B$1324,"<="&B12) -> 6853.91 | N12: =IF(tblMovimientos[[#This Row],[Tipo de Movimiento]]="Ingreso",tblMovimientos[[#This Row],[Monto (S/)]],"0") -> 0 | O12: =IF(tblMovimientos[[#This Row],[Tipo de Movimiento]]="Egreso",tblMovimientos[[#This Row],[Monto (S/)]],"0") -> 9798.63 | P12: =IF(tblMovimientos[[#This Row],[Tipo de Movimiento]]="Ingreso",tblMovimientos[[#This Row],[Ingreso]],-tblMovimientos[[#This Row],[Egreso]]) -> -9798.63 | Q12: =_xlfn.XLOOKUP(tblMovimientos[[#This Row],[Cuenta Bancaria]],Cuentas!$C:$C,Cuentas!$A:$A,"")&"" -> SSP Group | R12: =_xlfn.XLOOKUP(tblMovimientos[[#This Row],[Cuenta Bancaria]],Cuentas!$C:$C,Cuentas!$B:$B,"",0,-1)&""
B13: 46143 | C13: =_xlfn.XLOOKUP(tblMovimientos[[#This Row],[Cuenta Bancaria]],Listas!$B:$B,Listas!$A:$A,"") -> 3628 Thomas Ave | D13: Bank of America - 3628 Thomas Ave - 4406-USD | E13: =_xlfn.XLOOKUP(tblMovimientos[[#This Row],[Cuenta Bancaria]],Listas!$B:$B,Listas!$C:$C,"") -> Bank of America | F13: Ingreso | G13: Ing.Cobro de Renta (Real State) | H13: =IFERROR(_xlfn.XLOOKUP(G13,Listas!E:E,Listas!F:F,""),"") -> Operativo | I13: =IFERROR(_xlfn.XLOOKUP(G13,Listas!E:E,Listas!G:G,""),"") -> Externo | J13: 5050 | K13: =IF(F13="Ingreso",J13,-J13) -> 5050 | L13: 2026-05 | M13: =SUMIFS('Saldos Iniciales'!$D:$D,'Saldos Iniciales'!$A:$A,C13,'Saldos Iniciales'!$B:$B,D13)+SUMIFS($K$1:$K$1324,$C$1:$C$1324,C13,$D$1:$D$1324,D13,$B$1:$B$1324,"<="&B13) -> 21338.39 | N13: =IF(tblMovimientos[[#This Row],[Tipo de Movimiento]]="Ingreso",tblMovimientos[[#This Row],[Monto (S/)]],"0") -> 5050 | O13: =IF(tblMovimientos[[#This Row],[Tipo de Movimiento]]="Egreso",tblMovimientos[[#This Row],[Monto (S/)]],"0") -> 0 | P13: =IF(tblMovimientos[[#This Row],[Tipo de Movimiento]]="Ingreso",tblMovimientos[[#This Row],[Ingreso]],-tblMovimientos[[#This Row],[Egreso]]) -> 5050 | Q13: =_xlfn.XLOOKUP(tblMovimientos[[#This Row],[Cuenta Bancaria]],Cuentas!$C:$C,Cuentas!$A:$A,"")&"" -> SSP Group | R13: =_xlfn.XLOOKUP(tblMovimientos[[#This Row],[Cuenta Bancaria]],Cuentas!$C:$C,Cuentas!$B:$B,"",0,-1)&""
B14: 46143 | C14: =_xlfn.XLOOKUP(tblMovimientos[[#This Row],[Cuenta Bancaria]],Listas!$B:$B,Listas!$A:$A,"") -> 3628 Thomas Ave | D14: Bank of America - 3628 Thomas Ave - 4406-USD | E14: =_xlfn.XLOOKUP(tblMovimientos[[#This Row],[Cuenta Bancaria]],Listas!$B:$B,Listas!$C:$C,"") -> Bank of America | F14: Egreso | G14: Eg.Deuda Terceros (Intereses+Capital) | H14: =IFERROR(_xlfn.XLOOKUP(G14,Listas!E:E,Listas!F:F,""),"") -> Financiamiento | I14: =IFERROR(_xlfn.XLOOKUP(G14,Listas!E:E,Listas!G:G,""),"") -> Externo | J14: 8773.04 | K14: =IF(F14="Ingreso",J14,-J14) -> -8773.04 | L14: 2026-05 | M14: =SUMIFS('Saldos Iniciales'!$D:$D,'Saldos Iniciales'!$A:$A,C14,'Saldos Iniciales'!$B:$B,D14)+SUMIFS($K$1:$K$1324,$C$1:$C$1324,C14,$D$1:$D$1324,D14,$B$1:$B$1324,"<="&B14) -> 21338.39 | N14: =IF(tblMovimientos[[#This Row],[Tipo de Movimiento]]="Ingreso",tblMovimientos[[#This Row],[Monto (S/)]],"0") -> 0 | O14: =IF(tblMovimientos[[#This Row],[Tipo de Movimiento]]="Egreso",tblMovimientos[[#This Row],[Monto (S/)]],"0") -> 8773.04 | P14: =IF(tblMovimientos[[#This Row],[Tipo de Movimiento]]="Ingreso",tblMovimientos[[#This Row],[Ingreso]],-tblMovimientos[[#This Row],[Egreso]]) -> -8773.04 | Q14: =_xlfn.XLOOKUP(tblMovimientos[[#This Row],[Cuenta Bancaria]],Cuentas!$C:$C,Cuentas!$A:$A,"")&"" -> SSP Group | R14: =_xlfn.XLOOKUP(tblMovimientos[[#This Row],[Cuenta Bancaria]],Cuentas!$C:$C,Cuentas!$B:$B,"",0,-1)&""
B15: 46143 | C15: =_xlfn.XLOOKUP(tblMovimientos[[#This Row],[Cuenta Bancaria]],Listas!$B:$B,Listas!$A:$A,"") -> M1B | D15: Amerant Bank - M1B - 0906-USD | E15: =_xlfn.XLOOKUP(tblMovimientos[[#This Row],[Cuenta Bancaria]],Listas!$B:$B,Listas!$C:$C,"") -> Amerant Bank | F15: Ingreso | G15: Ing.Intereses Recibidos de Unidad de Negocio | H15: =IFERROR(_xlfn.XLOOKUP(G15,Listas!E:E,Listas!F:F,""),"") -> Operativo | I15: =IFERROR(_xlfn.XLOOKUP(G15,Listas!E:E,Listas!G:G,""),"") -> Externo | J15: 6748.49 | K15: =IF(F15="Ingreso",J15,-J15) -> 6748.49 | L15: 2026-05 | M15: =SUMIFS('Saldos Iniciales'!$D:$D,'Saldos Iniciales'!$A:$A,C15,'Saldos Iniciales'!$B:$B,D15)+SUMIFS($K$1:$K$1324,$C$1:$C$1324,C15,$D$1:$D$1324,D15,$B$1:$B$1324,"<="&B15) -> 46288.03 | N15: =IF(tblMovimientos[[#This Row],[Tipo de Movimiento]]="Ingreso",tblMovimientos[[#This Row],[Monto (S/)]],"0") -> 6748.49 | O15: =IF(tblMovimientos[[#This Row],[Tipo de Movimiento]]="Egreso",tblMovimientos[[#This Row],[Monto (S/)]],"0") -> 0 | P15: =IF(tblMovimientos[[#This Row],[Tipo de Movimiento]]="Ingreso",tblMovimientos[[#This Row],[Ingreso]],-tblMovimientos[[#This Row],[Egreso]]) -> 6748.49 | Q15: =_xlfn.XLOOKUP(tblMovimientos[[#This Row],[Cuenta Bancaria]],Cuentas!$C:$C,Cuentas!$A:$A,"")&"" -> SSP Group | R15: =_xlfn.XLOOKUP(tblMovimientos[[#This Row],[Cuenta Bancaria]],Cuentas!$C:$C,Cuentas!$B:$B,"",0,-1)&""
... B238: 46174 | C238: =_xlfn.XLOOKUP(tblMovimientos[[#This Row],[Cuenta Bancaria]],Listas!$B:$B,Listas!$A:$A,"") -> Durand | D238: Amerant Bank - Durand - 0106-USD | E238: =_xlfn.XLOOKUP(tblMovimientos[[#This Row],[Cuenta Bancaria]],Listas!$B:$B,Listas!$C:$C,"") -> Amerant Bank | F238: Egreso | G238: Eg.Gastos Bancarios | H238: =IFERROR(_xlfn.XLOOKUP(G238,Listas!E:E,Listas!F:F,""),"") -> Operativo | I238: =IFERROR(_xlfn.XLOOKUP(G238,Listas!E:E,Listas!G:G,""),"") -> Externo | J238: 0 | K238: =IF(F238="Ingreso",J238,-J238) -> 0 | L238: 2026-06 | M238: =SUMIFS('Saldos Iniciales'!$D:$D,'Saldos Iniciales'!$A:$A,C238,'Saldos Iniciales'!$B:$B,D238)+SUMIFS($K$1:$K$1324,$C$1:$C$1324,C238,$D$1:$D$1324,D238,$B$1:$B$1324,"<="&B238) -> 1669.89 | N238: =IF(tblMovimientos[[#This Row],[Tipo de Movimiento]]="Ingreso",tblMovimientos[[#This Row],[Monto (S/)]],"0") -> 0 | O238: =IF(tblMovimientos[[#This Row],[Tipo de Movimiento]]="Egreso",tblMovimientos[[#This Row],[Monto (S/)]],"0") -> 0 | P238: =IF(tblMovimientos[[#This Row],[Tipo de Movimiento]]="Ingreso",tblMovimientos[[#This Row],[Ingreso]],-tblMovimientos[[#This Row],[Egreso]]) -> 0 | Q238: =_xlfn.XLOOKUP(tblMovimientos[[#This Row],[Cuenta Bancaria]],Cuentas!$C:$C,Cuentas!$A:$A,"")&"" -> SSP Group | R238: =_xlfn.XLOOKUP(tblMovimientos[[#This Row],[Cuenta Bancaria]],Cuentas!$C:$C,Cuentas!$B:$B,"",0,-1)&""
B239: 46174 | C239: =_xlfn.XLOOKUP(tblMovimientos[[#This Row],[Cuenta Bancaria]],Listas!$B:$B,Listas!$A:$A,"") -> Green Stone Trust | D239: Bank of America - Green Stone Trust - 3632-USD | E239: =_xlfn.XLOOKUP(tblMovimientos[[#This Row],[Cuenta Bancaria]],Listas!$B:$B,Listas!$C:$C,"") -> Bank of America | F239: Egreso | G239: Eg.Gastos Bancarios | H239: =IFERROR(_xlfn.XLOOKUP(G239,Listas!E:E,Listas!F:F,""),"") -> Operativo | I239: =IFERROR(_xlfn.XLOOKUP(G239,Listas!E:E,Listas!G:G,""),"") -> Externo | K239: =IF(F239="Ingreso",J239,-J239) -> 0 | L239: 2026-06 | M239: =SUMIFS('Saldos Iniciales'!$D:$D,'Saldos Iniciales'!$A:$A,C239,'Saldos Iniciales'!$B:$B,D239)+SUMIFS($K$1:$K$1324,$C$1:$C$1324,C239,$D$1:$D$1324,D239,$B$1:$B$1324,"<="&B239) -> 1968.99 | N239: =IF(tblMovimientos[[#This Row],[Tipo de Movimiento]]="Ingreso",tblMovimientos[[#This Row],[Monto (S/)]],"0") -> 0 | O239: =IF(tblMovimientos[[#This Row],[Tipo de Movimiento]]="Egreso",tblMovimientos[[#This Row],[Monto (S/)]],"0") -> 0 | P239: =IF(tblMovimientos[[#This Row],[Tipo de Movimiento]]="Ingreso",tblMovimientos[[#This Row],[Ingreso]],-tblMovimientos[[#This Row],[Egreso]]) -> 0 | Q239: =_xlfn.XLOOKUP(tblMovimientos[[#This Row],[Cuenta Bancaria]],Cuentas!$C:$C,Cuentas!$A:$A,"")&"" -> SSP Group | R239: =_xlfn.XLOOKUP(tblMovimientos[[#This Row],[Cuenta Bancaria]],Cuentas!$C:$C,Cuentas!$B:$B,"",0,-1)&"" -> Trust
B240: 46174 | C240: =_xlfn.XLOOKUP(tblMovimientos[[#This Row],[Cuenta Bancaria]],Listas!$B:$B,Listas!$A:$A,"") -> Cross Security Trust | D240: Bank of America - Cross Security Trust - 6642-USD | E240: =_xlfn.XLOOKUP(tblMovimientos[[#This Row],[Cuenta Bancaria]],Listas!$B:$B,Listas!$C:$C,"") -> Bank of America | F240: Egreso | G240: Eg.Gastos Operativos (Proveedor) | H240: =IFERROR(_xlfn.XLOOKUP(G240,Listas!E:E,Listas!F:F,""),"") -> Operativo | I240: =IFERROR(_xlfn.XLOOKUP(G240,Listas!E:E,Listas!G:G,""),"") -> Externo | J240: 13270 | K240: =IF(F240="Ingreso",J240,-J240) -> -13270 | L240: 2026-06 | M240: =SUMIFS('Saldos Iniciales'!$D:$D,'Saldos Iniciales'!$A:$A,C240,'Saldos Iniciales'!$B:$B,D240)+SUMIFS($K$1:$K$1324,$C$1:$C$1324,C240,$D$1:$D$1324,D240,$B$1:$B$1324,"<="&B240) -> 20375.37 | N240: =IF(tblMovimientos[[#This Row],[Tipo de Movimiento]]="Ingreso",tblMovimientos[[#This Row],[Monto (S/)]],"0") -> 0 | O240: =IF(tblMovimientos[[#This Row],[Tipo de Movimiento]]="Egreso",tblMovimientos[[#This Row],[Monto (S/)]],"0") -> 13270 | P240: =IF(tblMovimientos[[#This Row],[Tipo de Movimiento]]="Ingreso",tblMovimientos[[#This Row],[Ingreso]],-tblMovimientos[[#This Row],[Egreso]]) -> -13270 | Q240: =_xlfn.XLOOKUP(tblMovimientos[[#This Row],[Cuenta Bancaria]],Cuentas!$C:$C,Cuentas!$A:$A,"")&"" -> SSP Group | R240: =_xlfn.XLOOKUP(tblMovimientos[[#This Row],[Cuenta Bancaria]],Cuentas!$C:$C,Cuentas!$B:$B,"",0,-1)&"" -> Trust
B241: 46174 | C241: =_xlfn.XLOOKUP(tblMovimientos[[#This Row],[Cuenta Bancaria]],Listas!$B:$B,Listas!$A:$A,"") -> Cross Security Trust | D241: Bank of America - Cross Security Trust - 6642-USD | E241: =_xlfn.XLOOKUP(tblMovimientos[[#This Row],[Cuenta Bancaria]],Listas!$B:$B,Listas!$C:$C,"") -> Bank of America | F241: Egreso | G241: Eg.Gastos Operativos (Proveedor) | H241: =IFERROR(_xlfn.XLOOKUP(G241,Listas!E:E,Listas!F:F,""),"") -> Operativo | I241: =IFERROR(_xlfn.XLOOKUP(G241,Listas!E:E,Listas!G:G,""),"") -> Externo | J241: 54445 | K241: =IF(F241="Ingreso",J241,-J241) -> -54445 | L241: 2026-06 | M241: =SUMIFS('Saldos Iniciales'!$D:$D,'Saldos Iniciales'!$A:$A,C241,'Saldos Iniciales'!$B:$B,D241)+SUMIFS($K$1:$K$1324,$C$1:$C$1324,C241,$D$1:$D$1324,D241,$B$1:$B$1324,"<="&B241) -> 20375.37 | N241: =IF(tblMovimientos[[#This Row],[Tipo de Movimiento]]="Ingreso",tblMovimientos[[#This Row],[Monto (S/)]],"0") -> 0 | O241: =IF(tblMovimientos[[#This Row],[Tipo de Movimiento]]="Egreso",tblMovimientos[[#This Row],[Monto (S/)]],"0") -> 54445 | P241: =IF(tblMovimientos[[#This Row],[Tipo de Movimiento]]="Ingreso",tblMovimientos[[#This Row],[Ingreso]],-tblMovimientos[[#This Row],[Egreso]]) -> -54445 | Q241: =_xlfn.XLOOKUP(tblMovimientos[[#This Row],[Cuenta Bancaria]],Cuentas!$C:$C,Cuentas!$A:$A,"")&"" -> SSP Group | R241: =_xlfn.XLOOKUP(tblMovimientos[[#This Row],[Cuenta Bancaria]],Cuentas!$C:$C,Cuentas!$B:$B,"",0,-1)&"" -> Trust
B242: 46175 | C242: =_xlfn.XLOOKUP(tblMovimientos[[#This Row],[Cuenta Bancaria]],Listas!$B:$B,Listas!$A:$A,"") -> 2515 Overbrook | D242: Bank of America - 2515 Overbrook - 4648-USD | E242: =_xlfn.XLOOKUP(tblMovimientos[[#This Row],[Cuenta Bancaria]],Listas!$B:$B,Listas!$C:$C,"") -> Bank of America | F242: Egreso | G242: Eg.Gastos Operativos (Proveedor) | H242: =IFERROR(_xlfn.XLOOKUP(G242,Listas!E:E,Listas!F:F,""),"") -> Operativo | I242: =IFERROR(_xlfn.XLOOKUP(G242,Listas!E:E,Listas!G:G,""),"") -> Externo | J242: 626.3 | K242: =IF(F242="Ingreso",J242,-J242) -> -626.3 | L242: 2026-06 | M242: =SUMIFS('Saldos Iniciales'!$D:$D,'Saldos Iniciales'!$A:$A,C242,'Saldos Iniciales'!$B:$B,D242)+SUMIFS($K$1:$K$1324,$C$1:$C$1324,C242,$D$1:$D$1324,D242,$B$1:$B$1324,"<="&B242) -> 25459.55 | N242: =IF(tblMovimientos[[#This Row],[Tipo de Movimiento]]="Ingreso",tblMovimientos[[#This Row],[Monto (S/)]],"0") -> 0 | O242: =IF(tblMovimientos[[#This Row],[Tipo de Movimiento]]="Egreso",tblMovimientos[[#This Row],[Monto (S/)]],"0") -> 626.3 | P242: =IF(tblMovimientos[[#This Row],[Tipo de Movimiento]]="Ingreso",tblMovimientos[[#This Row],[Ingreso]],-tblMovimientos[[#This Row],[Egreso]]) -> -626.3 | Q242: =_xlfn.XLOOKUP(tblMovimientos[[#This Row],[Cuenta Bancaria]],Cuentas!$C:$C,Cuentas!$A:$A,"")&"" -> SSP Group | R242: =_xlfn.XLOOKUP(tblMovimientos[[#This Row],[Cuenta Bancaria]],Cuentas!$C:$C,Cuentas!$B:$B,"",0,-1)&""
B243: 46175 | C243: =_xlfn.XLOOKUP(tblMovimientos[[#This Row],[Cuenta Bancaria]],Listas!$B:$B,Listas!$A:$A,"") -> Go Blue | D243: Amerant Bank - Go Blue - 8206-USD | E243: =_xlfn.XLOOKUP(tblMovimientos[[#This Row],[Cuenta Bancaria]],Listas!$B:$B,Listas!$C:$C,"") -> Amerant Bank | F243: Egreso | G243: Eg.Gastos Operativos (Proveedor) | H243: =IFERROR(_xlfn.XLOOKUP(G243,Listas!E:E,Listas!F:F,""),"") -> Operativo | I243: =IFERROR(_xlfn.XLOOKUP(G243,Listas!E:E,Listas!G:G,""),"") -> Externo | J243: 3309.58 | K243: =IF(F243="Ingreso",J243,-J243) -> -3309.58 | L243: 2026-06 | M243: =SUMIFS('Saldos Iniciales'!$D:$D,'Saldos Iniciales'!$A:$A,C243,'Saldos Iniciales'!$B:$B,D243)+SUMIFS($K$1:$K$1324,$C$1:$C$1324,C243,$D$1:$D$1324,D243,$B$1:$B$1324,"<="&B243) -> 3514.89 | N243: =IF(tblMovimientos[[#This Row],[Tipo de Movimiento]]="Ingreso",tblMovimientos[[#This Row],[Monto (S/)]],"0") -> 0 | O243: =IF(tblMovimientos[[#This Row],[Tipo de Movimiento]]="Egreso",tblMovimientos[[#This Row],[Monto (S/)]],"0") -> 3309.58 | P243: =IF(tblMovimientos[[#This Row],[Tipo de Movimiento]]="Ingreso",tblMovimientos[[#This Row],[Ingreso]],-tblMovimientos[[#This Row],[Egreso]]) -> -3309.58 | Q243: =_xlfn.XLOOKUP(tblMovimientos[[#This Row],[Cuenta Bancaria]],Cuentas!$C:$C,Cuentas!$A:$A,"")&"" -> SSP Group | R243: =_xlfn.XLOOKUP(tblMovimientos[[#This Row],[Cuenta Bancaria]],Cuentas!$C:$C,Cuentas!$B:$B,"",0,-1)&""
B244: 46176 | C244: =_xlfn.XLOOKUP(tblMovimientos[[#This Row],[Cuenta Bancaria]],Listas!$B:$B,Listas!$A:$A,"") -> SSP Capital | D244: Bank of America - SSP Capital - 2580-USD | E244: =_xlfn.XLOOKUP(tblMovimientos[[#This Row],[Cuenta Bancaria]],Listas!$B:$B,Listas!$C:$C,"") -> Bank of America | F244: Egreso | G244: Eg.Gastos Operativos (Proveedor) | H244: =IFERROR(_xlfn.XLOOKUP(G244,Listas!E:E,Listas!F:F,""),"") -> Operativo | I244: =IFERROR(_xlfn.XLOOKUP(G244,Listas!E:E,Listas!G:G,""),"") -> Externo | J244: 290.01 | K244: =IF(F244="Ingreso",J244,-J244) -> -290.01 | L244: 2026-06 | M244: =SUMIFS('Saldos Iniciales'!$D:$D,'Saldos Iniciales'!$A:$A,C244,'Saldos Iniciales'!$B:$B,D244)+SUMIFS($K$1:$K$1324,$C$1:$C$1324,C244,$D$1:$D$1324,D244,$B$1:$B$1324,"<="&B244) -> 10553.2 | N244: =IF(tblMovimientos[[#This Row],[Tipo de Movimiento]]="Ingreso",tblMovimientos[[#This Row],[Monto (S/)]],"0") -> 0 | O244: =IF(tblMovimientos[[#This Row],[Tipo de Movimiento]]="Egreso",tblMovimientos[[#This Row],[Monto (S/)]],"0") -> 290.01 | P244: =IF(tblMovimientos[[#This Row],[Tipo de Movimiento]]="Ingreso",tblMovimientos[[#This Row],[Ingreso]],-tblMovimientos[[#This Row],[Egreso]]) -> -290.01 | Q244: =_xlfn.XLOOKUP(tblMovimientos[[#This Row],[Cuenta Bancaria]],Cuentas!$C:$C,Cuentas!$A:$A,"")&"" -> SSP Group | R244: =_xlfn.XLOOKUP(tblMovimientos[[#This Row],[Cuenta Bancaria]],Cuentas!$C:$C,Cuentas!$B:$B,"",0,-1)&""
B245: 46176 | C245: =_xlfn.XLOOKUP(tblMovimientos[[#This Row],[Cuenta Bancaria]],Listas!$B:$B,Listas!$A:$A,"") -> Cross Family Trust | D245: Bank of America - Cross Family Trust - 3124-USD | E245: =_xlfn.XLOOKUP(tblMovimientos[[#This Row],[Cuenta Bancaria]],Listas!$B:$B,Listas!$C:$C,"") -> Bank of America | F245: Egreso | G245: Eg.Gastos Operativos (Proveedor) | H245: =IFERROR(_xlfn.XLOOKUP(G245,Listas!E:E,Listas!F:F,""),"") -> Operativo | I245: =IFERROR(_xlfn.XLOOKUP(G245,Listas!E:E,Listas!G:G,""),"") -> Externo | J245: 6000 | K245: =IF(F245="Ingreso",J245,-J245) -> -6000 | L245: 2026-06 | M245: =SUMIFS('Saldos Iniciales'!$D:$D,'Saldos Iniciales'!$A:$A,C245,'Saldos Iniciales'!$B:$B,D245)+SUMIFS($K$1:$K$1324,$C$1:$C$1324,C245,$D$1:$D$1324,D245,$B$1:$B$1324,"<="&B245) -> 51206.89 | N245: =IF(tblMovimientos[[#This Row],[Tipo de Movimiento]]="Ingreso",tblMovimientos[[#This Row],[Monto (S/)]],"0") -> 0 | O245: =IF(tblMovimientos[[#This Row],[Tipo de Movimiento]]="Egreso",tblMovimientos[[#This Row],[Monto (S/)]],"0") -> 6000 | P245: =IF(tblMovimientos[[#This Row],[Tipo de Movimiento]]="Ingreso",tblMovimientos[[#This Row],[Ingreso]],-tblMovimientos[[#This Row],[Egreso]]) -> -6000 | Q245: =_xlfn.XLOOKUP(tblMovimientos[[#This Row],[Cuenta Bancaria]],Cuentas!$C:$C,Cuentas!$A:$A,"")&"" -> SSP Group | R245: =_xlfn.XLOOKUP(tblMovimientos[[#This Row],[Cuenta Bancaria]],Cuentas!$C:$C,Cuentas!$B:$B,"",0,-1)&"" -> Trust
B246: 46177 | C246: =_xlfn.XLOOKUP(tblMovimientos[[#This Row],[Cuenta Bancaria]],Listas!$B:$B,Listas!$A:$A,"") -> Go Blue | D246: Amerant Bank - Go Blue - 8206-USD | E246: =_xlfn.XLOOKUP(tblMovimientos[[#This Row],[Cuenta Bancaria]],Listas!$B:$B,Listas!$C:$C,"") -> Amerant Bank | F246: Egreso | G246: Eg.Gastos Bancarios | H246: =IFERROR(_xlfn.XLOOKUP(G246,Listas!E:E,Listas!F:F,""),"") -> Operativo | I246: =IFERROR(_xlfn.XLOOKUP(G246,Listas!E:E,Listas!G:G,""),"") -> Externo | J246: 15 | K246: =IF(F246="Ingreso",J246,-J246) -> -15 | L246: 2026-06 | M246: =SUMIFS('Saldos Iniciales'!$D:$D,'Saldos Iniciales'!$A:$A,C246,'Saldos Iniciales'!$B:$B,D246)+SUMIFS($K$1:$K$1324,$C$1:$C$1324,C246,$D$1:$D$1324,D246,$B$1:$B$1324,"<="&B246) -> 2422.74 | N246: =IF(tblMovimientos[[#This Row],[Tipo de Movimiento]]="Ingreso",tblMovimientos[[#This Row],[Monto (S/)]],"0") -> 0 | O246: =IF(tblMovimientos[[#This Row],[Tipo de Movimiento]]="Egreso",tblMovimientos[[#This Row],[Monto (S/)]],"0") -> 15 | P246: =IF(tblMovimientos[[#This Row],[Tipo de Movimiento]]="Ingreso",tblMovimientos[[#This Row],[Ingreso]],-tblMovimientos[[#This Row],[Egreso]]) -> -15 | Q246: =_xlfn.XLOOKUP(tblMovimientos[[#This Row],[Cuenta Bancaria]],Cuentas!$C:$C,Cuentas!$A:$A,"")&"" -> SSP Group | R246: =_xlfn.XLOOKUP(tblMovimientos[[#This Row],[Cuenta Bancaria]],Cuentas!$C:$C,Cuentas!$B:$B,"",0,-1)&""
B247: 46177 | C247: =_xlfn.XLOOKUP(tblMovimientos[[#This Row],[Cuenta Bancaria]],Listas!$B:$B,Listas!$A:$A,"") -> Go Blue | D247: Amerant Bank - Go Blue - 8206-USD | E247: =_xlfn.XLOOKUP(tblMovimientos[[#This Row],[Cuenta Bancaria]],Listas!$B:$B,Listas!$C:$C,"") -> Amerant Bank | F247: Egreso | G247: Eg.Gastos Bancarios | H247: =IFERROR(_xlfn.XLOOKUP(G247,Listas!E:E,Listas!F:F,""),"") -> Operativo | I247: =IFERROR(_xlfn.XLOOKUP(G247,Listas!E:E,Listas!G:G,""),"") -> Externo | J247: 15 | K247: =IF(F247="Ingreso",J247,-J247) -> -15 | L247: 2026-06 | M247: =SUMIFS('Saldos Iniciales'!$D:$D,'Saldos Iniciales'!$A:$A,C247,'Saldos Iniciales'!$B:$B,D247)+SUMIFS($K$1:$K$1324,$C$1:$C$1324,C247,$D$1:$D$1324,D247,$B$1:$B$1324,"<="&B247) -> 2422.74 | N247: =IF(tblMovimientos[[#This Row],[Tipo de Movimiento]]="Ingreso",tblMovimientos[[#This Row],[Monto (S/)]],"0") -> 0 | O247: =IF(tblMovimientos[[#This Row],[Tipo de Movimiento]]="Egreso",tblMovimientos[[#This Row],[Monto (S/)]],"0") -> 15 | P247: =IF(tblMovimientos[[#This Row],[Tipo de Movimiento]]="Ingreso",tblMovimientos[[#This Row],[Ingreso]],-tblMovimientos[[#This Row],[Egreso]]) -> -15 | Q247: =_xlfn.XLOOKUP(tblMovimientos[[#This Row],[Cuenta Bancaria]],Cuentas!$C:$C,Cuentas!$A:$A,"")&"" -> SSP Group | R247: =_xlfn.XLOOKUP(tblMovimientos[[#This Row],[Cuenta Bancaria]],Cuentas!$C:$C,Cuentas!$B:$B,"",0,-1)&""
B248: 46177 | C248: =_xlfn.XLOOKUP(tblMovimientos[[#This Row],[Cuenta Bancaria]],Listas!$B:$B,Listas!$A:$A,"") -> Go Blue | D248: Amerant Bank - Go Blue - 8206-USD | E248: =_xlfn.XLOOKUP(tblMovimientos[[#This Row],[Cuenta Bancaria]],Listas!$B:$B,Listas!$C:$C,"") -> Amerant Bank | F248: Egreso | G248: Eg.Gastos Bancarios | H248: =IFERROR(_xlfn.XLOOKUP(G248,Listas!E:E,Listas!F:F,""),"") -> Operativo | I248: =IFERROR(_xlfn.XLOOKUP(G248,Listas!E:E,Listas!G:G,""),"") -> Externo | J248: 15 | K248: =IF(F248="Ingreso",J248,-J248) -> -15 | L248: 2026-06 | M248: =SUMIFS('Saldos Iniciales'!$D:$D,'Saldos Iniciales'!$A:$A,C248,'Saldos Iniciales'!$B:$B,D248)+SUMIFS($K$1:$K$1324,$C$1:$C$1324,C248,$D$1:$D$1324,D248,$B$1:$B$1324,"<="&B248) -> 2422.74 | N248: =IF(tblMovimientos[[#This Row],[Tipo de Movimiento]]="Ingreso",tblMovimientos[[#This Row],[Monto (S/)]],"0") -> 0 | O248: =IF(tblMovimientos[[#This Row],[Tipo de Movimiento]]="Egreso",tblMovimientos[[#This Row],[Monto (S/)]],"0") -> 15 | P248: =IF(tblMovimientos[[#This Row],[Tipo de Movimiento]]="Ingreso",tblMovimientos[[#This Row],[Ingreso]],-tblMovimientos[[#This Row],[Egreso]]) -> -15 | Q248: =_xlfn.XLOOKUP(tblMovimientos[[#This Row],[Cuenta Bancaria]],Cuentas!$C:$C,Cuentas!$A:$A,"")&"" -> SSP Group | R248: =_xlfn.XLOOKUP(tblMovimientos[[#This Row],[Cuenta Bancaria]],Cuentas!$C:$C,Cuentas!$B:$B,"",0,-1)&""
B249: 46177 | C249: =_xlfn.XLOOKUP(tblMovimientos[[#This Row],[Cuenta Bancaria]],Listas!$B:$B,Listas!$A:$A,"") -> SSP Capital | D249: Bank of America - SSP Capital - 2580-USD | E249: =_xlfn.XLOOKUP(tblMovimientos[[#This Row],[Cuenta Bancaria]],Listas!$B:$B,Listas!$C:$C,"") -> Bank of America | F249: Ingreso | G249: Ing.Intereses Recibidos de Unidad de Negocio | H249: =IFERROR(_xlfn.XLOOKUP(G249,Listas!E:E,Listas!F:F,""),"") -> Operativo | I249: =IFERROR(_xlfn.XLOOKUP(G249,Listas!E:E,Listas!G:G,""),"") -> Externo | J249: 15307.88 | K249: =IF(F249="Ingreso",J249,-J249) -> 15307.88 | L249: 2026-06 | M249: =SUMIFS('Saldos Iniciales'!$D:$D,'Saldos Iniciales'!$A:$A,C249,'Saldos Iniciales'!$B:$B,D249)+SUMIFS($K$1:$K$1324,$C$1:$C$1324,C249,$D$1:$D$1324,D249,$B$1:$B$1324,"<="&B249) -> 25322.66 | N249: =IF(tblMovimientos[[#This Row],[Tipo de Movimiento]]="Ingreso",tblMovimientos[[#This Row],[Monto (S/)]],"0") -> 15307.88 | O249: =IF(tblMovimientos[[#This Row],[Tipo de Movimiento]]="Egreso",tblMovimientos[[#This Row],[Monto (S/)]],"0") -> 0 | P249: =IF(tblMovimientos[[#This Row],[Tipo de Movimiento]]="Ingreso",tblMovimientos[[#This Row],[Ingreso]],-tblMovimientos[[#This Row],[Egreso]]) -> 15307.88 | Q249: =_xlfn.XLOOKUP(tblMovimientos[[#This Row],[Cuenta Bancaria]],Cuentas!$C:$C,Cuentas!$A:$A,"")&"" -> SSP Group | R249: =_xlfn.XLOOKUP(tblMovimientos[[#This Row],[Cuenta Bancaria]],Cuentas!$C:$C,Cuentas!$B:$B,"",0,-1)&""
B250: 46177 | C250: =_xlfn.XLOOKUP(tblMovimientos[[#This Row],[Cuenta Bancaria]],Listas!$B:$B,Listas!$A:$A,"") -> SSP Capital | D250: Bank of America - SSP Capital - 2580-USD | E250: =_xlfn.XLOOKUP(tblMovimientos[[#This Row],[Cuenta Bancaria]],Listas!$B:$B,Listas!$C:$C,"") -> Bank of America | F250: Egreso | G250: Eg.Gastos Operativos (Proveedor) | H250: =IFERROR(_xlfn.XLOOKUP(G250,Listas!E:E,Listas!F:F,""),"") -> Operativo | I250: =IFERROR(_xlfn.XLOOKUP(G250,Listas!E:E,Listas!G:G,""),"") -> Externo | J250: 538.42 | K250: =IF(F250="Ingreso",J250,-J250) -> -538.42 | L250: 2026-06 | M250: =SUMIFS('Saldos Iniciales'!$D:$D,'Saldos Iniciales'!$A:$A,C250,'Saldos Iniciales'!$B:$B,D250)+SUMIFS($K$1:$K$1324,$C$1:$C$1324,C250,$D$1:$D$1324,D250,$B$1:$B$1324,"<="&B250) -> 25322.66 | N250: =IF(tblMovimientos[[#This Row],[Tipo de Movimiento]]="Ingreso",tblMovimientos[[#This Row],[Monto (S/)]],"0") -> 0 | O250: =IF(tblMovimientos[[#This Row],[Tipo de Movimiento]]="Egreso",tblMovimientos[[#This Row],[Monto (S/)]],"0") -> 538.42 | P250: =IF(tblMovimientos[[#This Row],[Tipo de Movimiento]]="Ingreso",tblMovimientos[[#This Row],[Ingreso]],-tblMovimientos[[#This Row],[Egreso]]) -> -538.42 | Q250: =_xlfn.XLOOKUP(tblMovimientos[[#This Row],[Cuenta Bancaria]],Cuentas!$C:$C,Cuentas!$A:$A,"")&"" -> SSP Group | R250: =_xlfn.XLOOKUP(tblMovimientos[[#This Row],[Cuenta Bancaria]],Cuentas!$C:$C,Cuentas!$B:$B,"",0,-1)&""
B251: 46177 | C251: =_xlfn.XLOOKUP(tblMovimientos[[#This Row],[Cuenta Bancaria]],Listas!$B:$B,Listas!$A:$A,"") -> A&M Imports | D251: Bank of America - A&M Imports - 3797-USD | E251: =_xlfn.XLOOKUP(tblMovimientos[[#This Row],[Cuenta Bancaria]],Listas!$B:$B,Listas!$C:$C,"") -> Bank of America | F251: Egreso | G251: Eg.Prestamos Concedidos a Unidades de negocio | H251: =IFERROR(_xlfn.XLOOKUP(G251,Listas!E:E,Listas!F:F,""),"") -> Operativo | I251: =IFERROR(_xlfn.XLOOKUP(G251,Listas!E:E,Listas!G:G,""),"") -> Externo | J251: 60000 | K251: =IF(F251="Ingreso",J251,-J251) -> -60000 | L251: 2026-06 | M251: =SUMIFS('Saldos Iniciales'!$D:$D,'Saldos Iniciales'!$A:$A,C251,'Saldos Iniciales'!$B:$B,D251)+SUMIFS($K$1:$K$1324,$C$1:$C$1324,C251,$D$1:$D$1324,D251,$B$1:$B$1324,"<="&B251) -> 729545.24 | N251: =IF(tblMovimientos[[#This Row],[Tipo de Movimiento]]="Ingreso",tblMovimientos[[#This Row],[Monto (S/)]],"0") -> 0 | O251: =IF(tblMovimientos[[#This Row],[Tipo de Movimiento]]="Egreso",tblMovimientos[[#This Row],[Monto (S/)]],"0") -> 60000 | P251: =IF(tblMovimientos[[#This Row],[Tipo de Movimiento]]="Ingreso",tblMovimientos[[#This Row],[Ingreso]],-tblMovimientos[[#This Row],[Egreso]]) -> -60000 | Q251: =_xlfn.XLOOKUP(tblMovimientos[[#This Row],[Cuenta Bancaria]],Cuentas!$C:$C,Cuentas!$A:$A,"")&"" -> SSP Group | R251: =_xlfn.XLOOKUP(tblMovimientos[[#This Row],[Cuenta Bancaria]],Cuentas!$C:$C,Cuentas!$B:$B,"",0,-1)&""
... B313: 46185 | C313: =_xlfn.XLOOKUP(tblMovimientos[[#This Row],[Cuenta Bancaria]],Listas!$B:$B,Listas!$A:$A,"") -> SSP Capital | D313: Amerant Bank - SSP Capital - 4706-USD | E313: =_xlfn.XLOOKUP(tblMovimientos[[#This Row],[Cuenta Bancaria]],Listas!$B:$B,Listas!$C:$C,"") -> Amerant Bank | F313: Ingreso | G313: Ing.Deuda Recibida de Terceros | H313: =IFERROR(_xlfn.XLOOKUP(G313,Listas!E:E,Listas!F:F,""),"") -> Financiamiento | I313: =IFERROR(_xlfn.XLOOKUP(G313,Listas!E:E,Listas!G:G,""),"") -> Externo | J313: 2970000 | K313: =IF(F313="Ingreso",J313,-J313) -> 2970000 | L313: 2026-06 | M313: =SUMIFS('Saldos Iniciales'!$D:$D,'Saldos Iniciales'!$A:$A,C313,'Saldos Iniciales'!$B:$B,D313)+SUMIFS($K$1:$K$1324,$C$1:$C$1324,C313,$D$1:$D$1324,D313,$B$1:$B$1324,"<="&B313) -> 2988249.8 | N313: =IF(tblMovimientos[[#This Row],[Tipo de Movimiento]]="Ingreso",tblMovimientos[[#This Row],[Monto (S/)]],"0") -> 2970000 | O313: =IF(tblMovimientos[[#This Row],[Tipo de Movimiento]]="Egreso",tblMovimientos[[#This Row],[Monto (S/)]],"0") -> 0 | P313: =IF(tblMovimientos[[#This Row],[Tipo de Movimiento]]="Ingreso",tblMovimientos[[#This Row],[Ingreso]],-tblMovimientos[[#This Row],[Egreso]]) -> 2970000 | Q313: =_xlfn.XLOOKUP(tblMovimientos[[#This Row],[Cuenta Bancaria]],Cuentas!$C:$C,Cuentas!$A:$A,"")&"" -> SSP Group | R313: =_xlfn.XLOOKUP(tblMovimientos[[#This Row],[Cuenta Bancaria]],Cuentas!$C:$C,Cuentas!$B:$B,"",0,-1)&""
B314: 46185 | C314: =_xlfn.XLOOKUP(tblMovimientos[[#This Row],[Cuenta Bancaria]],Listas!$B:$B,Listas!$A:$A,"") -> Cross Security Trust | D314: Bank of America - Cross Security Trust - 6642-USD | E314: =_xlfn.XLOOKUP(tblMovimientos[[#This Row],[Cuenta Bancaria]],Listas!$B:$B,Listas!$C:$C,"") -> Bank of America | F314: Ingreso | G314: Ing.Interes bancario | J314: 0.62 | K314: =IF(F314="Ingreso",J314,-J314) -> 0.62 | L314: 2026-06 | M314: =SUMIFS('Saldos Iniciales'!$D:$D,'Saldos Iniciales'!$A:$A,C314,'Saldos Iniciales'!$B:$B,D314)+SUMIFS($K$1:$K$1324,$C$1:$C$1324,C314,$D$1:$D$1324,D314,$B$1:$B$1324,"<="&B314) -> 20375.99 | N314: =IF(tblMovimientos[[#This Row],[Tipo de Movimiento]]="Ingreso",tblMovimientos[[#This Row],[Monto (S/)]],"0") -> 0.62 | O314: =IF(tblMovimientos[[#This Row],[Tipo de Movimiento]]="Egreso",tblMovimientos[[#This Row],[Monto (S/)]],"0") -> 0 | P314: =IF(tblMovimientos[[#This Row],[Tipo de Movimiento]]="Ingreso",tblMovimientos[[#This Row],[Ingreso]],-tblMovimientos[[#This Row],[Egreso]]) -> 0.62 | Q314: =_xlfn.XLOOKUP(tblMovimientos[[#This Row],[Cuenta Bancaria]],Cuentas!$C:$C,Cuentas!$A:$A,"")&"" -> SSP Group | R314: =_xlfn.XLOOKUP(tblMovimientos[[#This Row],[Cuenta Bancaria]],Cuentas!$C:$C,Cuentas!$B:$B,"",0,-1)&"" -> Trust
B315: 46188 | C315: =_xlfn.XLOOKUP(tblMovimientos[[#This Row],[Cuenta Bancaria]],Listas!$B:$B,Listas!$A:$A,"") -> Go Blue | D315: Amerant Bank - Go Blue - 8206-USD | E315: =_xlfn.XLOOKUP(tblMovimientos[[#This Row],[Cuenta Bancaria]],Listas!$B:$B,Listas!$C:$C,"") -> Amerant Bank | F315: Egreso | G315: Eg.Gastos Operativos (Proveedor) | H315: =IFERROR(_xlfn.XLOOKUP(G315,Listas!E:E,Listas!F:F,""),"") -> Operativo | I315: =IFERROR(_xlfn.XLOOKUP(G315,Listas!E:E,Listas!G:G,""),"") -> Externo | J315: 50 | K315: =IF(F315="Ingreso",J315,-J315) -> -50 | L315: 2026-06 | M315: =SUMIFS('Saldos Iniciales'!$D:$D,'Saldos Iniciales'!$A:$A,C315,'Saldos Iniciales'!$B:$B,D315)+SUMIFS($K$1:$K$1324,$C$1:$C$1324,C315,$D$1:$D$1324,D315,$B$1:$B$1324,"<="&B315) -> 48724.73 | N315: =IF(tblMovimientos[[#This Row],[Tipo de Movimiento]]="Ingreso",tblMovimientos[[#This Row],[Monto (S/)]],"0") -> 0 | O315: =IF(tblMovimientos[[#This Row],[Tipo de Movimiento]]="Egreso",tblMovimientos[[#This Row],[Monto (S/)]],"0") -> 50 | P315: =IF(tblMovimientos[[#This Row],[Tipo de Movimiento]]="Ingreso",tblMovimientos[[#This Row],[Ingreso]],-tblMovimientos[[#This Row],[Egreso]]) -> -50 | Q315: =_xlfn.XLOOKUP(tblMovimientos[[#This Row],[Cuenta Bancaria]],Cuentas!$C:$C,Cuentas!$A:$A,"")&"" -> SSP Group | R315: =_xlfn.XLOOKUP(tblMovimientos[[#This Row],[Cuenta Bancaria]],Cuentas!$C:$C,Cuentas!$B:$B,"",0,-1)&""
B316: 46188 | C316: =_xlfn.XLOOKUP(tblMovimientos[[#This Row],[Cuenta Bancaria]],Listas!$B:$B,Listas!$A:$A,"") -> CFT Group | D316: Amerant Bank - CFT Group - 1906-USD | E316: =_xlfn.XLOOKUP(tblMovimientos[[#This Row],[Cuenta Bancaria]],Listas!$B:$B,Listas!$C:$C,"") -> Amerant Bank | F316: Ingreso | G316: Ing.Transferencias entre cuentas (Misma entidad legal) | H316: =IFERROR(_xlfn.XLOOKUP(G316,Listas!E:E,Listas!F:F,""),"") -> Operativo | I316: =IFERROR(_xlfn.XLOOKUP(G316,Listas!E:E,Listas!G:G,""),"") -> Interno | J316: 270000 | K316: =IF(F316="Ingreso",J316,-J316) -> 270000 | L316: 2026-06 | M316: =SUMIFS('Saldos Iniciales'!$D:$D,'Saldos Iniciales'!$A:$A,C316,'Saldos Iniciales'!$B:$B,D316)+SUMIFS($K$1:$K$1324,$C$1:$C$1324,C316,$D$1:$D$1324,D316,$B$1:$B$1324,"<="&B316) -> 968878.52 | N316: =IF(tblMovimientos[[#This Row],[Tipo de Movimiento]]="Ingreso",tblMovimientos[[#This Row],[Monto (S/)]],"0") -> 270000 | O316: =IF(tblMovimientos[[#This Row],[Tipo de Movimiento]]="Egreso",tblMovimientos[[#This Row],[Monto (S/)]],"0") -> 0 | P316: =IF(tblMovimientos[[#This Row],[Tipo de Movimiento]]="Ingreso",tblMovimientos[[#This Row],[Ingreso]],-tblMovimientos[[#This Row],[Egreso]]) -> 270000 | Q316: =_xlfn.XLOOKUP(tblMovimientos[[#This Row],[Cuenta Bancaria]],Cuentas!$C:$C,Cuentas!$A:$A,"")&"" -> SSP Group | R316: =_xlfn.XLOOKUP(tblMovimientos[[#This Row],[Cuenta Bancaria]],Cuentas!$C:$C,Cuentas!$B:$B,"",0,-1)&""
B317: 46188 | C317: =_xlfn.XLOOKUP(tblMovimientos[[#This Row],[Cuenta Bancaria]],Listas!$B:$B,Listas!$A:$A,"") -> CFT Group | D317: Amerant Bank - CFT Group - 1906-USD | E317: =_xlfn.XLOOKUP(tblMovimientos[[#This Row],[Cuenta Bancaria]],Listas!$B:$B,Listas!$C:$C,"") -> Amerant Bank | F317: Egreso | G317: Eg.Deuda Terceros (Intereses+Capital) | H317: =IFERROR(_xlfn.XLOOKUP(G317,Listas!E:E,Listas!F:F,""),"") -> Financiamiento | I317: =IFERROR(_xlfn.XLOOKUP(G317,Listas!E:E,Listas!G:G,""),"") -> Externo | J317: 2366.67 | K317: =IF(F317="Ingreso",J317,-J317) -> -2366.67 | L317: 2026-06 | M317: =SUMIFS('Saldos Iniciales'!$D:$D,'Saldos Iniciales'!$A:$A,C317,'Saldos Iniciales'!$B:$B,D317)+SUMIFS($K$1:$K$1324,$C$1:$C$1324,C317,$D$1:$D$1324,D317,$B$1:$B$1324,"<="&B317) -> 968878.52 | N317: =IF(tblMovimientos[[#This Row],[Tipo de Movimiento]]="Ingreso",tblMovimientos[[#This Row],[Monto (S/)]],"0") -> 0 | O317: =IF(tblMovimientos[[#This Row],[Tipo de Movimiento]]="Egreso",tblMovimientos[[#This Row],[Monto (S/)]],"0") -> 2366.67 | P317: =IF(tblMovimientos[[#This Row],[Tipo de Movimiento]]="Ingreso",tblMovimientos[[#This Row],[Ingreso]],-tblMovimientos[[#This Row],[Egreso]]) -> -2366.67 | Q317: =_xlfn.XLOOKUP(tblMovimientos[[#This Row],[Cuenta Bancaria]],Cuentas!$C:$C,Cuentas!$A:$A,"")&"" -> SSP Group | R317: =_xlfn.XLOOKUP(tblMovimientos[[#This Row],[Cuenta Bancaria]],Cuentas!$C:$C,Cuentas!$B:$B,"",0,-1)&""
B318: 46188 | C318: =_xlfn.XLOOKUP(tblMovimientos[[#This Row],[Cuenta Bancaria]],Listas!$B:$B,Listas!$A:$A,"") -> CFT Group | D318: Amerant Bank - CFT Group - 1906-USD | E318: =_xlfn.XLOOKUP(tblMovimientos[[#This Row],[Cuenta Bancaria]],Listas!$B:$B,Listas!$C:$C,"") -> Amerant Bank | F318: Egreso | G318: Eg.Deuda Terceros (Intereses+Capital) | H318: =IFERROR(_xlfn.XLOOKUP(G318,Listas!E:E,Listas!F:F,""),"") -> Financiamiento | I318: =IFERROR(_xlfn.XLOOKUP(G318,Listas!E:E,Listas!G:G,""),"") -> Externo | J318: 3500 | K318: =IF(F318="Ingreso",J318,-J318) -> -3500 | L318: 2026-06 | M318: =SUMIFS('Saldos Iniciales'!$D:$D,'Saldos Iniciales'!$A:$A,C318,'Saldos Iniciales'!$B:$B,D318)+SUMIFS($K$1:$K$1324,$C$1:$C$1324,C318,$D$1:$D$1324,D318,$B$1:$B$1324,"<="&B318) -> 968878.52 | N318: =IF(tblMovimientos[[#This Row],[Tipo de Movimiento]]="Ingreso",tblMovimientos[[#This Row],[Monto (S/)]],"0") -> 0 | O318: =IF(tblMovimientos[[#This Row],[Tipo de Movimiento]]="Egreso",tblMovimientos[[#This Row],[Monto (S/)]],"0") -> 3500 | P318: =IF(tblMovimientos[[#This Row],[Tipo de Movimiento]]="Ingreso",tblMovimientos[[#This Row],[Ingreso]],-tblMovimientos[[#This Row],[Egreso]]) -> -3500 | Q318: =_xlfn.XLOOKUP(tblMovimientos[[#This Row],[Cuenta Bancaria]],Cuentas!$C:$C,Cuentas!$A:$A,"")&"" -> SSP Group | R318: =_xlfn.XLOOKUP(tblMovimientos[[#This Row],[Cuenta Bancaria]],Cuentas!$C:$C,Cuentas!$B:$B,"",0,-1)&""
B319: 46188 | C319: =_xlfn.XLOOKUP(tblMovimientos[[#This Row],[Cuenta Bancaria]],Listas!$B:$B,Listas!$A:$A,"") -> CFT Group | D319: Amerant Bank - CFT Group - 1906-USD | E319: =_xlfn.XLOOKUP(tblMovimientos[[#This Row],[Cuenta Bancaria]],Listas!$B:$B,Listas!$C:$C,"") -> Amerant Bank | F319: Egreso | G319: Eg.Deuda Terceros (Intereses+Capital) | H319: =IFERROR(_xlfn.XLOOKUP(G319,Listas!E:E,Listas!F:F,""),"") -> Financiamiento | I319: =IFERROR(_xlfn.XLOOKUP(G319,Listas!E:E,Listas!G:G,""),"") -> Externo | J319: 10608.89 | K319: =IF(F319="Ingreso",J319,-J319) -> -10608.89 | L319: 2026-06 | M319: =SUMIFS('Saldos Iniciales'!$D:$D,'Saldos Iniciales'!$A:$A,C319,'Saldos Iniciales'!$B:$B,D319)+SUMIFS($K$1:$K$1324,$C$1:$C$1324,C319,$D$1:$D$1324,D319,$B$1:$B$1324,"<="&B319) -> 968878.52 | N319: =IF(tblMovimientos[[#This Row],[Tipo de Movimiento]]="Ingreso",tblMovimientos[[#This Row],[Monto (S/)]],"0") -> 0 | O319: =IF(tblMovimientos[[#This Row],[Tipo de Movimiento]]="Egreso",tblMovimientos[[#This Row],[Monto (S/)]],"0") -> 10608.89 | P319: =IF(tblMovimientos[[#This Row],[Tipo de Movimiento]]="Ingreso",tblMovimientos[[#This Row],[Ingreso]],-tblMovimientos[[#This Row],[Egreso]]) -> -10608.89 | Q319: =_xlfn.XLOOKUP(tblMovimientos[[#This Row],[Cuenta Bancaria]],Cuentas!$C:$C,Cuentas!$A:$A,"")&"" -> SSP Group | R319: =_xlfn.XLOOKUP(tblMovimientos[[#This Row],[Cuenta Bancaria]],Cuentas!$C:$C,Cuentas!$B:$B,"",0,-1)&""
B320: 46188 | C320: =_xlfn.XLOOKUP(tblMovimientos[[#This Row],[Cuenta Bancaria]],Listas!$B:$B,Listas!$A:$A,"") -> CFT Group | D320: Amerant Bank - CFT Group - 1906-USD | E320: =_xlfn.XLOOKUP(tblMovimientos[[#This Row],[Cuenta Bancaria]],Listas!$B:$B,Listas!$C:$C,"") -> Amerant Bank | F320: Egreso | G320: Eg.Deuda Terceros (Intereses+Capital) | H320: =IFERROR(_xlfn.XLOOKUP(G320,Listas!E:E,Listas!F:F,""),"") -> Financiamiento | I320: =IFERROR(_xlfn.XLOOKUP(G320,Listas!E:E,Listas!G:G,""),"") -> Externo | J320: 12055.56 | K320: =IF(F320="Ingreso",J320,-J320) -> -12055.56 | L320: 2026-06 | M320: =SUMIFS('Saldos Iniciales'!$D:$D,'Saldos Iniciales'!$A:$A,C320,'Saldos Iniciales'!$B:$B,D320)+SUMIFS($K$1:$K$1324,$C$1:$C$1324,C320,$D$1:$D$1324,D320,$B$1:$B$1324,"<="&B320) -> 968878.52 | N320: =IF(tblMovimientos[[#This Row],[Tipo de Movimiento]]="Ingreso",tblMovimientos[[#This Row],[Monto (S/)]],"0") -> 0 | O320: =IF(tblMovimientos[[#This Row],[Tipo de Movimiento]]="Egreso",tblMovimientos[[#This Row],[Monto (S/)]],"0") -> 12055.56 | P320: =IF(tblMovimientos[[#This Row],[Tipo de Movimiento]]="Ingreso",tblMovimientos[[#This Row],[Ingreso]],-tblMovimientos[[#This Row],[Egreso]]) -> -12055.56 | Q320: =_xlfn.XLOOKUP(tblMovimientos[[#This Row],[Cuenta Bancaria]],Cuentas!$C:$C,Cuentas!$A:$A,"")&"" -> SSP Group | R320: =_xlfn.XLOOKUP(tblMovimientos[[#This Row],[Cuenta Bancaria]],Cuentas!$C:$C,Cuentas!$B:$B,"",0,-1)&""
B321: 46188 | C321: =_xlfn.XLOOKUP(tblMovimientos[[#This Row],[Cuenta Bancaria]],Listas!$B:$B,Listas!$A:$A,"") -> CFT Group | D321: Amerant Bank - CFT Group - 1906-USD | E321: =_xlfn.XLOOKUP(tblMovimientos[[#This Row],[Cuenta Bancaria]],Listas!$B:$B,Listas!$C:$C,"") -> Amerant Bank | F321: Egreso | G321: Eg.Deuda Terceros (Intereses+Capital) | H321: =IFERROR(_xlfn.XLOOKUP(G321,Listas!E:E,Listas!F:F,""),"") -> Financiamiento | I321: =IFERROR(_xlfn.XLOOKUP(G321,Listas!E:E,Listas!G:G,""),"") -> Externo | J321: 22166.67 | K321: =IF(F321="Ingreso",J321,-J321) -> -22166.67 | L321: 2026-06 | M321: =SUMIFS('Saldos Iniciales'!$D:$D,'Saldos Iniciales'!$A:$A,C321,'Saldos Iniciales'!$B:$B,D321)+SUMIFS($K$1:$K$1324,$C$1:$C$1324,C321,$D$1:$D$1324,D321,$B$1:$B$1324,"<="&B321) -> 968878.52 | N321: =IF(tblMovimientos[[#This Row],[Tipo de Movimiento]]="Ingreso",tblMovimientos[[#This Row],[Monto (S/)]],"0") -> 0 | O321: =IF(tblMovimientos[[#This Row],[Tipo de Movimiento]]="Egreso",tblMovimientos[[#This Row],[Monto (S/)]],"0") -> 22166.67 | P321: =IF(tblMovimientos[[#This Row],[Tipo de Movimiento]]="Ingreso",tblMovimientos[[#This Row],[Ingreso]],-tblMovimientos[[#This Row],[Egreso]]) -> -22166.67 | Q321: =_xlfn.XLOOKUP(tblMovimientos[[#This Row],[Cuenta Bancaria]],Cuentas!$C:$C,Cuentas!$A:$A,"")&"" -> SSP Group | R321: =_xlfn.XLOOKUP(tblMovimientos[[#This Row],[Cuenta Bancaria]],Cuentas!$C:$C,Cuentas!$B:$B,"",0,-1)&""
B322: 46188 | C322: =_xlfn.XLOOKUP(tblMovimientos[[#This Row],[Cuenta Bancaria]],Listas!$B:$B,Listas!$A:$A,"") -> CFT Group | D322: Amerant Bank - CFT Group - 1906-USD | E322: =_xlfn.XLOOKUP(tblMovimientos[[#This Row],[Cuenta Bancaria]],Listas!$B:$B,Listas!$C:$C,"") -> Amerant Bank | F322: Egreso | G322: Eg.Deuda Terceros (Intereses+Capital) | H322: =IFERROR(_xlfn.XLOOKUP(G322,Listas!E:E,Listas!F:F,""),"") -> Financiamiento | I322: =IFERROR(_xlfn.XLOOKUP(G322,Listas!E:E,Listas!G:G,""),"") -> Externo | J322: 24111.11 | K322: =IF(F322="Ingreso",J322,-J322) -> -24111.11 | L322: 2026-06 | M322: =SUMIFS('Saldos Iniciales'!$D:$D,'Saldos Iniciales'!$A:$A,C322,'Saldos Iniciales'!$B:$B,D322)+SUMIFS($K$1:$K$1324,$C$1:$C$1324,C322,$D$1:$D$1324,D322,$B$1:$B$1324,"<="&B322) -> 968878.52 | N322: =IF(tblMovimientos[[#This Row],[Tipo de Movimiento]]="Ingreso",tblMovimientos[[#This Row],[Monto (S/)]],"0") -> 0 | O322: =IF(tblMovimientos[[#This Row],[Tipo de Movimiento]]="Egreso",tblMovimientos[[#This Row],[Monto (S/)]],"0") -> 24111.11 | P322: =IF(tblMovimientos[[#This Row],[Tipo de Movimiento]]="Ingreso",tblMovimientos[[#This Row],[Ingreso]],-tblMovimientos[[#This Row],[Egreso]]) -> -24111.11 | Q322: =_xlfn.XLOOKUP(tblMovimientos[[#This Row],[Cuenta Bancaria]],Cuentas!$C:$C,Cuentas!$A:$A,"")&"" -> SSP Group | R322: =_xlfn.XLOOKUP(tblMovimientos[[#This Row],[Cuenta Bancaria]],Cuentas!$C:$C,Cuentas!$B:$B,"",0,-1)&""
B323: 46188 | C323: =_xlfn.XLOOKUP(tblMovimientos[[#This Row],[Cuenta Bancaria]],Listas!$B:$B,Listas!$A:$A,"") -> CFT Group | D323: Amerant Bank - CFT Group - 1906-USD | E323: =_xlfn.XLOOKUP(tblMovimientos[[#This Row],[Cuenta Bancaria]],Listas!$B:$B,Listas!$C:$C,"") -> Amerant Bank | F323: Egreso | G323: Eg.Prestamos Concedidos a Unidades de negocio | H323: =IFERROR(_xlfn.XLOOKUP(G323,Listas!E:E,Listas!F:F,""),"") -> Operativo | I323: =IFERROR(_xlfn.XLOOKUP(G323,Listas!E:E,Listas!G:G,""),"") -> Externo | J323: 40000 | K323: =IF(F323="Ingreso",J323,-J323) -> -40000 | L323: 2026-06 | M323: =SUMIFS('Saldos Iniciales'!$D:$D,'Saldos Iniciales'!$A:$A,C323,'Saldos Iniciales'!$B:$B,D323)+SUMIFS($K$1:$K$1324,$C$1:$C$1324,C323,$D$1:$D$1324,D323,$B$1:$B$1324,"<="&B323) -> 968878.52 | N323: =IF(tblMovimientos[[#This Row],[Tipo de Movimiento]]="Ingreso",tblMovimientos[[#This Row],[Monto (S/)]],"0") -> 0 | O323: =IF(tblMovimientos[[#This Row],[Tipo de Movimiento]]="Egreso",tblMovimientos[[#This Row],[Monto (S/)]],"0") -> 40000 | P323: =IF(tblMovimientos[[#This Row],[Tipo de Movimiento]]="Ingreso",tblMovimientos[[#This Row],[Ingreso]],-tblMovimientos[[#This Row],[Egreso]]) -> -40000 | Q323: =_xlfn.XLOOKUP(tblMovimientos[[#This Row],[Cuenta Bancaria]],Cuentas!$C:$C,Cuentas!$A:$A,"")&"" -> SSP Group | R323: =_xlfn.XLOOKUP(tblMovimientos[[#This Row],[Cuenta Bancaria]],Cuentas!$C:$C,Cuentas!$B:$B,"",0,-1)&""
B324: 46188 | C324: =_xlfn.XLOOKUP(tblMovimientos[[#This Row],[Cuenta Bancaria]],Listas!$B:$B,Listas!$A:$A,"") -> CFT Group | D324: Amerant Bank - CFT Group - 1906-USD | E324: =_xlfn.XLOOKUP(tblMovimientos[[#This Row],[Cuenta Bancaria]],Listas!$B:$B,Listas!$C:$C,"") -> Amerant Bank | F324: Egreso | G324: Eg.Prestamos Concedidos a Unidades de negocio | H324: =IFERROR(_xlfn.XLOOKUP(G324,Listas!E:E,Listas!F:F,""),"") -> Operativo | I324: =IFERROR(_xlfn.XLOOKUP(G324,Listas!E:E,Listas!G:G,""),"") -> Externo | J324: 60000 | K324: =IF(F324="Ingreso",J324,-J324) -> -60000 | L324: 2026-06 | M324: =SUMIFS('Saldos Iniciales'!$D:$D,'Saldos Iniciales'!$A:$A,C324,'Saldos Iniciales'!$B:$B,D324)+SUMIFS($K$1:$K$1324,$C$1:$C$1324,C324,$D$1:$D$1324,D324,$B$1:$B$1324,"<="&B324) -> 968878.52 | N324: =IF(tblMovimientos[[#This Row],[Tipo de Movimiento]]="Ingreso",tblMovimientos[[#This Row],[Monto (S/)]],"0") -> 0 | O324: =IF(tblMovimientos[[#This Row],[Tipo de Movimiento]]="Egreso",tblMovimientos[[#This Row],[Monto (S/)]],"0") -> 60000 | P324: =IF(tblMovimientos[[#This Row],[Tipo de Movimiento]]="Ingreso",tblMovimientos[[#This Row],[Ingreso]],-tblMovimientos[[#This Row],[Egreso]]) -> -60000 | Q324: =_xlfn.XLOOKUP(tblMovimientos[[#This Row],[Cuenta Bancaria]],Cuentas!$C:$C,Cuentas!$A:$A,"")&"" -> SSP Group | R324: =_xlfn.XLOOKUP(tblMovimientos[[#This Row],[Cuenta Bancaria]],Cuentas!$C:$C,Cuentas!$B:$B,"",0,-1)&""
B325: 46188 | C325: =_xlfn.XLOOKUP(tblMovimientos[[#This Row],[Cuenta Bancaria]],Listas!$B:$B,Listas!$A:$A,"") -> CFT Group | D325: Amerant Bank - CFT Group - 1906-USD | E325: =_xlfn.XLOOKUP(tblMovimientos[[#This Row],[Cuenta Bancaria]],Listas!$B:$B,Listas!$C:$C,"") -> Amerant Bank | F325: Egreso | G325: Eg.Prestamos Concedidos a Unidades de negocio | H325: =IFERROR(_xlfn.XLOOKUP(G325,Listas!E:E,Listas!F:F,""),"") -> Operativo | I325: =IFERROR(_xlfn.XLOOKUP(G325,Listas!E:E,Listas!G:G,""),"") -> Externo | J325: 100000 | K325: =IF(F325="Ingreso",J325,-J325) -> -100000 | L325: 2026-06 | M325: =SUMIFS('Saldos Iniciales'!$D:$D,'Saldos Iniciales'!$A:$A,C325,'Saldos Iniciales'!$B:$B,D325)+SUMIFS($K$1:$K$1324,$C$1:$C$1324,C325,$D$1:$D$1324,D325,$B$1:$B$1324,"<="&B325) -> 968878.52 | N325: =IF(tblMovimientos[[#This Row],[Tipo de Movimiento]]="Ingreso",tblMovimientos[[#This Row],[Monto (S/)]],"0") -> 0 | O325: =IF(tblMovimientos[[#This Row],[Tipo de Movimiento]]="Egreso",tblMovimientos[[#This Row],[Monto (S/)]],"0") -> 100000 | P325: =IF(tblMovimientos[[#This Row],[Tipo de Movimiento]]="Ingreso",tblMovimientos[[#This Row],[Ingreso]],-tblMovimientos[[#This Row],[Egreso]]) -> -100000 | Q325: =_xlfn.XLOOKUP(tblMovimientos[[#This Row],[Cuenta Bancaria]],Cuentas!$C:$C,Cuentas!$A:$A,"")&"" -> SSP Group | R325: =_xlfn.XLOOKUP(tblMovimientos[[#This Row],[Cuenta Bancaria]],Cuentas!$C:$C,Cuentas!$B:$B,"",0,-1)&""
B326: 46188 | C326: =_xlfn.XLOOKUP(tblMovimientos[[#This Row],[Cuenta Bancaria]],Listas!$B:$B,Listas!$A:$A,"") -> CFT Group | D326: Amerant Bank - CFT Group - 1906-USD | E326: =_xlfn.XLOOKUP(tblMovimientos[[#This Row],[Cuenta Bancaria]],Listas!$B:$B,Listas!$C:$C,"") -> Amerant Bank | F326: Egreso | G326: Eg.Prestamos Concedidos a Unidades de negocio | H326: =IFERROR(_xlfn.XLOOKUP(G326,Listas!E:E,Listas!F:F,""),"") -> Operativo | I326: =IFERROR(_xlfn.XLOOKUP(G326,Listas!E:E,Listas!G:G,""),"") -> Externo | J326: 150000 | K326: =IF(F326="Ingreso",J326,-J326) -> -150000 | L326: 2026-06 | M326: =SUMIFS('Saldos Iniciales'!$D:$D,'Saldos Iniciales'!$A:$A,C326,'Saldos Iniciales'!$B:$B,D326)+SUMIFS($K$1:$K$1324,$C$1:$C$1324,C326,$D$1:$D$1324,D326,$B$1:$B$1324,"<="&B326) -> 968878.52 | N326: =IF(tblMovimientos[[#This Row],[Tipo de Movimiento]]="Ingreso",tblMovimientos[[#This Row],[Monto (S/)]],"0") -> 0 | O326: =IF(tblMovimientos[[#This Row],[Tipo de Movimiento]]="Egreso",tblMovimientos[[#This Row],[Monto (S/)]],"0") -> 150000 | P326: =IF(tblMovimientos[[#This Row],[Tipo de Movimiento]]="Ingreso",tblMovimientos[[#This Row],[Ingreso]],-tblMovimientos[[#This Row],[Egreso]]) -> -150000 | Q326: =_xlfn.XLOOKUP(tblMovimientos[[#This Row],[Cuenta Bancaria]],Cuentas!$C:$C,Cuentas!$A:$A,"")&"" -> SSP Group | R326: =_xlfn.XLOOKUP(tblMovimientos[[#This Row],[Cuenta Bancaria]],Cuentas!$C:$C,Cuentas!$B:$B,"",0,-1)&""
... B381: 46198 | C381: =_xlfn.XLOOKUP(tblMovimientos[[#This Row],[Cuenta Bancaria]],Listas!$B:$B,Listas!$A:$A,"") -> 3628 Thomas Ave | D381: Bank of America - 3628 Thomas Ave - 4406-USD | E381: =_xlfn.XLOOKUP(tblMovimientos[[#This Row],[Cuenta Bancaria]],Listas!$B:$B,Listas!$C:$C,"") -> Bank of America | F381: Egreso | G381: Eg.Gastos Operativos (Proveedor) | H381: =IFERROR(_xlfn.XLOOKUP(G381,Listas!E:E,Listas!F:F,""),"") -> Operativo | I381: =IFERROR(_xlfn.XLOOKUP(G381,Listas!E:E,Listas!G:G,""),"") -> Externo | J381: 207.75 | K381: =IF(F381="Ingreso",J381,-J381) -> -207.75 | L381: 2026-06 | M381: =SUMIFS('Saldos Iniciales'!$D:$D,'Saldos Iniciales'!$A:$A,C381,'Saldos Iniciales'!$B:$B,D381)+SUMIFS($K$1:$K$1324,$C$1:$C$1324,C381,$D$1:$D$1324,D381,$B$1:$B$1324,"<="&B381) -> 28473.6 | N381: =IF(tblMovimientos[[#This Row],[Tipo de Movimiento]]="Ingreso",tblMovimientos[[#This Row],[Monto (S/)]],"0") -> 0 | O381: =IF(tblMovimientos[[#This Row],[Tipo de Movimiento]]="Egreso",tblMovimientos[[#This Row],[Monto (S/)]],"0") -> 207.75 | P381: =IF(tblMovimientos[[#This Row],[Tipo de Movimiento]]="Ingreso",tblMovimientos[[#This Row],[Ingreso]],-tblMovimientos[[#This Row],[Egreso]]) -> -207.75 | Q381: =_xlfn.XLOOKUP(tblMovimientos[[#This Row],[Cuenta Bancaria]],Cuentas!$C:$C,Cuentas!$A:$A,"")&"" -> SSP Group | R381: =_xlfn.XLOOKUP(tblMovimientos[[#This Row],[Cuenta Bancaria]],Cuentas!$C:$C,Cuentas!$B:$B,"",0,-1)&""
B382: 46198 | C382: =_xlfn.XLOOKUP(tblMovimientos[[#This Row],[Cuenta Bancaria]],Listas!$B:$B,Listas!$A:$A,"") -> CFT Group | D382: Amerant Bank - CFT Group - 1906-USD | E382: =_xlfn.XLOOKUP(tblMovimientos[[#This Row],[Cuenta Bancaria]],Listas!$B:$B,Listas!$C:$C,"") -> Amerant Bank | F382: Ingreso | H382: =IFERROR(_xlfn.XLOOKUP(G382,Listas!E:E,Listas!F:F,""),"") -> 0 | I382: =IFERROR(_xlfn.XLOOKUP(G382,Listas!E:E,Listas!G:G,""),"") -> 0 | J382: 10000 | K382: =IF(F382="Ingreso",J382,-J382) -> 10000 | L382: 2026-06 | M382: =SUMIFS('Saldos Iniciales'!$D:$D,'Saldos Iniciales'!$A:$A,C382,'Saldos Iniciales'!$B:$B,D382)+SUMIFS($K$1:$K$1324,$C$1:$C$1324,C382,$D$1:$D$1324,D382,$B$1:$B$1324,"<="&B382) -> 6264386.4 | N382: =IF(tblMovimientos[[#This Row],[Tipo de Movimiento]]="Ingreso",tblMovimientos[[#This Row],[Monto (S/)]],"0") -> 10000 | O382: =IF(tblMovimientos[[#This Row],[Tipo de Movimiento]]="Egreso",tblMovimientos[[#This Row],[Monto (S/)]],"0") -> 0 | P382: =IF(tblMovimientos[[#This Row],[Tipo de Movimiento]]="Ingreso",tblMovimientos[[#This Row],[Ingreso]],-tblMovimientos[[#This Row],[Egreso]]) -> 10000 | Q382: =_xlfn.XLOOKUP(tblMovimientos[[#This Row],[Cuenta Bancaria]],Cuentas!$C:$C,Cuentas!$A:$A,"")&"" -> SSP Group | R382: =_xlfn.XLOOKUP(tblMovimientos[[#This Row],[Cuenta Bancaria]],Cuentas!$C:$C,Cuentas!$B:$B,"",0,-1)&""
B383: 46198 | C383: =_xlfn.XLOOKUP(tblMovimientos[[#This Row],[Cuenta Bancaria]],Listas!$B:$B,Listas!$A:$A,"") -> CFT Group | D383: Amerant Bank - CFT Group - 1906-USD | E383: =_xlfn.XLOOKUP(tblMovimientos[[#This Row],[Cuenta Bancaria]],Listas!$B:$B,Listas!$C:$C,"") -> Amerant Bank | F383: Ingreso | G383: Ing.Deuda Recibida de Empresas relacionadas | H383: =IFERROR(_xlfn.XLOOKUP(G383,Listas!E:E,Listas!F:F,""),"") -> Financiamiento | I383: =IFERROR(_xlfn.XLOOKUP(G383,Listas!E:E,Listas!G:G,""),"") -> Interno | J383: 150000 | K383: =IF(F383="Ingreso",J383,-J383) -> 150000 | L383: 2026-06 | M383: =SUMIFS('Saldos Iniciales'!$D:$D,'Saldos Iniciales'!$A:$A,C383,'Saldos Iniciales'!$B:$B,D383)+SUMIFS($K$1:$K$1324,$C$1:$C$1324,C383,$D$1:$D$1324,D383,$B$1:$B$1324,"<="&B383) -> 6264386.4 | N383: =IF(tblMovimientos[[#This Row],[Tipo de Movimiento]]="Ingreso",tblMovimientos[[#This Row],[Monto (S/)]],"0") -> 150000 | O383: =IF(tblMovimientos[[#This Row],[Tipo de Movimiento]]="Egreso",tblMovimientos[[#This Row],[Monto (S/)]],"0") -> 0 | P383: =IF(tblMovimientos[[#This Row],[Tipo de Movimiento]]="Ingreso",tblMovimientos[[#This Row],[Ingreso]],-tblMovimientos[[#This Row],[Egreso]]) -> 150000 | Q383: =_xlfn.XLOOKUP(tblMovimientos[[#This Row],[Cuenta Bancaria]],Cuentas!$C:$C,Cuentas!$A:$A,"")&"" -> SSP Group | R383: =_xlfn.XLOOKUP(tblMovimientos[[#This Row],[Cuenta Bancaria]],Cuentas!$C:$C,Cuentas!$B:$B,"",0,-1)&""
B384: 46198 | C384: =_xlfn.XLOOKUP(tblMovimientos[[#This Row],[Cuenta Bancaria]],Listas!$B:$B,Listas!$A:$A,"") -> CFT Group | D384: Amerant Bank - CFT Group - 1906-USD | E384: =_xlfn.XLOOKUP(tblMovimientos[[#This Row],[Cuenta Bancaria]],Listas!$B:$B,Listas!$C:$C,"") -> Amerant Bank | F384: Ingreso | G384: Ing.Recibe Aporte de Capital de Empresas relacionadas | H384: =IFERROR(_xlfn.XLOOKUP(G384,Listas!E:E,Listas!F:F,""),"") -> Inversion | I384: =IFERROR(_xlfn.XLOOKUP(G384,Listas!E:E,Listas!G:G,""),"") -> Interno | J384: 500000 | K384: =IF(F384="Ingreso",J384,-J384) -> 500000 | L384: 2026-06 | M384: =SUMIFS('Saldos Iniciales'!$D:$D,'Saldos Iniciales'!$A:$A,C384,'Saldos Iniciales'!$B:$B,D384)+SUMIFS($K$1:$K$1324,$C$1:$C$1324,C384,$D$1:$D$1324,D384,$B$1:$B$1324,"<="&B384) -> 6264386.4 | N384: =IF(tblMovimientos[[#This Row],[Tipo de Movimiento]]="Ingreso",tblMovimientos[[#This Row],[Monto (S/)]],"0") -> 500000 | O384: =IF(tblMovimientos[[#This Row],[Tipo de Movimiento]]="Egreso",tblMovimientos[[#This Row],[Monto (S/)]],"0") -> 0 | P384: =IF(tblMovimientos[[#This Row],[Tipo de Movimiento]]="Ingreso",tblMovimientos[[#This Row],[Ingreso]],-tblMovimientos[[#This Row],[Egreso]]) -> 500000 | Q384: =_xlfn.XLOOKUP(tblMovimientos[[#This Row],[Cuenta Bancaria]],Cuentas!$C:$C,Cuentas!$A:$A,"")&"" -> SSP Group | R384: =_xlfn.XLOOKUP(tblMovimientos[[#This Row],[Cuenta Bancaria]],Cuentas!$C:$C,Cuentas!$B:$B,"",0,-1)&""
B385: 46198 | C385: =_xlfn.XLOOKUP(tblMovimientos[[#This Row],[Cuenta Bancaria]],Listas!$B:$B,Listas!$A:$A,"") -> CFT Group | D385: Amerant Bank - CFT Group - 1906-USD | E385: =_xlfn.XLOOKUP(tblMovimientos[[#This Row],[Cuenta Bancaria]],Listas!$B:$B,Listas!$C:$C,"") -> Amerant Bank | F385: Egreso | G385: Eg.Deuda Terceros (Intereses) | H385: =IFERROR(_xlfn.XLOOKUP(G385,Listas!E:E,Listas!F:F,""),"") -> Financiamiento | I385: =IFERROR(_xlfn.XLOOKUP(G385,Listas!E:E,Listas!G:G,""),"") -> Externo | J385: 10000 | K385: =IF(F385="Ingreso",J385,-J385) -> -10000 | L385: 2026-06 | M385: =SUMIFS('Saldos Iniciales'!$D:$D,'Saldos Iniciales'!$A:$A,C385,'Saldos Iniciales'!$B:$B,D385)+SUMIFS($K$1:$K$1324,$C$1:$C$1324,C385,$D$1:$D$1324,D385,$B$1:$B$1324,"<="&B385) -> 6264386.4 | N385: =IF(tblMovimientos[[#This Row],[Tipo de Movimiento]]="Ingreso",tblMovimientos[[#This Row],[Monto (S/)]],"0") -> 0 | O385: =IF(tblMovimientos[[#This Row],[Tipo de Movimiento]]="Egreso",tblMovimientos[[#This Row],[Monto (S/)]],"0") -> 10000 | P385: =IF(tblMovimientos[[#This Row],[Tipo de Movimiento]]="Ingreso",tblMovimientos[[#This Row],[Ingreso]],-tblMovimientos[[#This Row],[Egreso]]) -> -10000 | Q385: =_xlfn.XLOOKUP(tblMovimientos[[#This Row],[Cuenta Bancaria]],Cuentas!$C:$C,Cuentas!$A:$A,"")&"" -> SSP Group | R385: =_xlfn.XLOOKUP(tblMovimientos[[#This Row],[Cuenta Bancaria]],Cuentas!$C:$C,Cuentas!$B:$B,"",0,-1)&""
B386: 46198 | C386: =_xlfn.XLOOKUP(tblMovimientos[[#This Row],[Cuenta Bancaria]],Listas!$B:$B,Listas!$A:$A,"") -> CFT Group | D386: Amerant Bank - CFT Group - 1906-USD | E386: =_xlfn.XLOOKUP(tblMovimientos[[#This Row],[Cuenta Bancaria]],Listas!$B:$B,Listas!$C:$C,"") -> Amerant Bank | F386: Egreso | G386: Eg.Deuda Terceros (Intereses) | H386: =IFERROR(_xlfn.XLOOKUP(G386,Listas!E:E,Listas!F:F,""),"") -> Financiamiento | I386: =IFERROR(_xlfn.XLOOKUP(G386,Listas!E:E,Listas!G:G,""),"") -> Externo | J386: 10833.33 | K386: =IF(F386="Ingreso",J386,-J386) -> -10833.33 | L386: 2026-06 | M386: =SUMIFS('Saldos Iniciales'!$D:$D,'Saldos Iniciales'!$A:$A,C386,'Saldos Iniciales'!$B:$B,D386)+SUMIFS($K$1:$K$1324,$C$1:$C$1324,C386,$D$1:$D$1324,D386,$B$1:$B$1324,"<="&B386) -> 6264386.4 | N386: =IF(tblMovimientos[[#This Row],[Tipo de Movimiento]]="Ingreso",tblMovimientos[[#This Row],[Monto (S/)]],"0") -> 0 | O386: =IF(tblMovimientos[[#This Row],[Tipo de Movimiento]]="Egreso",tblMovimientos[[#This Row],[Monto (S/)]],"0") -> 10833.33 | P386: =IF(tblMovimientos[[#This Row],[Tipo de Movimiento]]="Ingreso",tblMovimientos[[#This Row],[Ingreso]],-tblMovimientos[[#This Row],[Egreso]]) -> -10833.33 | Q386: =_xlfn.XLOOKUP(tblMovimientos[[#This Row],[Cuenta Bancaria]],Cuentas!$C:$C,Cuentas!$A:$A,"")&"" -> SSP Group | R386: =_xlfn.XLOOKUP(tblMovimientos[[#This Row],[Cuenta Bancaria]],Cuentas!$C:$C,Cuentas!$B:$B,"",0,-1)&""
B387: 46198 | C387: =_xlfn.XLOOKUP(tblMovimientos[[#This Row],[Cuenta Bancaria]],Listas!$B:$B,Listas!$A:$A,"") -> CFT Group | D387: Amerant Bank - CFT Group - 1906-USD | E387: =_xlfn.XLOOKUP(tblMovimientos[[#This Row],[Cuenta Bancaria]],Listas!$B:$B,Listas!$C:$C,"") -> Amerant Bank | F387: Egreso | G387: Eg.Deuda Terceros (Intereses) | H387: =IFERROR(_xlfn.XLOOKUP(G387,Listas!E:E,Listas!F:F,""),"") -> Financiamiento | I387: =IFERROR(_xlfn.XLOOKUP(G387,Listas!E:E,Listas!G:G,""),"") -> Externo | J387: 71041.67 | K387: =IF(F387="Ingreso",J387,-J387) -> -71041.67 | L387: 2026-06 | M387: =SUMIFS('Saldos Iniciales'!$D:$D,'Saldos Iniciales'!$A:$A,C387,'Saldos Iniciales'!$B:$B,D387)+SUMIFS($K$1:$K$1324,$C$1:$C$1324,C387,$D$1:$D$1324,D387,$B$1:$B$1324,"<="&B387) -> 6264386.4 | N387: =IF(tblMovimientos[[#This Row],[Tipo de Movimiento]]="Ingreso",tblMovimientos[[#This Row],[Monto (S/)]],"0") -> 0 | O387: =IF(tblMovimientos[[#This Row],[Tipo de Movimiento]]="Egreso",tblMovimientos[[#This Row],[Monto (S/)]],"0") -> 71041.67 | P387: =IF(tblMovimientos[[#This Row],[Tipo de Movimiento]]="Ingreso",tblMovimientos[[#This Row],[Ingreso]],-tblMovimientos[[#This Row],[Egreso]]) -> -71041.67 | Q387: =_xlfn.XLOOKUP(tblMovimientos[[#This Row],[Cuenta Bancaria]],Cuentas!$C:$C,Cuentas!$A:$A,"")&"" -> SSP Group | R387: =_xlfn.XLOOKUP(tblMovimientos[[#This Row],[Cuenta Bancaria]],Cuentas!$C:$C,Cuentas!$B:$B,"",0,-1)&""
B388: 46198 | C388: =_xlfn.XLOOKUP(tblMovimientos[[#This Row],[Cuenta Bancaria]],Listas!$B:$B,Listas!$A:$A,"") -> CFT Group | D388: Amerant Bank - CFT Group - 1906-USD | E388: =_xlfn.XLOOKUP(tblMovimientos[[#This Row],[Cuenta Bancaria]],Listas!$B:$B,Listas!$C:$C,"") -> Amerant Bank | F388: Egreso | G388: Eg.Prestamos Concedidos a Empresas relacionadas | H388: =IFERROR(_xlfn.XLOOKUP(G388,Listas!E:E,Listas!F:F,""),"") -> Operativo | I388: =IFERROR(_xlfn.XLOOKUP(G388,Listas!E:E,Listas!G:G,""),"") -> Interno | J388: 1850000 | K388: =IF(F388="Ingreso",J388,-J388) -> -1850000 | L388: 2026-06 | M388: =SUMIFS('Saldos Iniciales'!$D:$D,'Saldos Iniciales'!$A:$A,C388,'Saldos Iniciales'!$B:$B,D388)+SUMIFS($K$1:$K$1324,$C$1:$C$1324,C388,$D$1:$D$1324,D388,$B$1:$B$1324,"<="&B388) -> 6264386.4 | N388: =IF(tblMovimientos[[#This Row],[Tipo de Movimiento]]="Ingreso",tblMovimientos[[#This Row],[Monto (S/)]],"0") -> 0 | O388: =IF(tblMovimientos[[#This Row],[Tipo de Movimiento]]="Egreso",tblMovimientos[[#This Row],[Monto (S/)]],"0") -> 1850000 | P388: =IF(tblMovimientos[[#This Row],[Tipo de Movimiento]]="Ingreso",tblMovimientos[[#This Row],[Ingreso]],-tblMovimientos[[#This Row],[Egreso]]) -> -1850000 | Q388: =_xlfn.XLOOKUP(tblMovimientos[[#This Row],[Cuenta Bancaria]],Cuentas!$C:$C,Cuentas!$A:$A,"")&"" -> SSP Group | R388: =_xlfn.XLOOKUP(tblMovimientos[[#This Row],[Cuenta Bancaria]],Cuentas!$C:$C,Cuentas!$B:$B,"",0,-1)&""
B389: 46198 | C389: =_xlfn.XLOOKUP(tblMovimientos[[#This Row],[Cuenta Bancaria]],Listas!$B:$B,Listas!$A:$A,"") -> Cross Family Trust | D389: Amerant Bank - Cross Family Trust - 4706-USD | E389: =_xlfn.XLOOKUP(tblMovimientos[[#This Row],[Cuenta Bancaria]],Listas!$B:$B,Listas!$C:$C,"") -> Amerant Bank | F389: Ingreso | G389: Ing.Distribucion a socios | H389: =IFERROR(_xlfn.XLOOKUP(G389,Listas!E:E,Listas!F:F,""),"") -> Inversion | I389: =IFERROR(_xlfn.XLOOKUP(G389,Listas!E:E,Listas!G:G,""),"") -> Externo | J389: 150000 | K389: =IF(F389="Ingreso",J389,-J389) -> 150000 | L389: 2026-06 | M389: =SUMIFS('Saldos Iniciales'!$D:$D,'Saldos Iniciales'!$A:$A,C389,'Saldos Iniciales'!$B:$B,D389)+SUMIFS($K$1:$K$1324,$C$1:$C$1324,C389,$D$1:$D$1324,D389,$B$1:$B$1324,"<="&B389) -> 1881717.6 | N389: =IF(tblMovimientos[[#This Row],[Tipo de Movimiento]]="Ingreso",tblMovimientos[[#This Row],[Monto (S/)]],"0") -> 150000 | O389: =IF(tblMovimientos[[#This Row],[Tipo de Movimiento]]="Egreso",tblMovimientos[[#This Row],[Monto (S/)]],"0") -> 0 | P389: =IF(tblMovimientos[[#This Row],[Tipo de Movimiento]]="Ingreso",tblMovimientos[[#This Row],[Ingreso]],-tblMovimientos[[#This Row],[Egreso]]) -> 150000 | Q389: =_xlfn.XLOOKUP(tblMovimientos[[#This Row],[Cuenta Bancaria]],Cuentas!$C:$C,Cuentas!$A:$A,"")&"" -> SSP Group | R389: =_xlfn.XLOOKUP(tblMovimientos[[#This Row],[Cuenta Bancaria]],Cuentas!$C:$C,Cuentas!$B:$B,"",0,-1)&"" -> Trust
B390: 46198 | C390: =_xlfn.XLOOKUP(tblMovimientos[[#This Row],[Cuenta Bancaria]],Listas!$B:$B,Listas!$A:$A,"") -> Cross Family Trust | D390: Amerant Bank - Cross Family Trust - 4706-USD | E390: =_xlfn.XLOOKUP(tblMovimientos[[#This Row],[Cuenta Bancaria]],Listas!$B:$B,Listas!$C:$C,"") -> Amerant Bank | F390: Ingreso | G390: Ing.Distribucion a socios | H390: =IFERROR(_xlfn.XLOOKUP(G390,Listas!E:E,Listas!F:F,""),"") -> Inversion | I390: =IFERROR(_xlfn.XLOOKUP(G390,Listas!E:E,Listas!G:G,""),"") -> Externo | J390: 2380000 | K390: =IF(F390="Ingreso",J390,-J390) -> 2380000 | L390: 2026-06 | M390: =SUMIFS('Saldos Iniciales'!$D:$D,'Saldos Iniciales'!$A:$A,C390,'Saldos Iniciales'!$B:$B,D390)+SUMIFS($K$1:$K$1324,$C$1:$C$1324,C390,$D$1:$D$1324,D390,$B$1:$B$1324,"<="&B390) -> 1881717.6 | N390: =IF(tblMovimientos[[#This Row],[Tipo de Movimiento]]="Ingreso",tblMovimientos[[#This Row],[Monto (S/)]],"0") -> 2380000 | O390: =IF(tblMovimientos[[#This Row],[Tipo de Movimiento]]="Egreso",tblMovimientos[[#This Row],[Monto (S/)]],"0") -> 0 | P390: =IF(tblMovimientos[[#This Row],[Tipo de Movimiento]]="Ingreso",tblMovimientos[[#This Row],[Ingreso]],-tblMovimientos[[#This Row],[Egreso]]) -> 2380000 | Q390: =_xlfn.XLOOKUP(tblMovimientos[[#This Row],[Cuenta Bancaria]],Cuentas!$C:$C,Cuentas!$A:$A,"")&"" -> SSP Group | R390: =_xlfn.XLOOKUP(tblMovimientos[[#This Row],[Cuenta Bancaria]],Cuentas!$C:$C,Cuentas!$B:$B,"",0,-1)&"" -> Trust
B391: 46198 | C391: =_xlfn.XLOOKUP(tblMovimientos[[#This Row],[Cuenta Bancaria]],Listas!$B:$B,Listas!$A:$A,"") -> Cross Family Trust | D391: Amerant Bank - Cross Family Trust - 4706-USD | E391: =_xlfn.XLOOKUP(tblMovimientos[[#This Row],[Cuenta Bancaria]],Listas!$B:$B,Listas!$C:$C,"") -> Amerant Bank | F391: Egreso | G391: Eg.Distribucion a socios (CFT,CCT,CST) | H391: =IFERROR(_xlfn.XLOOKUP(G391,Listas!E:E,Listas!F:F,""),"") -> Inversion | I391: =IFERROR(_xlfn.XLOOKUP(G391,Listas!E:E,Listas!G:G,""),"") -> Interno | J391: 150000 | K391: =IF(F391="Ingreso",J391,-J391) -> -150000 | L391: 2026-06 | M391: =SUMIFS('Saldos Iniciales'!$D:$D,'Saldos Iniciales'!$A:$A,C391,'Saldos Iniciales'!$B:$B,D391)+SUMIFS($K$1:$K$1324,$C$1:$C$1324,C391,$D$1:$D$1324,D391,$B$1:$B$1324,"<="&B391) -> 1881717.6 | N391: =IF(tblMovimientos[[#This Row],[Tipo de Movimiento]]="Ingreso",tblMovimientos[[#This Row],[Monto (S/)]],"0") -> 0 | O391: =IF(tblMovimientos[[#This Row],[Tipo de Movimiento]]="Egreso",tblMovimientos[[#This Row],[Monto (S/)]],"0") -> 150000 | P391: =IF(tblMovimientos[[#This Row],[Tipo de Movimiento]]="Ingreso",tblMovimientos[[#This Row],[Ingreso]],-tblMovimientos[[#This Row],[Egreso]]) -> -150000 | Q391: =_xlfn.XLOOKUP(tblMovimientos[[#This Row],[Cuenta Bancaria]],Cuentas!$C:$C,Cuentas!$A:$A,"")&"" -> SSP Group | R391: =_xlfn.XLOOKUP(tblMovimientos[[#This Row],[Cuenta Bancaria]],Cuentas!$C:$C,Cuentas!$B:$B,"",0,-1)&"" -> Trust
B392: 46198 | C392: =_xlfn.XLOOKUP(tblMovimientos[[#This Row],[Cuenta Bancaria]],Listas!$B:$B,Listas!$A:$A,"") -> Cross Family Trust | D392: Amerant Bank - Cross Family Trust - 4706-USD | E392: =_xlfn.XLOOKUP(tblMovimientos[[#This Row],[Cuenta Bancaria]],Listas!$B:$B,Listas!$C:$C,"") -> Amerant Bank | F392: Egreso | G392: Eg.Inversiones Aporte de Capital a Empresas relacionadas | H392: =IFERROR(_xlfn.XLOOKUP(G392,Listas!E:E,Listas!F:F,""),"") -> Inversion | I392: =IFERROR(_xlfn.XLOOKUP(G392,Listas!E:E,Listas!G:G,""),"") -> Interno | J392: 500000 | K392: =IF(F392="Ingreso",J392,-J392) -> -500000 | L392: 2026-06 | M392: =SUMIFS('Saldos Iniciales'!$D:$D,'Saldos Iniciales'!$A:$A,C392,'Saldos Iniciales'!$B:$B,D392)+SUMIFS($K$1:$K$1324,$C$1:$C$1324,C392,$D$1:$D$1324,D392,$B$1:$B$1324,"<="&B392) -> 1881717.6 | N392: =IF(tblMovimientos[[#This Row],[Tipo de Movimiento]]="Ingreso",tblMovimientos[[#This Row],[Monto (S/)]],"0") -> 0 | O392: =IF(tblMovimientos[[#This Row],[Tipo de Movimiento]]="Egreso",tblMovimientos[[#This Row],[Monto (S/)]],"0") -> 500000 | P392: =IF(tblMovimientos[[#This Row],[Tipo de Movimiento]]="Ingreso",tblMovimientos[[#This Row],[Ingreso]],-tblMovimientos[[#This Row],[Egreso]]) -> -500000 | Q392: =_xlfn.XLOOKUP(tblMovimientos[[#This Row],[Cuenta Bancaria]],Cuentas!$C:$C,Cuentas!$A:$A,"")&"" -> SSP Group | R392: =_xlfn.XLOOKUP(tblMovimientos[[#This Row],[Cuenta Bancaria]],Cuentas!$C:$C,Cuentas!$B:$B,"",0,-1)&"" -> Trust
B393: 46198 | C393: =_xlfn.XLOOKUP(tblMovimientos[[#This Row],[Cuenta Bancaria]],Listas!$B:$B,Listas!$A:$A,"") -> SSP Capital | D393: Amerant Bank - SSP Capital - 4706-USD | E393: =_xlfn.XLOOKUP(tblMovimientos[[#This Row],[Cuenta Bancaria]],Listas!$B:$B,Listas!$C:$C,"") -> Amerant Bank | F393: Ingreso | G393: Ing.Deuda Recibida de Empresas relacionadas | H393: =IFERROR(_xlfn.XLOOKUP(G393,Listas!E:E,Listas!F:F,""),"") -> Financiamiento | I393: =IFERROR(_xlfn.XLOOKUP(G393,Listas!E:E,Listas!G:G,""),"") -> Interno | J393: 1850000 | K393: =IF(F393="Ingreso",J393,-J393) -> 1850000 | L393: 2026-06 | M393: =SUMIFS('Saldos Iniciales'!$D:$D,'Saldos Iniciales'!$A:$A,C393,'Saldos Iniciales'!$B:$B,D393)+SUMIFS($K$1:$K$1324,$C$1:$C$1324,C393,$D$1:$D$1324,D393,$B$1:$B$1324,"<="&B393) -> 1109351.6 | N393: =IF(tblMovimientos[[#This Row],[Tipo de Movimiento]]="Ingreso",tblMovimientos[[#This Row],[Monto (S/)]],"0") -> 1850000 | O393: =IF(tblMovimientos[[#This Row],[Tipo de Movimiento]]="Egreso",tblMovimientos[[#This Row],[Monto (S/)]],"0") -> 0 | P393: =IF(tblMovimientos[[#This Row],[Tipo de Movimiento]]="Ingreso",tblMovimientos[[#This Row],[Ingreso]],-tblMovimientos[[#This Row],[Egreso]]) -> 1850000 | Q393: =_xlfn.XLOOKUP(tblMovimientos[[#This Row],[Cuenta Bancaria]],Cuentas!$C:$C,Cuentas!$A:$A,"")&"" -> SSP Group | R393: =_xlfn.XLOOKUP(tblMovimientos[[#This Row],[Cuenta Bancaria]],Cuentas!$C:$C,Cuentas!$B:$B,"",0,-1)&""
B394: 46198 | C394: =_xlfn.XLOOKUP(tblMovimientos[[#This Row],[Cuenta Bancaria]],Listas!$B:$B,Listas!$A:$A,"") -> SSP Capital | D394: Amerant Bank - SSP Capital - 4706-USD | E394: =_xlfn.XLOOKUP(tblMovimientos[[#This Row],[Cuenta Bancaria]],Listas!$B:$B,Listas!$C:$C,"") -> Amerant Bank | F394: Egreso | G394: Eg.Deuda Terceros (Intereses) | H394: =IFERROR(_xlfn.XLOOKUP(G394,Listas!E:E,Listas!F:F,""),"") -> Financiamiento | I394: =IFERROR(_xlfn.XLOOKUP(G394,Listas!E:E,Listas!G:G,""),"") -> Externo | J394: 4071.45 | K394: =IF(F394="Ingreso",J394,-J394) -> -4071.45 | L394: 2026-06 | M394: =SUMIFS('Saldos Iniciales'!$D:$D,'Saldos Iniciales'!$A:$A,C394,'Saldos Iniciales'!$B:$B,D394)+SUMIFS($K$1:$K$1324,$C$1:$C$1324,C394,$D$1:$D$1324,D394,$B$1:$B$1324,"<="&B394) -> 1109351.6 | N394: =IF(tblMovimientos[[#This Row],[Tipo de Movimiento]]="Ingreso",tblMovimientos[[#This Row],[Monto (S/)]],"0") -> 0 | O394: =IF(tblMovimientos[[#This Row],[Tipo de Movimiento]]="Egreso",tblMovimientos[[#This Row],[Monto (S/)]],"0") -> 4071.45 | P394: =IF(tblMovimientos[[#This Row],[Tipo de Movimiento]]="Ingreso",tblMovimientos[[#This Row],[Ingreso]],-tblMovimientos[[#This Row],[Egreso]]) -> -4071.45 | Q394: =_xlfn.XLOOKUP(tblMovimientos[[#This Row],[Cuenta Bancaria]],Cuentas!$C:$C,Cuentas!$A:$A,"")&"" -> SSP Group | R394: =_xlfn.XLOOKUP(tblMovimientos[[#This Row],[Cuenta Bancaria]],Cuentas!$C:$C,Cuentas!$B:$B,"",0,-1)&""
... B412: 46198 | C412: =_xlfn.XLOOKUP(tblMovimientos[[#This Row],[Cuenta Bancaria]],Listas!$B:$B,Listas!$A:$A,"") -> Go Blue | D412: Amerant Bank - Go Blue - 8206-USD | E412: =_xlfn.XLOOKUP(tblMovimientos[[#This Row],[Cuenta Bancaria]],Listas!$B:$B,Listas!$C:$C,"") -> Amerant Bank | F412: Egreso | G412: Eg.Gastos Bancarios | H412: =IFERROR(_xlfn.XLOOKUP(G412,Listas!E:E,Listas!F:F,""),"") -> Operativo | I412: =IFERROR(_xlfn.XLOOKUP(G412,Listas!E:E,Listas!G:G,""),"") -> Externo | J412: 15 | K412: =IF(F412="Ingreso",J412,-J412) -> -15 | L412: 2026-06 | M412: =SUMIFS('Saldos Iniciales'!$D:$D,'Saldos Iniciales'!$A:$A,C412,'Saldos Iniciales'!$B:$B,D412)+SUMIFS($K$1:$K$1324,$C$1:$C$1324,C412,$D$1:$D$1324,D412,$B$1:$B$1324,"<="&B412) -> 32732.08 | N412: =IF(tblMovimientos[[#This Row],[Tipo de Movimiento]]="Ingreso",tblMovimientos[[#This Row],[Monto (S/)]],"0") -> 0 | O412: =IF(tblMovimientos[[#This Row],[Tipo de Movimiento]]="Egreso",tblMovimientos[[#This Row],[Monto (S/)]],"0") -> 15 | P412: =IF(tblMovimientos[[#This Row],[Tipo de Movimiento]]="Ingreso",tblMovimientos[[#This Row],[Ingreso]],-tblMovimientos[[#This Row],[Egreso]]) -> -15 | Q412: =_xlfn.XLOOKUP(tblMovimientos[[#This Row],[Cuenta Bancaria]],Cuentas!$C:$C,Cuentas!$A:$A,"")&"" -> SSP Group | R412: =_xlfn.XLOOKUP(tblMovimientos[[#This Row],[Cuenta Bancaria]],Cuentas!$C:$C,Cuentas!$B:$B,"",0,-1)&""
B413: 46198 | C413: =_xlfn.XLOOKUP(tblMovimientos[[#This Row],[Cuenta Bancaria]],Listas!$B:$B,Listas!$A:$A,"") -> Cross Security Trust | D413: Bank of America - Cross Security Trust - 6642-USD | E413: =_xlfn.XLOOKUP(tblMovimientos[[#This Row],[Cuenta Bancaria]],Listas!$B:$B,Listas!$C:$C,"") -> Bank of America | F413: Ingreso | G413: Ing.Distribucion a socios | J413: 310000 | K413: =IF(F413="Ingreso",J413,-J413) -> 310000 | L413: 2026-06 | M413: =SUMIFS('Saldos Iniciales'!$D:$D,'Saldos Iniciales'!$A:$A,C413,'Saldos Iniciales'!$B:$B,D413)+SUMIFS($K$1:$K$1324,$C$1:$C$1324,C413,$D$1:$D$1324,D413,$B$1:$B$1324,"<="&B413) -> 330375.99 | N413: =IF(tblMovimientos[[#This Row],[Tipo de Movimiento]]="Ingreso",tblMovimientos[[#This Row],[Monto (S/)]],"0") -> 310000 | O413: =IF(tblMovimientos[[#This Row],[Tipo de Movimiento]]="Egreso",tblMovimientos[[#This Row],[Monto (S/)]],"0") -> 0 | P413: =IF(tblMovimientos[[#This Row],[Tipo de Movimiento]]="Ingreso",tblMovimientos[[#This Row],[Ingreso]],-tblMovimientos[[#This Row],[Egreso]]) -> 310000 | Q413: =_xlfn.XLOOKUP(tblMovimientos[[#This Row],[Cuenta Bancaria]],Cuentas!$C:$C,Cuentas!$A:$A,"")&"" -> SSP Group | R413: =_xlfn.XLOOKUP(tblMovimientos[[#This Row],[Cuenta Bancaria]],Cuentas!$C:$C,Cuentas!$B:$B,"",0,-1)&"" -> Trust
B414: 46199 | C414: =_xlfn.XLOOKUP(tblMovimientos[[#This Row],[Cuenta Bancaria]],Listas!$B:$B,Listas!$A:$A,"") -> SSP Capital | D414: Bank of America - SSP Capital - 2580-USD | E414: =_xlfn.XLOOKUP(tblMovimientos[[#This Row],[Cuenta Bancaria]],Listas!$B:$B,Listas!$C:$C,"") -> Bank of America | F414: Egreso | G414: Eg.Gastos Operativos (Proveedor) | H414: =IFERROR(_xlfn.XLOOKUP(G414,Listas!E:E,Listas!F:F,""),"") -> Operativo | I414: =IFERROR(_xlfn.XLOOKUP(G414,Listas!E:E,Listas!G:G,""),"") -> Externo | J414: 762.99 | K414: =IF(F414="Ingreso",J414,-J414) -> -762.99 | L414: 2026-06 | M414: =SUMIFS('Saldos Iniciales'!$D:$D,'Saldos Iniciales'!$A:$A,C414,'Saldos Iniciales'!$B:$B,D414)+SUMIFS($K$1:$K$1324,$C$1:$C$1324,C414,$D$1:$D$1324,D414,$B$1:$B$1324,"<="&B414) -> 8497 | N414: =IF(tblMovimientos[[#This Row],[Tipo de Movimiento]]="Ingreso",tblMovimientos[[#This Row],[Monto (S/)]],"0") -> 0 | O414: =IF(tblMovimientos[[#This Row],[Tipo de Movimiento]]="Egreso",tblMovimientos[[#This Row],[Monto (S/)]],"0") -> 762.99 | P414: =IF(tblMovimientos[[#This Row],[Tipo de Movimiento]]="Ingreso",tblMovimientos[[#This Row],[Ingreso]],-tblMovimientos[[#This Row],[Egreso]]) -> -762.99 | Q414: =_xlfn.XLOOKUP(tblMovimientos[[#This Row],[Cuenta Bancaria]],Cuentas!$C:$C,Cuentas!$A:$A,"")&"" -> SSP Group | R414: =_xlfn.XLOOKUP(tblMovimientos[[#This Row],[Cuenta Bancaria]],Cuentas!$C:$C,Cuentas!$B:$B,"",0,-1)&""
B415: 46199 | C415: =_xlfn.XLOOKUP(tblMovimientos[[#This Row],[Cuenta Bancaria]],Listas!$B:$B,Listas!$A:$A,"") -> CFT Group | D415: Bank of America - CFT Group - 4415-USD | E415: =_xlfn.XLOOKUP(tblMovimientos[[#This Row],[Cuenta Bancaria]],Listas!$B:$B,Listas!$C:$C,"") -> Bank of America | F415: Egreso | G415: Eg.Deuda Relacionadas (Intereses) | H415: =IFERROR(_xlfn.XLOOKUP(G415,Listas!E:E,Listas!F:F,""),"") -> Financiamiento | I415: =IFERROR(_xlfn.XLOOKUP(G415,Listas!E:E,Listas!G:G,""),"") -> Externo | J415: 850 | K415: =IF(F415="Ingreso",J415,-J415) -> -850 | L415: 2026-06 | M415: =SUMIFS('Saldos Iniciales'!$D:$D,'Saldos Iniciales'!$A:$A,C415,'Saldos Iniciales'!$B:$B,D415)+SUMIFS($K$1:$K$1324,$C$1:$C$1324,C415,$D$1:$D$1324,D415,$B$1:$B$1324,"<="&B415) -> 28413.32 | N415: =IF(tblMovimientos[[#This Row],[Tipo de Movimiento]]="Ingreso",tblMovimientos[[#This Row],[Monto (S/)]],"0") -> 0 | O415: =IF(tblMovimientos[[#This Row],[Tipo de Movimiento]]="Egreso",tblMovimientos[[#This Row],[Monto (S/)]],"0") -> 850 | P415: =IF(tblMovimientos[[#This Row],[Tipo de Movimiento]]="Ingreso",tblMovimientos[[#This Row],[Ingreso]],-tblMovimientos[[#This Row],[Egreso]]) -> -850 | Q415: =_xlfn.XLOOKUP(tblMovimientos[[#This Row],[Cuenta Bancaria]],Cuentas!$C:$C,Cuentas!$A:$A,"")&"" -> SSP Group | R415: =_xlfn.XLOOKUP(tblMovimientos[[#This Row],[Cuenta Bancaria]],Cuentas!$C:$C,Cuentas!$B:$B,"",0,-1)&""
B416: 46199 | C416: =_xlfn.XLOOKUP(tblMovimientos[[#This Row],[Cuenta Bancaria]],Listas!$B:$B,Listas!$A:$A,"") -> CFT Group | D416: Bank of America - CFT Group - 4415-USD | E416: =_xlfn.XLOOKUP(tblMovimientos[[#This Row],[Cuenta Bancaria]],Listas!$B:$B,Listas!$C:$C,"") -> Bank of America | F416: Egreso | G416: Eg.Gastos Bancarios | H416: =IFERROR(_xlfn.XLOOKUP(G416,Listas!E:E,Listas!F:F,""),"") -> Operativo | I416: =IFERROR(_xlfn.XLOOKUP(G416,Listas!E:E,Listas!G:G,""),"") -> Externo | J416: 30 | K416: =IF(F416="Ingreso",J416,-J416) -> -30 | L416: 2026-06 | M416: =SUMIFS('Saldos Iniciales'!$D:$D,'Saldos Iniciales'!$A:$A,C416,'Saldos Iniciales'!$B:$B,D416)+SUMIFS($K$1:$K$1324,$C$1:$C$1324,C416,$D$1:$D$1324,D416,$B$1:$B$1324,"<="&B416) -> 28413.32 | N416: =IF(tblMovimientos[[#This Row],[Tipo de Movimiento]]="Ingreso",tblMovimientos[[#This Row],[Monto (S/)]],"0") -> 0 | O416: =IF(tblMovimientos[[#This Row],[Tipo de Movimiento]]="Egreso",tblMovimientos[[#This Row],[Monto (S/)]],"0") -> 30 | P416: =IF(tblMovimientos[[#This Row],[Tipo de Movimiento]]="Ingreso",tblMovimientos[[#This Row],[Ingreso]],-tblMovimientos[[#This Row],[Egreso]]) -> -30 | Q416: =_xlfn.XLOOKUP(tblMovimientos[[#This Row],[Cuenta Bancaria]],Cuentas!$C:$C,Cuentas!$A:$A,"")&"" -> SSP Group | R416: =_xlfn.XLOOKUP(tblMovimientos[[#This Row],[Cuenta Bancaria]],Cuentas!$C:$C,Cuentas!$B:$B,"",0,-1)&""
B417: 46199 | C417: =_xlfn.XLOOKUP(tblMovimientos[[#This Row],[Cuenta Bancaria]],Listas!$B:$B,Listas!$A:$A,"") -> 3628 Thomas Ave | D417: Bank of America - 3628 Thomas Ave - 4406-USD | E417: =_xlfn.XLOOKUP(tblMovimientos[[#This Row],[Cuenta Bancaria]],Listas!$B:$B,Listas!$C:$C,"") -> Bank of America | F417: Egreso | G417: Eg.Gastos Bancarios | H417: =IFERROR(_xlfn.XLOOKUP(G417,Listas!E:E,Listas!F:F,""),"") -> Operativo | I417: =IFERROR(_xlfn.XLOOKUP(G417,Listas!E:E,Listas!G:G,""),"") -> Externo | J417: 15 | K417: =IF(F417="Ingreso",J417,-J417) -> -15 | L417: 2026-06 | M417: =SUMIFS('Saldos Iniciales'!$D:$D,'Saldos Iniciales'!$A:$A,C417,'Saldos Iniciales'!$B:$B,D417)+SUMIFS($K$1:$K$1324,$C$1:$C$1324,C417,$D$1:$D$1324,D417,$B$1:$B$1324,"<="&B417) -> 28458.6 | N417: =IF(tblMovimientos[[#This Row],[Tipo de Movimiento]]="Ingreso",tblMovimientos[[#This Row],[Monto (S/)]],"0") -> 0 | O417: =IF(tblMovimientos[[#This Row],[Tipo de Movimiento]]="Egreso",tblMovimientos[[#This Row],[Monto (S/)]],"0") -> 15 | P417: =IF(tblMovimientos[[#This Row],[Tipo de Movimiento]]="Ingreso",tblMovimientos[[#This Row],[Ingreso]],-tblMovimientos[[#This Row],[Egreso]]) -> -15 | Q417: =_xlfn.XLOOKUP(tblMovimientos[[#This Row],[Cuenta Bancaria]],Cuentas!$C:$C,Cuentas!$A:$A,"")&"" -> SSP Group | R417: =_xlfn.XLOOKUP(tblMovimientos[[#This Row],[Cuenta Bancaria]],Cuentas!$C:$C,Cuentas!$B:$B,"",0,-1)&""
B418: 46199 | C418: =_xlfn.XLOOKUP(tblMovimientos[[#This Row],[Cuenta Bancaria]],Listas!$B:$B,Listas!$A:$A,"") -> CFT Group | D418: Amerant Bank - CFT Group - 1906-USD | E418: =_xlfn.XLOOKUP(tblMovimientos[[#This Row],[Cuenta Bancaria]],Listas!$B:$B,Listas!$C:$C,"") -> Amerant Bank | F418: Egreso | G418: Eg.Deuda Terceros (Intereses) | H418: =IFERROR(_xlfn.XLOOKUP(G418,Listas!E:E,Listas!F:F,""),"") -> Financiamiento | I418: =IFERROR(_xlfn.XLOOKUP(G418,Listas!E:E,Listas!G:G,""),"") -> Externo | J418: 10000 | K418: =IF(F418="Ingreso",J418,-J418) -> -10000 | L418: 2026-06 | M418: =SUMIFS('Saldos Iniciales'!$D:$D,'Saldos Iniciales'!$A:$A,C418,'Saldos Iniciales'!$B:$B,D418)+SUMIFS($K$1:$K$1324,$C$1:$C$1324,C418,$D$1:$D$1324,D418,$B$1:$B$1324,"<="&B418) -> 6254386.4 | N418: =IF(tblMovimientos[[#This Row],[Tipo de Movimiento]]="Ingreso",tblMovimientos[[#This Row],[Monto (S/)]],"0") -> 0 | O418: =IF(tblMovimientos[[#This Row],[Tipo de Movimiento]]="Egreso",tblMovimientos[[#This Row],[Monto (S/)]],"0") -> 10000 | P418: =IF(tblMovimientos[[#This Row],[Tipo de Movimiento]]="Ingreso",tblMovimientos[[#This Row],[Ingreso]],-tblMovimientos[[#This Row],[Egreso]]) -> -10000 | Q418: =_xlfn.XLOOKUP(tblMovimientos[[#This Row],[Cuenta Bancaria]],Cuentas!$C:$C,Cuentas!$A:$A,"")&"" -> SSP Group | R418: =_xlfn.XLOOKUP(tblMovimientos[[#This Row],[Cuenta Bancaria]],Cuentas!$C:$C,Cuentas!$B:$B,"",0,-1)&""
B419: 46199 | C419: =_xlfn.XLOOKUP(tblMovimientos[[#This Row],[Cuenta Bancaria]],Listas!$B:$B,Listas!$A:$A,"") -> Cross Family Trust | D419: Amerant Bank - Cross Family Trust - 4706-USD | E419: =_xlfn.XLOOKUP(tblMovimientos[[#This Row],[Cuenta Bancaria]],Listas!$B:$B,Listas!$C:$C,"") -> Amerant Bank | F419: Egreso | G419: Eg.Distribucion a socios (CFT,CCT,CST) | H419: =IFERROR(_xlfn.XLOOKUP(G419,Listas!E:E,Listas!F:F,""),"") -> Inversion | I419: =IFERROR(_xlfn.XLOOKUP(G419,Listas!E:E,Listas!G:G,""),"") -> Interno | J419: 600000 | K419: =IF(F419="Ingreso",J419,-J419) -> -600000 | L419: 2026-06 | M419: =SUMIFS('Saldos Iniciales'!$D:$D,'Saldos Iniciales'!$A:$A,C419,'Saldos Iniciales'!$B:$B,D419)+SUMIFS($K$1:$K$1324,$C$1:$C$1324,C419,$D$1:$D$1324,D419,$B$1:$B$1324,"<="&B419) -> 1281717.6 | N419: =IF(tblMovimientos[[#This Row],[Tipo de Movimiento]]="Ingreso",tblMovimientos[[#This Row],[Monto (S/)]],"0") -> 0 | O419: =IF(tblMovimientos[[#This Row],[Tipo de Movimiento]]="Egreso",tblMovimientos[[#This Row],[Monto (S/)]],"0") -> 600000 | P419: =IF(tblMovimientos[[#This Row],[Tipo de Movimiento]]="Ingreso",tblMovimientos[[#This Row],[Ingreso]],-tblMovimientos[[#This Row],[Egreso]]) -> -600000 | Q419: =_xlfn.XLOOKUP(tblMovimientos[[#This Row],[Cuenta Bancaria]],Cuentas!$C:$C,Cuentas!$A:$A,"")&"" -> SSP Group | R419: =_xlfn.XLOOKUP(tblMovimientos[[#This Row],[Cuenta Bancaria]],Cuentas!$C:$C,Cuentas!$B:$B,"",0,-1)&"" -> Trust
B420: 46199 | C420: =_xlfn.XLOOKUP(tblMovimientos[[#This Row],[Cuenta Bancaria]],Listas!$B:$B,Listas!$A:$A,"") -> Go Blue | D420: Amerant Bank - Go Blue - 8206-USD | E420: =_xlfn.XLOOKUP(tblMovimientos[[#This Row],[Cuenta Bancaria]],Listas!$B:$B,Listas!$C:$C,"") -> Amerant Bank | F420: Egreso | G420: Eg.Gastos Operativos (Proveedor) | H420: =IFERROR(_xlfn.XLOOKUP(G420,Listas!E:E,Listas!F:F,""),"") -> Operativo | I420: =IFERROR(_xlfn.XLOOKUP(G420,Listas!E:E,Listas!G:G,""),"") -> Externo | J420: 3091.79 | K420: =IF(F420="Ingreso",J420,-J420) -> -3091.79 | L420: 2026-06 | M420: =SUMIFS('Saldos Iniciales'!$D:$D,'Saldos Iniciales'!$A:$A,C420,'Saldos Iniciales'!$B:$B,D420)+SUMIFS($K$1:$K$1324,$C$1:$C$1324,C420,$D$1:$D$1324,D420,$B$1:$B$1324,"<="&B420) -> 24625.29 | N420: =IF(tblMovimientos[[#This Row],[Tipo de Movimiento]]="Ingreso",tblMovimientos[[#This Row],[Monto (S/)]],"0") -> 0 | O420: =IF(tblMovimientos[[#This Row],[Tipo de Movimiento]]="Egreso",tblMovimientos[[#This Row],[Monto (S/)]],"0") -> 3091.79 | P420: =IF(tblMovimientos[[#This Row],[Tipo de Movimiento]]="Ingreso",tblMovimientos[[#This Row],[Ingreso]],-tblMovimientos[[#This Row],[Egreso]]) -> -3091.79 | Q420: =_xlfn.XLOOKUP(tblMovimientos[[#This Row],[Cuenta Bancaria]],Cuentas!$C:$C,Cuentas!$A:$A,"")&"" -> SSP Group | R420: =_xlfn.XLOOKUP(tblMovimientos[[#This Row],[Cuenta Bancaria]],Cuentas!$C:$C,Cuentas!$B:$B,"",0,-1)&""
B421: 46199 | C421: =_xlfn.XLOOKUP(tblMovimientos[[#This Row],[Cuenta Bancaria]],Listas!$B:$B,Listas!$A:$A,"") -> Go Blue | D421: Amerant Bank - Go Blue - 8206-USD | E421: =_xlfn.XLOOKUP(tblMovimientos[[#This Row],[Cuenta Bancaria]],Listas!$B:$B,Listas!$C:$C,"") -> Amerant Bank | F421: Egreso | G421: Eg.Gastos Bancarios | H421: =IFERROR(_xlfn.XLOOKUP(G421,Listas!E:E,Listas!F:F,""),"") -> Operativo | I421: =IFERROR(_xlfn.XLOOKUP(G421,Listas!E:E,Listas!G:G,""),"") -> Externo | J421: 15 | K421: =IF(F421="Ingreso",J421,-J421) -> -15 | L421: 2026-06 | M421: =SUMIFS('Saldos Iniciales'!$D:$D,'Saldos Iniciales'!$A:$A,C421,'Saldos Iniciales'!$B:$B,D421)+SUMIFS($K$1:$K$1324,$C$1:$C$1324,C421,$D$1:$D$1324,D421,$B$1:$B$1324,"<="&B421) -> 24625.29 | N421: =IF(tblMovimientos[[#This Row],[Tipo de Movimiento]]="Ingreso",tblMovimientos[[#This Row],[Monto (S/)]],"0") -> 0 | O421: =IF(tblMovimientos[[#This Row],[Tipo de Movimiento]]="Egreso",tblMovimientos[[#This Row],[Monto (S/)]],"0") -> 15 | P421: =IF(tblMovimientos[[#This Row],[Tipo de Movimiento]]="Ingreso",tblMovimientos[[#This Row],[Ingreso]],-tblMovimientos[[#This Row],[Egreso]]) -> -15 | Q421: =_xlfn.XLOOKUP(tblMovimientos[[#This Row],[Cuenta Bancaria]],Cuentas!$C:$C,Cuentas!$A:$A,"")&"" -> SSP Group | R421: =_xlfn.XLOOKUP(tblMovimientos[[#This Row],[Cuenta Bancaria]],Cuentas!$C:$C,Cuentas!$B:$B,"",0,-1)&""
B422: 46199 | C422: =_xlfn.XLOOKUP(tblMovimientos[[#This Row],[Cuenta Bancaria]],Listas!$B:$B,Listas!$A:$A,"") -> Go Blue | D422: Amerant Bank - Go Blue - 8206-USD | E422: =_xlfn.XLOOKUP(tblMovimientos[[#This Row],[Cuenta Bancaria]],Listas!$B:$B,Listas!$C:$C,"") -> Amerant Bank | F422: Egreso | H422: =IFERROR(_xlfn.XLOOKUP(G422,Listas!E:E,Listas!F:F,""),"") -> 0 | I422: =IFERROR(_xlfn.XLOOKUP(G422,Listas!E:E,Listas!G:G,""),"") -> 0 | J422: 5000 | K422: =IF(F422="Ingreso",J422,-J422) -> -5000 | L422: 2026-06 | M422: =SUMIFS('Saldos Iniciales'!$D:$D,'Saldos Iniciales'!$A:$A,C422,'Saldos Iniciales'!$B:$B,D422)+SUMIFS($K$1:$K$1324,$C$1:$C$1324,C422,$D$1:$D$1324,D422,$B$1:$B$1324,"<="&B422) -> 24625.29 | N422: =IF(tblMovimientos[[#This Row],[Tipo de Movimiento]]="Ingreso",tblMovimientos[[#This Row],[Monto (S/)]],"0") -> 0 | O422: =IF(tblMovimientos[[#This Row],[Tipo de Movimiento]]="Egreso",tblMovimientos[[#This Row],[Monto (S/)]],"0") -> 5000 | P422: =IF(tblMovimientos[[#This Row],[Tipo de Movimiento]]="Ingreso",tblMovimientos[[#This Row],[Ingreso]],-tblMovimientos[[#This Row],[Egreso]]) -> -5000 | Q422: =_xlfn.XLOOKUP(tblMovimientos[[#This Row],[Cuenta Bancaria]],Cuentas!$C:$C,Cuentas!$A:$A,"")&"" -> SSP Group | R422: =_xlfn.XLOOKUP(tblMovimientos[[#This Row],[Cuenta Bancaria]],Cuentas!$C:$C,Cuentas!$B:$B,"",0,-1)&""
B423: 46202 | C423: =_xlfn.XLOOKUP(tblMovimientos[[#This Row],[Cuenta Bancaria]],Listas!$B:$B,Listas!$A:$A,"") -> A&M Imports | D423: Bank of America - A&M Imports - 3797-USD | E423: =_xlfn.XLOOKUP(tblMovimientos[[#This Row],[Cuenta Bancaria]],Listas!$B:$B,Listas!$C:$C,"") -> Bank of America | F423: Ingreso | G423: Ing.Devolucion Gastos Operativos (Proveedor) | H423: =IFERROR(_xlfn.XLOOKUP(G423,Listas!E:E,Listas!F:F,""),"") -> Operativo | I423: =IFERROR(_xlfn.XLOOKUP(G423,Listas!E:E,Listas!G:G,""),"") -> Externo | J423: 16978.9 | K423: =IF(F423="Ingreso",J423,-J423) -> 16978.9 | L423: 2026-06 | M423: =SUMIFS('Saldos Iniciales'!$D:$D,'Saldos Iniciales'!$A:$A,C423,'Saldos Iniciales'!$B:$B,D423)+SUMIFS($K$1:$K$1324,$C$1:$C$1324,C423,$D$1:$D$1324,D423,$B$1:$B$1324,"<="&B423) -> 489745.63 | N423: =IF(tblMovimientos[[#This Row],[Tipo de Movimiento]]="Ingreso",tblMovimientos[[#This Row],[Monto (S/)]],"0") -> 16978.9 | O423: =IF(tblMovimientos[[#This Row],[Tipo de Movimiento]]="Egreso",tblMovimientos[[#This Row],[Monto (S/)]],"0") -> 0 | P423: =IF(tblMovimientos[[#This Row],[Tipo de Movimiento]]="Ingreso",tblMovimientos[[#This Row],[Ingreso]],-tblMovimientos[[#This Row],[Egreso]]) -> 16978.9 | Q423: =_xlfn.XLOOKUP(tblMovimientos[[#This Row],[Cuenta Bancaria]],Cuentas!$C:$C,Cuentas!$A:$A,"")&"" -> SSP Group | R423: =_xlfn.XLOOKUP(tblMovimientos[[#This Row],[Cuenta Bancaria]],Cuentas!$C:$C,Cuentas!$B:$B,"",0,-1)&""
B424: 46202 | C424: =_xlfn.XLOOKUP(tblMovimientos[[#This Row],[Cuenta Bancaria]],Listas!$B:$B,Listas!$A:$A,"") -> CFT Group | D424: Bank of America - CFT Group - 4415-USD | E424: =_xlfn.XLOOKUP(tblMovimientos[[#This Row],[Cuenta Bancaria]],Listas!$B:$B,Listas!$C:$C,"") -> Bank of America | F424: Ingreso | G424: Ing.Intereses Recibidos de Unidad de Negocio | H424: =IFERROR(_xlfn.XLOOKUP(G424,Listas!E:E,Listas!F:F,""),"") -> Operativo | I424: =IFERROR(_xlfn.XLOOKUP(G424,Listas!E:E,Listas!G:G,""),"") -> Externo | J424: 6021.16 | K424: =IF(F424="Ingreso",J424,-J424) -> 6021.16 | L424: 2026-06 | M424: =SUMIFS('Saldos Iniciales'!$D:$D,'Saldos Iniciales'!$A:$A,C424,'Saldos Iniciales'!$B:$B,D424)+SUMIFS($K$1:$K$1324,$C$1:$C$1324,C424,$D$1:$D$1324,D424,$B$1:$B$1324,"<="&B424) -> 39532.42 | N424: =IF(tblMovimientos[[#This Row],[Tipo de Movimiento]]="Ingreso",tblMovimientos[[#This Row],[Monto (S/)]],"0") -> 6021.16 | O424: =IF(tblMovimientos[[#This Row],[Tipo de Movimiento]]="Egreso",tblMovimientos[[#This Row],[Monto (S/)]],"0") -> 0 | P424: =IF(tblMovimientos[[#This Row],[Tipo de Movimiento]]="Ingreso",tblMovimientos[[#This Row],[Ingreso]],-tblMovimientos[[#This Row],[Egreso]]) -> 6021.16 | Q424: =_xlfn.XLOOKUP(tblMovimientos[[#This Row],[Cuenta Bancaria]],Cuentas!$C:$C,Cuentas!$A:$A,"")&"" -> SSP Group | R424: =_xlfn.XLOOKUP(tblMovimientos[[#This Row],[Cuenta Bancaria]],Cuentas!$C:$C,Cuentas!$B:$B,"",0,-1)&""
B425: 46202 | C425: =_xlfn.XLOOKUP(tblMovimientos[[#This Row],[Cuenta Bancaria]],Listas!$B:$B,Listas!$A:$A,"") -> CFT Group | D425: Bank of America - CFT Group - 4415-USD | E425: =_xlfn.XLOOKUP(tblMovimientos[[#This Row],[Cuenta Bancaria]],Listas!$B:$B,Listas!$C:$C,"") -> Bank of America | F425: Ingreso | G425: Ing.Intereses Recibidos de Unidad de Negocio | H425: =IFERROR(_xlfn.XLOOKUP(G425,Listas!E:E,Listas!F:F,""),"") -> Operativo | I425: =IFERROR(_xlfn.XLOOKUP(G425,Listas!E:E,Listas!G:G,""),"") -> Externo | J425: 5097.94 | K425: =IF(F425="Ingreso",J425,-J425) -> 5097.94 | L425: 2026-06 | M425: =SUMIFS('Saldos Iniciales'!$D:$D,'Saldos Iniciales'!$A:$A,C425,'Saldos Iniciales'!$B:$B,D425)+SUMIFS($K$1:$K$1324,$C$1:$C$1324,C425,$D$1:$D$1324,D425,$B$1:$B$1324,"<="&B425) -> 39532.42 | N425: =IF(tblMovimientos[[#This Row],[Tipo de Movimiento]]="Ingreso",tblMovimientos[[#This Row],[Monto (S/)]],"0") -> 5097.94 | O425: =IF(tblMovimientos[[#This Row],[Tipo de Movimiento]]="Egreso",tblMovimientos[[#This Row],[Monto (S/)]],"0") -> 0 | P425: =IF(tblMovimientos[[#This Row],[Tipo de Movimiento]]="Ingreso",tblMovimientos[[#This Row],[Ingreso]],-tblMovimientos[[#This Row],[Egreso]]) -> 5097.94 | Q425: =_xlfn.XLOOKUP(tblMovimientos[[#This Row],[Cuenta Bancaria]],Cuentas!$C:$C,Cuentas!$A:$A,"")&"" -> SSP Group | R425: =_xlfn.XLOOKUP(tblMovimientos[[#This Row],[Cuenta Bancaria]],Cuentas!$C:$C,Cuentas!$B:$B,"",0,-1)&""
B426: 46202 | C426: =_xlfn.XLOOKUP(tblMovimientos[[#This Row],[Cuenta Bancaria]],Listas!$B:$B,Listas!$A:$A,"") -> Cross Family Trust | D426: Amerant Bank - Cross Family Trust - 4706-USD | E426: =_xlfn.XLOOKUP(tblMovimientos[[#This Row],[Cuenta Bancaria]],Listas!$B:$B,Listas!$C:$C,"") -> Amerant Bank | F426: Egreso | G426: Eg.Distribucion a socios (CFT,CCT,CST) | H426: =IFERROR(_xlfn.XLOOKUP(G426,Listas!E:E,Listas!F:F,""),"") -> Inversion | I426: =IFERROR(_xlfn.XLOOKUP(G426,Listas!E:E,Listas!G:G,""),"") -> Interno | J426: 1000000 | K426: =IF(F426="Ingreso",J426,-J426) -> -1000000 | L426: 2026-06 | M426: =SUMIFS('Saldos Iniciales'!$D:$D,'Saldos Iniciales'!$A:$A,C426,'Saldos Iniciales'!$B:$B,D426)+SUMIFS($K$1:$K$1324,$C$1:$C$1324,C426,$D$1:$D$1324,D426,$B$1:$B$1324,"<="&B426) -> 281717.6 | N426: =IF(tblMovimientos[[#This Row],[Tipo de Movimiento]]="Ingreso",tblMovimientos[[#This Row],[Monto (S/)]],"0") -> 0 | O426: =IF(tblMovimientos[[#This Row],[Tipo de Movimiento]]="Egreso",tblMovimientos[[#This Row],[Monto (S/)]],"0") -> 1000000 | P426: =IF(tblMovimientos[[#This Row],[Tipo de Movimiento]]="Ingreso",tblMovimientos[[#This Row],[Ingreso]],-tblMovimientos[[#This Row],[Egreso]]) -> -1000000 | Q426: =_xlfn.XLOOKUP(tblMovimientos[[#This Row],[Cuenta Bancaria]],Cuentas!$C:$C,Cuentas!$A:$A,"")&"" -> SSP Group | R426: =_xlfn.XLOOKUP(tblMovimientos[[#This Row],[Cuenta Bancaria]],Cuentas!$C:$C,Cuentas!$B:$B,"",0,-1)&"" -> Trust
B427: 46202 | C427: =_xlfn.XLOOKUP(tblMovimientos[[#This Row],[Cuenta Bancaria]],Listas!$B:$B,Listas!$A:$A,"") -> SSP Capital | D427: Amerant Bank - SSP Capital - 4706-USD | E427: =_xlfn.XLOOKUP(tblMovimientos[[#This Row],[Cuenta Bancaria]],Listas!$B:$B,Listas!$C:$C,"") -> Amerant Bank | F427: Egreso | G427: Eg.Gastos Personal (Nomina, bono, etc) | H427: =IFERROR(_xlfn.XLOOKUP(G427,Listas!E:E,Listas!F:F,""),"") -> Operativo | I427: =IFERROR(_xlfn.XLOOKUP(G427,Listas!E:E,Listas!G:G,""),"") -> Externo | J427: 164221.8 | K427: =IF(F427="Ingreso",J427,-J427) -> -164221.8 | L427: 2026-06 | M427: =SUMIFS('Saldos Iniciales'!$D:$D,'Saldos Iniciales'!$A:$A,C427,'Saldos Iniciales'!$B:$B,D427)+SUMIFS($K$1:$K$1324,$C$1:$C$1324,C427,$D$1:$D$1324,D427,$B$1:$B$1324,"<="&B427) -> 945129.85 | N427: =IF(tblMovimientos[[#This Row],[Tipo de Movimiento]]="Ingreso",tblMovimientos[[#This Row],[Monto (S/)]],"0") -> 0 | O427: =IF(tblMovimientos[[#This Row],[Tipo de Movimiento]]="Egreso",tblMovimientos[[#This Row],[Monto (S/)]],"0") -> 164221.8 | P427: =IF(tblMovimientos[[#This Row],[Tipo de Movimiento]]="Ingreso",tblMovimientos[[#This Row],[Ingreso]],-tblMovimientos[[#This Row],[Egreso]]) -> -164221.8 | Q427: =_xlfn.XLOOKUP(tblMovimientos[[#This Row],[Cuenta Bancaria]],Cuentas!$C:$C,Cuentas!$A:$A,"")&"" -> SSP Group | R427: =_xlfn.XLOOKUP(tblMovimientos[[#This Row],[Cuenta Bancaria]],Cuentas!$C:$C,Cuentas!$B:$B,"",0,-1)&""
B428: 46202 | C428: =_xlfn.XLOOKUP(tblMovimientos[[#This Row],[Cuenta Bancaria]],Listas!$B:$B,Listas!$A:$A,"") -> Go Blue | D428: Amerant Bank - Go Blue - 8206-USD | E428: =_xlfn.XLOOKUP(tblMovimientos[[#This Row],[Cuenta Bancaria]],Listas!$B:$B,Listas!$C:$C,"") -> Amerant Bank | F428: Egreso | G428: Eg.Gastos Operativos (Proveedor) | H428: =IFERROR(_xlfn.XLOOKUP(G428,Listas!E:E,Listas!F:F,""),"") -> Operativo | I428: =IFERROR(_xlfn.XLOOKUP(G428,Listas!E:E,Listas!G:G,""),"") -> Externo | J428: 45.86 | K428: =IF(F428="Ingreso",J428,-J428) -> -45.86 | L428: 2026-06 | M428: =SUMIFS('Saldos Iniciales'!$D:$D,'Saldos Iniciales'!$A:$A,C428,'Saldos Iniciales'!$B:$B,D428)+SUMIFS($K$1:$K$1324,$C$1:$C$1324,C428,$D$1:$D$1324,D428,$B$1:$B$1324,"<="&B428) -> 18579.43 | N428: =IF(tblMovimientos[[#This Row],[Tipo de Movimiento]]="Ingreso",tblMovimientos[[#This Row],[Monto (S/)]],"0") -> 0 | O428: =IF(tblMovimientos[[#This Row],[Tipo de Movimiento]]="Egreso",tblMovimientos[[#This Row],[Monto (S/)]],"0") -> 45.86 | P428: =IF(tblMovimientos[[#This Row],[Tipo de Movimiento]]="Ingreso",tblMovimientos[[#This Row],[Ingreso]],-tblMovimientos[[#This Row],[Egreso]]) -> -45.86 | Q428: =_xlfn.XLOOKUP(tblMovimientos[[#This Row],[Cuenta Bancaria]],Cuentas!$C:$C,Cuentas!$A:$A,"")&"" -> SSP Group | R428: =_xlfn.XLOOKUP(tblMovimientos[[#This Row],[Cuenta Bancaria]],Cuentas!$C:$C,Cuentas!$B:$B,"",0,-1)&""
B429: 46202 | C429: =_xlfn.XLOOKUP(tblMovimientos[[#This Row],[Cuenta Bancaria]],Listas!$B:$B,Listas!$A:$A,"") -> Go Blue | D429: Amerant Bank - Go Blue - 8206-USD | E429: =_xlfn.XLOOKUP(tblMovimientos[[#This Row],[Cuenta Bancaria]],Listas!$B:$B,Listas!$C:$C,"") -> Amerant Bank | F429: Egreso | H429: =IFERROR(_xlfn.XLOOKUP(G429,Listas!E:E,Listas!F:F,""),"") -> 0 | I429: =IFERROR(_xlfn.XLOOKUP(G429,Listas!E:E,Listas!G:G,""),"") -> 0 | J429: 6000 | K429: =IF(F429="Ingreso",J429,-J429) -> -6000 | L429: 2026-06 | M429: =SUMIFS('Saldos Iniciales'!$D:$D,'Saldos Iniciales'!$A:$A,C429,'Saldos Iniciales'!$B:$B,D429)+SUMIFS($K$1:$K$1324,$C$1:$C$1324,C429,$D$1:$D$1324,D429,$B$1:$B$1324,"<="&B429) -> 18579.43 | N429: =IF(tblMovimientos[[#This Row],[Tipo de Movimiento]]="Ingreso",tblMovimientos[[#This Row],[Monto (S/)]],"0") -> 0 | O429: =IF(tblMovimientos[[#This Row],[Tipo de Movimiento]]="Egreso",tblMovimientos[[#This Row],[Monto (S/)]],"0") -> 6000 | P429: =IF(tblMovimientos[[#This Row],[Tipo de Movimiento]]="Ingreso",tblMovimientos[[#This Row],[Ingreso]],-tblMovimientos[[#This Row],[Egreso]]) -> -6000 | Q429: =_xlfn.XLOOKUP(tblMovimientos[[#This Row],[Cuenta Bancaria]],Cuentas!$C:$C,Cuentas!$A:$A,"")&"" -> SSP Group | R429: =_xlfn.XLOOKUP(tblMovimientos[[#This Row],[Cuenta Bancaria]],Cuentas!$C:$C,Cuentas!$B:$B,"",0,-1)&""
B430: 46202 | C430: =_xlfn.XLOOKUP(tblMovimientos[[#This Row],[Cuenta Bancaria]],Listas!$B:$B,Listas!$A:$A,"") -> Cross Security Trust | D430: Bank of America - Cross Security Trust - 6642-USD | E430: =_xlfn.XLOOKUP(tblMovimientos[[#This Row],[Cuenta Bancaria]],Listas!$B:$B,Listas!$C:$C,"") -> Bank of America | F430: Egreso | G430: Eg.Gastos Operativos (Proveedor) | J430: 2970 | K430: =IF(F430="Ingreso",J430,-J430) -> -2970 | L430: 2026-06 | M430: =SUMIFS('Saldos Iniciales'!$D:$D,'Saldos Iniciales'!$A:$A,C430,'Saldos Iniciales'!$B:$B,D430)+SUMIFS($K$1:$K$1324,$C$1:$C$1324,C430,$D$1:$D$1324,D430,$B$1:$B$1324,"<="&B430) -> 327405.99 | N430: =IF(tblMovimientos[[#This Row],[Tipo de Movimiento]]="Ingreso",tblMovimientos[[#This Row],[Monto (S/)]],"0") -> 0 | O430: =IF(tblMovimientos[[#This Row],[Tipo de Movimiento]]="Egreso",tblMovimientos[[#This Row],[Monto (S/)]],"0") -> 2970 | P430: =IF(tblMovimientos[[#This Row],[Tipo de Movimiento]]="Ingreso",tblMovimientos[[#This Row],[Ingreso]],-tblMovimientos[[#This Row],[Egreso]]) -> -2970 | Q430: =_xlfn.XLOOKUP(tblMovimientos[[#This Row],[Cuenta Bancaria]],Cuentas!$C:$C,Cuentas!$A:$A,"")&"" -> SSP Group | R430: =_xlfn.XLOOKUP(tblMovimientos[[#This Row],[Cuenta Bancaria]],Cuentas!$C:$C,Cuentas!$B:$B,"",0,-1)&"" -> Trust
B431: 46203 | C431: =_xlfn.XLOOKUP(tblMovimientos[[#This Row],[Cuenta Bancaria]],Listas!$B:$B,Listas!$A:$A,"") -> M1B | D431: Amerant Bank - M1B - 0906-USD | E431: =_xlfn.XLOOKUP(tblMovimientos[[#This Row],[Cuenta Bancaria]],Listas!$B:$B,Listas!$C:$C,"") -> Amerant Bank | F431: Ingreso | G431: Ing.Intereses Recibidos de Unidad de Negocio | H431: =IFERROR(_xlfn.XLOOKUP(G431,Listas!E:E,Listas!F:F,""),"") -> Operativo | I431: =IFERROR(_xlfn.XLOOKUP(G431,Listas!E:E,Listas!G:G,""),"") -> Externo | J431: 6753.49 | K431: =IF(F431="Ingreso",J431,-J431) -> 6753.49 | L431: 2026-06 | M431: =SUMIFS('Saldos Iniciales'!$D:$D,'Saldos Iniciales'!$A:$A,C431,'Saldos Iniciales'!$B:$B,D431)+SUMIFS($K$1:$K$1324,$C$1:$C$1324,C431,$D$1:$D$1324,D431,$B$1:$B$1324,"<="&B431) -> 74139.68 | N431: =IF(tblMovimientos[[#This Row],[Tipo de Movimiento]]="Ingreso",tblMovimientos[[#This Row],[Monto (S/)]],"0") -> 6753.49 | O431: =IF(tblMovimientos[[#This Row],[Tipo de Movimiento]]="Egreso",tblMovimientos[[#This Row],[Monto (S/)]],"0") -> 0 | P431: =IF(tblMovimientos[[#This Row],[Tipo de Movimiento]]="Ingreso",tblMovimientos[[#This Row],[Ingreso]],-tblMovimientos[[#This Row],[Egreso]]) -> 6753.49 | Q431: =_xlfn.XLOOKUP(tblMovimientos[[#This Row],[Cuenta Bancaria]],Cuentas!$C:$C,Cuentas!$A:$A,"")&"" -> SSP Group | R431: =_xlfn.XLOOKUP(tblMovimientos[[#This Row],[Cuenta Bancaria]],Cuentas!$C:$C,Cuentas!$B:$B,"",0,-1)&""
B432: 46203 | C432: =_xlfn.XLOOKUP(tblMovimientos[[#This Row],[Cuenta Bancaria]],Listas!$B:$B,Listas!$A:$A,"") -> SSP Capital | D432: Amerant Bank Money Market - SSP Capital - 1006-USD | E432: =_xlfn.XLOOKUP(tblMovimientos[[#This Row],[Cuenta Bancaria]],Listas!$B:$B,Listas!$C:$C,"") -> Amerant Bank Money Market | F432: Ingreso | G432: Ing.Interes bancario | H432: =IFERROR(_xlfn.XLOOKUP(G432,Listas!E:E,Listas!F:F,""),"") -> Operativo | I432: =IFERROR(_xlfn.XLOOKUP(G432,Listas!E:E,Listas!G:G,""),"") -> Externo | J432: 2267.66 | K432: =IF(F432="Ingreso",J432,-J432) -> 2267.66 | L432: 2026-06 | M432: =SUMIFS('Saldos Iniciales'!$D:$D,'Saldos Iniciales'!$A:$A,C432,'Saldos Iniciales'!$B:$B,D432)+SUMIFS($K$1:$K$1324,$C$1:$C$1324,C432,$D$1:$D$1324,D432,$B$1:$B$1324,"<="&B432) -> 806680.61 | N432: =IF(tblMovimientos[[#This Row],[Tipo de Movimiento]]="Ingreso",tblMovimientos[[#This Row],[Monto (S/)]],"0") -> 2267.66 | O432: =IF(tblMovimientos[[#This Row],[Tipo de Movimiento]]="Egreso",tblMovimientos[[#This Row],[Monto (S/)]],"0") -> 0 | P432: =IF(tblMovimientos[[#This Row],[Tipo de Movimiento]]="Ingreso",tblMovimientos[[#This Row],[Ingreso]],-tblMovimientos[[#This Row],[Egreso]]) -> 2267.66 | Q432: =_xlfn.XLOOKUP(tblMovimientos[[#This Row],[Cuenta Bancaria]],Cuentas!$C:$C,Cuentas!$A:$A,"")&"" -> SSP Group | R432: =_xlfn.XLOOKUP(tblMovimientos[[#This Row],[Cuenta Bancaria]],Cuentas!$C:$C,Cuentas!$B:$B,"",0,-1)&""
B433: 46203 | C433: =_xlfn.XLOOKUP(tblMovimientos[[#This Row],[Cuenta Bancaria]],Listas!$B:$B,Listas!$A:$A,"") -> SSP Capital | D433: Amerant Bank - SSP Capital - 4706-USD | E433: =_xlfn.XLOOKUP(tblMovimientos[[#This Row],[Cuenta Bancaria]],Listas!$B:$B,Listas!$C:$C,"") -> Amerant Bank | F433: Egreso | G433: Eg.Gastos Personal (Taxes) | H433: =IFERROR(_xlfn.XLOOKUP(G433,Listas!E:E,Listas!F:F,""),"") -> Operativo | I433: =IFERROR(_xlfn.XLOOKUP(G433,Listas!E:E,Listas!G:G,""),"") -> Externo | J433: 73431.09 | K433: =IF(F433="Ingreso",J433,-J433) -> -73431.09 | L433: 2026-06 | M433: =SUMIFS('Saldos Iniciales'!$D:$D,'Saldos Iniciales'!$A:$A,C433,'Saldos Iniciales'!$B:$B,D433)+SUMIFS($K$1:$K$1324,$C$1:$C$1324,C433,$D$1:$D$1324,D433,$B$1:$B$1324,"<="&B433) -> 871698.76 | N433: =IF(tblMovimientos[[#This Row],[Tipo de Movimiento]]="Ingreso",tblMovimientos[[#This Row],[Monto (S/)]],"0") -> 0 | O433: =IF(tblMovimientos[[#This Row],[Tipo de Movimiento]]="Egreso",tblMovimientos[[#This Row],[Monto (S/)]],"0") -> 73431.09 | P433: =IF(tblMovimientos[[#This Row],[Tipo de Movimiento]]="Ingreso",tblMovimientos[[#This Row],[Ingreso]],-tblMovimientos[[#This Row],[Egreso]]) -> -73431.09 | Q433: =_xlfn.XLOOKUP(tblMovimientos[[#This Row],[Cuenta Bancaria]],Cuentas!$C:$C,Cuentas!$A:$A,"")&"" -> SSP Group | R433: =_xlfn.XLOOKUP(tblMovimientos[[#This Row],[Cuenta Bancaria]],Cuentas!$C:$C,Cuentas!$B:$B,"",0,-1)&""
B434: 46203 | C434: =_xlfn.XLOOKUP(tblMovimientos[[#This Row],[Cuenta Bancaria]],Listas!$B:$B,Listas!$A:$A,"") -> SSP Capital | D434: Bank of America - SSP Capital - 2580-USD | E434: =_xlfn.XLOOKUP(tblMovimientos[[#This Row],[Cuenta Bancaria]],Listas!$B:$B,Listas!$C:$C,"") -> Bank of America | F434: Egreso | G434: Eg.Gastos Operativos (Proveedor) | H434: =IFERROR(_xlfn.XLOOKUP(G434,Listas!E:E,Listas!F:F,""),"") -> Operativo | I434: =IFERROR(_xlfn.XLOOKUP(G434,Listas!E:E,Listas!G:G,""),"") -> Externo | J434: 526.75 | K434: =IF(F434="Ingreso",J434,-J434) -> -526.75 | L434: 2026-06 | M434: =SUMIFS('Saldos Iniciales'!$D:$D,'Saldos Iniciales'!$A:$A,C434,'Saldos Iniciales'!$B:$B,D434)+SUMIFS($K$1:$K$1324,$C$1:$C$1324,C434,$D$1:$D$1324,D434,$B$1:$B$1324,"<="&B434) -> 7777.24 | N434: =IF(tblMovimientos[[#This Row],[Tipo de Movimiento]]="Ingreso",tblMovimientos[[#This Row],[Monto (S/)]],"0") -> 0 | O434: =IF(tblMovimientos[[#This Row],[Tipo de Movimiento]]="Egreso",tblMovimientos[[#This Row],[Monto (S/)]],"0") -> 526.75 | P434: =IF(tblMovimientos[[#This Row],[Tipo de Movimiento]]="Ingreso",tblMovimientos[[#This Row],[Ingreso]],-tblMovimientos[[#This Row],[Egreso]]) -> -526.75 | Q434: =_xlfn.XLOOKUP(tblMovimientos[[#This Row],[Cuenta Bancaria]],Cuentas!$C:$C,Cuentas!$A:$A,"")&"" -> SSP Group | R434: =_xlfn.XLOOKUP(tblMovimientos[[#This Row],[Cuenta Bancaria]],Cuentas!$C:$C,Cuentas!$B:$B,"",0,-1)&""
B435: 46203 | C435: =_xlfn.XLOOKUP(tblMovimientos[[#This Row],[Cuenta Bancaria]],Listas!$B:$B,Listas!$A:$A,"") -> SSP Capital | D435: Bank of America - SSP Capital - 2580-USD | E435: =_xlfn.XLOOKUP(tblMovimientos[[#This Row],[Cuenta Bancaria]],Listas!$B:$B,Listas!$C:$C,"") -> Bank of America | F435: Egreso | G435: Eg.Gastos Operativos (Proveedor) | H435: =IFERROR(_xlfn.XLOOKUP(G435,Listas!E:E,Listas!F:F,""),"") -> Operativo | I435: =IFERROR(_xlfn.XLOOKUP(G435,Listas!E:E,Listas!G:G,""),"") -> Externo | J435: 193.01 | K435: =IF(F435="Ingreso",J435,-J435) -> -193.01 | L435: 2026-06 | M435: =SUMIFS('Saldos Iniciales'!$D:$D,'Saldos Iniciales'!$A:$A,C435,'Saldos Iniciales'!$B:$B,D435)+SUMIFS($K$1:$K$1324,$C$1:$C$1324,C435,$D$1:$D$1324,D435,$B$1:$B$1324,"<="&B435) -> 7777.24 | N435: =IF(tblMovimientos[[#This Row],[Tipo de Movimiento]]="Ingreso",tblMovimientos[[#This Row],[Monto (S/)]],"0") -> 0 | O435: =IF(tblMovimientos[[#This Row],[Tipo de Movimiento]]="Egreso",tblMovimientos[[#This Row],[Monto (S/)]],"0") -> 193.01 | P435: =IF(tblMovimientos[[#This Row],[Tipo de Movimiento]]="Ingreso",tblMovimientos[[#This Row],[Ingreso]],-tblMovimientos[[#This Row],[Egreso]]) -> -193.01 | Q435: =_xlfn.XLOOKUP(tblMovimientos[[#This Row],[Cuenta Bancaria]],Cuentas!$C:$C,Cuentas!$A:$A,"")&"" -> SSP Group | R435: =_xlfn.XLOOKUP(tblMovimientos[[#This Row],[Cuenta Bancaria]],Cuentas!$C:$C,Cuentas!$B:$B,"",0,-1)&""
B436: 46203 | C436: =_xlfn.XLOOKUP(tblMovimientos[[#This Row],[Cuenta Bancaria]],Listas!$B:$B,Listas!$A:$A,"") -> CFT Group | D436: Bank of America - CFT Group - 4415-USD | E436: =_xlfn.XLOOKUP(tblMovimientos[[#This Row],[Cuenta Bancaria]],Listas!$B:$B,Listas!$C:$C,"") -> Bank of America | F436: Egreso | G436: Eg.Gastos Operativos (Proveedor) | H436: =IFERROR(_xlfn.XLOOKUP(G436,Listas!E:E,Listas!F:F,""),"") -> Operativo | I436: =IFERROR(_xlfn.XLOOKUP(G436,Listas!E:E,Listas!G:G,""),"") -> Externo | J436: 2977.94 | K436: =IF(F436="Ingreso",J436,-J436) -> -2977.94 | L436: 2026-06 | M436: =SUMIFS('Saldos Iniciales'!$D:$D,'Saldos Iniciales'!$A:$A,C436,'Saldos Iniciales'!$B:$B,D436)+SUMIFS($K$1:$K$1324,$C$1:$C$1324,C436,$D$1:$D$1324,D436,$B$1:$B$1324,"<="&B436) -> 35943.36 | N436: =IF(tblMovimientos[[#This Row],[Tipo de Movimiento]]="Ingreso",tblMovimientos[[#This Row],[Monto (S/)]],"0") -> 0 | O436: =IF(tblMovimientos[[#This Row],[Tipo de Movimiento]]="Egreso",tblMovimientos[[#This Row],[Monto (S/)]],"0") -> 2977.94 | P436: =IF(tblMovimientos[[#This Row],[Tipo de Movimiento]]="Ingreso",tblMovimientos[[#This Row],[Ingreso]],-tblMovimientos[[#This Row],[Egreso]]) -> -2977.94 | Q436: =_xlfn.XLOOKUP(tblMovimientos[[#This Row],[Cuenta Bancaria]],Cuentas!$C:$C,Cuentas!$A:$A,"")&"" -> SSP Group | R436: =_xlfn.XLOOKUP(tblMovimientos[[#This Row],[Cuenta Bancaria]],Cuentas!$C:$C,Cuentas!$B:$B,"",0,-1)&""
B437: 46203 | C437: =_xlfn.XLOOKUP(tblMovimientos[[#This Row],[Cuenta Bancaria]],Listas!$B:$B,Listas!$A:$A,"") -> CFT Group | D437: Bank of America - CFT Group - 4415-USD | E437: =_xlfn.XLOOKUP(tblMovimientos[[#This Row],[Cuenta Bancaria]],Listas!$B:$B,Listas!$C:$C,"") -> Bank of America | F437: Egreso | G437: Eg.Gastos Personal (Nomina, bono, etc) | H437: =IFERROR(_xlfn.XLOOKUP(G437,Listas!E:E,Listas!F:F,""),"") -> Operativo | I437: =IFERROR(_xlfn.XLOOKUP(G437,Listas!E:E,Listas!G:G,""),"") -> Externo | J437: 611.12 | K437: =IF(F437="Ingreso",J437,-J437) -> -611.12 | L437: 2026-06 | M437: =SUMIFS('Saldos Iniciales'!$D:$D,'Saldos Iniciales'!$A:$A,C437,'Saldos Iniciales'!$B:$B,D437)+SUMIFS($K$1:$K$1324,$C$1:$C$1324,C437,$D$1:$D$1324,D437,$B$1:$B$1324,"<="&B437) -> 35943.36 | N437: =IF(tblMovimientos[[#This Row],[Tipo de Movimiento]]="Ingreso",tblMovimientos[[#This Row],[Monto (S/)]],"0") -> 0 | O437: =IF(tblMovimientos[[#This Row],[Tipo de Movimiento]]="Egreso",tblMovimientos[[#This Row],[Monto (S/)]],"0") -> 611.12 | P437: =IF(tblMovimientos[[#This Row],[Tipo de Movimiento]]="Ingreso",tblMovimientos[[#This Row],[Ingreso]],-tblMovimientos[[#This Row],[Egreso]]) -> -611.12 | Q437: =_xlfn.XLOOKUP(tblMovimientos[[#This Row],[Cuenta Bancaria]],Cuentas!$C:$C,Cuentas!$A:$A,"")&"" -> SSP Group | R437: =_xlfn.XLOOKUP(tblMovimientos[[#This Row],[Cuenta Bancaria]],Cuentas!$C:$C,Cuentas!$B:$B,"",0,-1)&""
B438: 46203 | C438: =_xlfn.XLOOKUP(tblMovimientos[[#This Row],[Cuenta Bancaria]],Listas!$B:$B,Listas!$A:$A,"") -> Cross Family Trust | D438: Bank of America - Cross Family Trust - 3124-USD | E438: =_xlfn.XLOOKUP(tblMovimientos[[#This Row],[Cuenta Bancaria]],Listas!$B:$B,Listas!$C:$C,"") -> Bank of America | F438: Egreso | G438: Eg.Gastos Operativos (Proveedor) | H438: =IFERROR(_xlfn.XLOOKUP(G438,Listas!E:E,Listas!F:F,""),"") -> Operativo | I438: =IFERROR(_xlfn.XLOOKUP(G438,Listas!E:E,Listas!G:G,""),"") -> Externo | J438: 6000 | K438: =IF(F438="Ingreso",J438,-J438) -> -6000 | L438: 2026-06 | M438: =SUMIFS('Saldos Iniciales'!$D:$D,'Saldos Iniciales'!$A:$A,C438,'Saldos Iniciales'!$B:$B,D438)+SUMIFS($K$1:$K$1324,$C$1:$C$1324,C438,$D$1:$D$1324,D438,$B$1:$B$1324,"<="&B438) -> 45206.89 | N438: =IF(tblMovimientos[[#This Row],[Tipo de Movimiento]]="Ingreso",tblMovimientos[[#This Row],[Monto (S/)]],"0") -> 0 | O438: =IF(tblMovimientos[[#This Row],[Tipo de Movimiento]]="Egreso",tblMovimientos[[#This Row],[Monto (S/)]],"0") -> 6000 | P438: =IF(tblMovimientos[[#This Row],[Tipo de Movimiento]]="Ingreso",tblMovimientos[[#This Row],[Ingreso]],-tblMovimientos[[#This Row],[Egreso]]) -> -6000 | Q438: =_xlfn.XLOOKUP(tblMovimientos[[#This Row],[Cuenta Bancaria]],Cuentas!$C:$C,Cuentas!$A:$A,"")&"" -> SSP Group | R438: =_xlfn.XLOOKUP(tblMovimientos[[#This Row],[Cuenta Bancaria]],Cuentas!$C:$C,Cuentas!$B:$B,"",0,-1)&"" -> Trust
B439: 46203 | C439: =_xlfn.XLOOKUP(tblMovimientos[[#This Row],[Cuenta Bancaria]],Listas!$B:$B,Listas!$A:$A,"") -> Cross Security Trust | D439: Bank of America - Cross Security Trust - 6642-USD | E439: =_xlfn.XLOOKUP(tblMovimientos[[#This Row],[Cuenta Bancaria]],Listas!$B:$B,Listas!$C:$C,"") -> Bank of America | F439: Egreso | G439: Eg.Gastos Operativos (Proveedor) | J439: 48163 | K439: =IF(F439="Ingreso",J439,-J439) -> -48163 | L439: 2026-06 | M439: =SUMIFS('Saldos Iniciales'!$D:$D,'Saldos Iniciales'!$A:$A,C439,'Saldos Iniciales'!$B:$B,D439)+SUMIFS($K$1:$K$1324,$C$1:$C$1324,C439,$D$1:$D$1324,D439,$B$1:$B$1324,"<="&B439) -> 267503.99 | N439: =IF(tblMovimientos[[#This Row],[Tipo de Movimiento]]="Ingreso",tblMovimientos[[#This Row],[Monto (S/)]],"0") -> 0 | O439: =IF(tblMovimientos[[#This Row],[Tipo de Movimiento]]="Egreso",tblMovimientos[[#This Row],[Monto (S/)]],"0") -> 48163 | P439: =IF(tblMovimientos[[#This Row],[Tipo de Movimiento]]="Ingreso",tblMovimientos[[#This Row],[Ingreso]],-tblMovimientos[[#This Row],[Egreso]]) -> -48163 | Q439: =_xlfn.XLOOKUP(tblMovimientos[[#This Row],[Cuenta Bancaria]],Cuentas!$C:$C,Cuentas!$A:$A,"")&"" -> SSP Group | R439: =_xlfn.XLOOKUP(tblMovimientos[[#This Row],[Cuenta Bancaria]],Cuentas!$C:$C,Cuentas!$B:$B,"",0,-1)&"" -> Trust
B440: 46203 | C440: =_xlfn.XLOOKUP(tblMovimientos[[#This Row],[Cuenta Bancaria]],Listas!$B:$B,Listas!$A:$A,"") -> Cross Security Trust | D440: Bank of America - Cross Security Trust - 6642-USD | E440: =_xlfn.XLOOKUP(tblMovimientos[[#This Row],[Cuenta Bancaria]],Listas!$B:$B,Listas!$C:$C,"") -> Bank of America | F440: Egreso | G440: Eg.Gastos Operativos (Proveedor) | J440: 11739 | K440: =IF(F440="Ingreso",J440,-J440) -> -11739 | L440: 2026-06 | M440: =SUMIFS('Saldos Iniciales'!$D:$D,'Saldos Iniciales'!$A:$A,C440,'Saldos Iniciales'!$B:$B,D440)+SUMIFS($K$1:$K$1324,$C$1:$C$1324,C440,$D$1:$D$1324,D440,$B$1:$B$1324,"<="&B440) -> 267503.99 | N440: =IF(tblMovimientos[[#This Row],[Tipo de Movimiento]]="Ingreso",tblMovimientos[[#This Row],[Monto (S/)]],"0") -> 0 | O440: =IF(tblMovimientos[[#This Row],[Tipo de Movimiento]]="Egreso",tblMovimientos[[#This Row],[Monto (S/)]],"0") -> 11739 | P440: =IF(tblMovimientos[[#This Row],[Tipo de Movimiento]]="Ingreso",tblMovimientos[[#This Row],[Ingreso]],-tblMovimientos[[#This Row],[Egreso]]) -> -11739 | Q440: =_xlfn.XLOOKUP(tblMovimientos[[#This Row],[Cuenta Bancaria]],Cuentas!$C:$C,Cuentas!$A:$A,"")&"" -> SSP Group | R440: =_xlfn.XLOOKUP(tblMovimientos[[#This Row],[Cuenta Bancaria]],Cuentas!$C:$C,Cuentas!$B:$B,"",0,-1)&"" -> Trust
B441: 46204 | C441: =_xlfn.XLOOKUP(tblMovimientos[[#This Row],[Cuenta Bancaria]],Listas!$B:$B,Listas!$A:$A,"") -> Go Blue | D441: Amerant Bank - Go Blue - 8206-USD | E441: =_xlfn.XLOOKUP(tblMovimientos[[#This Row],[Cuenta Bancaria]],Listas!$B:$B,Listas!$C:$C,"") -> Amerant Bank | F441: Egreso | G441: Eg.Gastos Operativos (Proveedor) | H441: =IFERROR(_xlfn.XLOOKUP(G441,Listas!E:E,Listas!F:F,""),"") -> Operativo | I441: =IFERROR(_xlfn.XLOOKUP(G441,Listas!E:E,Listas!G:G,""),"") -> Externo | J441: 175 | K441: =IF(F441="Ingreso",J441,-J441) -> -175 | L441: 2026-07 | M441: =SUMIFS('Saldos Iniciales'!$D:$D,'Saldos Iniciales'!$A:$A,C441,'Saldos Iniciales'!$B:$B,D441)+SUMIFS($K$1:$K$1324,$C$1:$C$1324,C441,$D$1:$D$1324,D441,$B$1:$B$1324,"<="&B441) -> 18404.43 | N441: =IF(tblMovimientos[[#This Row],[Tipo de Movimiento]]="Ingreso",tblMovimientos[[#This Row],[Monto (S/)]],"0") -> 0 | O441: =IF(tblMovimientos[[#This Row],[Tipo de Movimiento]]="Egreso",tblMovimientos[[#This Row],[Monto (S/)]],"0") -> 175 | P441: =IF(tblMovimientos[[#This Row],[Tipo de Movimiento]]="Ingreso",tblMovimientos[[#This Row],[Ingreso]],-tblMovimientos[[#This Row],[Egreso]]) -> -175 | Q441: =_xlfn.XLOOKUP(tblMovimientos[[#This Row],[Cuenta Bancaria]],Cuentas!$C:$C,Cuentas!$A:$A,"")&"" -> SSP Group | R441: =_xlfn.XLOOKUP(tblMovimientos[[#This Row],[Cuenta Bancaria]],Cuentas!$C:$C,Cuentas!$B:$B,"",0,-1)&""
B442: 46204 | C442: =_xlfn.XLOOKUP(tblMovimientos[[#This Row],[Cuenta Bancaria]],Listas!$B:$B,Listas!$A:$A,"") -> A&M Imports | D442: Bank of America - A&M Imports - 3797-USD | E442: =_xlfn.XLOOKUP(tblMovimientos[[#This Row],[Cuenta Bancaria]],Listas!$B:$B,Listas!$C:$C,"") -> Bank of America | F442: Ingreso | G442: Ing.Intereses Recibidos de Unidad de Negocio | H442: =IFERROR(_xlfn.XLOOKUP(G442,Listas!E:E,Listas!F:F,""),"") -> Operativo | I442: =IFERROR(_xlfn.XLOOKUP(G442,Listas!E:E,Listas!G:G,""),"") -> Externo | J442: 16785.27 | K442: =IF(F442="Ingreso",J442,-J442) -> 16785.27 | L442: 2026-07 | M442: =SUMIFS('Saldos Iniciales'!$D:$D,'Saldos Iniciales'!$A:$A,C442,'Saldos Iniciales'!$B:$B,D442)+SUMIFS($K$1:$K$1324,$C$1:$C$1324,C442,$D$1:$D$1324,D442,$B$1:$B$1324,"<="&B442) -> 507936.38 | N442: =IF(tblMovimientos[[#This Row],[Tipo de Movimiento]]="Ingreso",tblMovimientos[[#This Row],[Monto (S/)]],"0") -> 16785.27 | O442: =IF(tblMovimientos[[#This Row],[Tipo de Movimiento]]="Egreso",tblMovimientos[[#This Row],[Monto (S/)]],"0") -> 0 | P442: =IF(tblMovimientos[[#This Row],[Tipo de Movimiento]]="Ingreso",tblMovimientos[[#This Row],[Ingreso]],-tblMovimientos[[#This Row],[Egreso]]) -> 16785.27 | Q442: =_xlfn.XLOOKUP(tblMovimientos[[#This Row],[Cuenta Bancaria]],Cuentas!$C:$C,Cuentas!$A:$A,"")&"" -> SSP Group | R442: =_xlfn.XLOOKUP(tblMovimientos[[#This Row],[Cuenta Bancaria]],Cuentas!$C:$C,Cuentas!$B:$B,"",0,-1)&""
B443: 46204 | C443: =_xlfn.XLOOKUP(tblMovimientos[[#This Row],[Cuenta Bancaria]],Listas!$B:$B,Listas!$A:$A,"") -> A&M Imports | D443: Bank of America - A&M Imports - 3797-USD | E443: =_xlfn.XLOOKUP(tblMovimientos[[#This Row],[Cuenta Bancaria]],Listas!$B:$B,Listas!$C:$C,"") -> Bank of America | F443: Ingreso | G443: Ing.Intereses Recibidos de Unidad de Negocio | H443: =IFERROR(_xlfn.XLOOKUP(G443,Listas!E:E,Listas!F:F,""),"") -> Operativo | I443: =IFERROR(_xlfn.XLOOKUP(G443,Listas!E:E,Listas!G:G,""),"") -> Externo | J443: 1405.48 | K443: =IF(F443="Ingreso",J443,-J443) -> 1405.48 | L443: 2026-07 | M443: =SUMIFS('Saldos Iniciales'!$D:$D,'Saldos Iniciales'!$A:$A,C443,'Saldos Iniciales'!$B:$B,D443)+SUMIFS($K$1:$K$1324,$C$1:$C$1324,C443,$D$1:$D$1324,D443,$B$1:$B$1324,"<="&B443) -> 507936.38 | N443: =IF(tblMovimientos[[#This Row],[Tipo de Movimiento]]="Ingreso",tblMovimientos[[#This Row],[Monto (S/)]],"0") -> 1405.48 | O443: =IF(tblMovimientos[[#This Row],[Tipo de Movimiento]]="Egreso",tblMovimientos[[#This Row],[Monto (S/)]],"0") -> 0 | P443: =IF(tblMovimientos[[#This Row],[Tipo de Movimiento]]="Ingreso",tblMovimientos[[#This Row],[Ingreso]],-tblMovimientos[[#This Row],[Egreso]]) -> 1405.48 | Q443: =_xlfn.XLOOKUP(tblMovimientos[[#This Row],[Cuenta Bancaria]],Cuentas!$C:$C,Cuentas!$A:$A,"")&"" -> SSP Group | R443: =_xlfn.XLOOKUP(tblMovimientos[[#This Row],[Cuenta Bancaria]],Cuentas!$C:$C,Cuentas!$B:$B,"",0,-1)&""
B444: 46204 | C444: =_xlfn.XLOOKUP(tblMovimientos[[#This Row],[Cuenta Bancaria]],Listas!$B:$B,Listas!$A:$A,"") -> Sacred Valley Capital | D444: Bank of America - Sacred Valley Capital - 4376-USD | E444: =_xlfn.XLOOKUP(tblMovimientos[[#This Row],[Cuenta Bancaria]],Listas!$B:$B,Listas!$C:$C,"") -> Bank of America | F444: Egreso | G444: Eg.Gastos Bancarios | H444: =IFERROR(_xlfn.XLOOKUP(G444,Listas!E:E,Listas!F:F,""),"") -> Operativo | I444: =IFERROR(_xlfn.XLOOKUP(G444,Listas!E:E,Listas!G:G,""),"") -> Externo | J444: 29.95 | K444: =IF(F444="Ingreso",J444,-J444) -> -29.95 | L444: 2026-07 | M444: =SUMIFS('Saldos Iniciales'!$D:$D,'Saldos Iniciales'!$A:$A,C444,'Saldos Iniciales'!$B:$B,D444)+SUMIFS($K$1:$K$1324,$C$1:$C$1324,C444,$D$1:$D$1324,D444,$B$1:$B$1324,"<="&B444) -> 54.4 | N444: =IF(tblMovimientos[[#This Row],[Tipo de Movimiento]]="Ingreso",tblMovimientos[[#This Row],[Monto (S/)]],"0") -> 0 | O444: =IF(tblMovimientos[[#This Row],[Tipo de Movimiento]]="Egreso",tblMovimientos[[#This Row],[Monto (S/)]],"0") -> 29.95 | P444: =IF(tblMovimientos[[#This Row],[Tipo de Movimiento]]="Ingreso",tblMovimientos[[#This Row],[Ingreso]],-tblMovimientos[[#This Row],[Egreso]]) -> -29.95 | Q444: =_xlfn.XLOOKUP(tblMovimientos[[#This Row],[Cuenta Bancaria]],Cuentas!$C:$C,Cuentas!$A:$A,"")&"" -> SSP Group | R444: =_xlfn.XLOOKUP(tblMovimientos[[#This Row],[Cuenta Bancaria]],Cuentas!$C:$C,Cuentas!$B:$B,"",0,-1)&""
B445: 46204 | C445: =_xlfn.XLOOKUP(tblMovimientos[[#This Row],[Cuenta Bancaria]],Listas!$B:$B,Listas!$A:$A,"") -> YWC Capital | D445: Bank of America - YWC Capital - 0282-USD | E445: =_xlfn.XLOOKUP(tblMovimientos[[#This Row],[Cuenta Bancaria]],Listas!$B:$B,Listas!$C:$C,"") -> Bank of America | F445: Egreso | G445: Eg.Gastos Bancarios | H445: =IFERROR(_xlfn.XLOOKUP(G445,Listas!E:E,Listas!F:F,""),"") -> Operativo | I445: =IFERROR(_xlfn.XLOOKUP(G445,Listas!E:E,Listas!G:G,""),"") -> Externo | J445: 29.95 | K445: =IF(F445="Ingreso",J445,-J445) -> -29.95 | L445: 2026-07 | M445: =SUMIFS('Saldos Iniciales'!$D:$D,'Saldos Iniciales'!$A:$A,C445,'Saldos Iniciales'!$B:$B,D445)+SUMIFS($K$1:$K$1324,$C$1:$C$1324,C445,$D$1:$D$1324,D445,$B$1:$B$1324,"<="&B445) -> 2207.82 | N445: =IF(tblMovimientos[[#This Row],[Tipo de Movimiento]]="Ingreso",tblMovimientos[[#This Row],[Monto (S/)]],"0") -> 0 | O445: =IF(tblMovimientos[[#This Row],[Tipo de Movimiento]]="Egreso",tblMovimientos[[#This Row],[Monto (S/)]],"0") -> 29.95 | P445: =IF(tblMovimientos[[#This Row],[Tipo de Movimiento]]="Ingreso",tblMovimientos[[#This Row],[Ingreso]],-tblMovimientos[[#This Row],[Egreso]]) -> -29.95 | Q445: =_xlfn.XLOOKUP(tblMovimientos[[#This Row],[Cuenta Bancaria]],Cuentas!$C:$C,Cuentas!$A:$A,"")&"" -> SSP Group | R445: =_xlfn.XLOOKUP(tblMovimientos[[#This Row],[Cuenta Bancaria]],Cuentas!$C:$C,Cuentas!$B:$B,"",0,-1)&""
B446: 46204 | C446: =_xlfn.XLOOKUP(tblMovimientos[[#This Row],[Cuenta Bancaria]],Listas!$B:$B,Listas!$A:$A,"") -> Arbor Capital Properties | D446: Bank of America - Arbor Capital Properties - 3262-USD | E446: =_xlfn.XLOOKUP(tblMovimientos[[#This Row],[Cuenta Bancaria]],Listas!$B:$B,Listas!$C:$C,"") -> Bank of America | F446: Egreso | G446: Eg.Gastos Bancarios | H446: =IFERROR(_xlfn.XLOOKUP(G446,Listas!E:E,Listas!F:F,""),"") -> Operativo | I446: =IFERROR(_xlfn.XLOOKUP(G446,Listas!E:E,Listas!G:G,""),"") -> Externo | J446: 16 | K446: =IF(F446="Ingreso",J446,-J446) -> -16 | L446: 2026-07 | M446: =SUMIFS('Saldos Iniciales'!$D:$D,'Saldos Iniciales'!$A:$A,C446,'Saldos Iniciales'!$B:$B,D446)+SUMIFS($K$1:$K$1324,$C$1:$C$1324,C446,$D$1:$D$1324,D446,$B$1:$B$1324,"<="&B446) -> 1412.08 | N446: =IF(tblMovimientos[[#This Row],[Tipo de Movimiento]]="Ingreso",tblMovimientos[[#This Row],[Monto (S/)]],"0") -> 0 | O446: =IF(tblMovimientos[[#This Row],[Tipo de Movimiento]]="Egreso",tblMovimientos[[#This Row],[Monto (S/)]],"0") -> 16 | P446: =IF(tblMovimientos[[#This Row],[Tipo de Movimiento]]="Ingreso",tblMovimientos[[#This Row],[Ingreso]],-tblMovimientos[[#This Row],[Egreso]]) -> -16 | Q446: =_xlfn.XLOOKUP(tblMovimientos[[#This Row],[Cuenta Bancaria]],Cuentas!$C:$C,Cuentas!$A:$A,"")&"" -> SSP Group | R446: =_xlfn.XLOOKUP(tblMovimientos[[#This Row],[Cuenta Bancaria]],Cuentas!$C:$C,Cuentas!$B:$B,"",0,-1)&""
B447: 46204 | C447: =_xlfn.XLOOKUP(tblMovimientos[[#This Row],[Cuenta Bancaria]],Listas!$B:$B,Listas!$A:$A,"") -> 2515 Overbrook | D447: Bank of America - 2515 Overbrook - 4648-USD | E447: =_xlfn.XLOOKUP(tblMovimientos[[#This Row],[Cuenta Bancaria]],Listas!$B:$B,Listas!$C:$C,"") -> Bank of America | F447: Egreso | G447: Eg.Deuda Terceros (Intereses) | H447: =IFERROR(_xlfn.XLOOKUP(G447,Listas!E:E,Listas!F:F,""),"") -> Financiamiento | I447: =IFERROR(_xlfn.XLOOKUP(G447,Listas!E:E,Listas!G:G,""),"") -> Externo | J447: 8533.33 | K447: =IF(F447="Ingreso",J447,-J447) -> -8533.33 | L447: 2026-07 | M447: =SUMIFS('Saldos Iniciales'!$D:$D,'Saldos Iniciales'!$A:$A,C447,'Saldos Iniciales'!$B:$B,D447)+SUMIFS($K$1:$K$1324,$C$1:$C$1324,C447,$D$1:$D$1324,D447,$B$1:$B$1324,"<="&B447) -> 22176.22 | N447: =IF(tblMovimientos[[#This Row],[Tipo de Movimiento]]="Ingreso",tblMovimientos[[#This Row],[Monto (S/)]],"0") -> 0 | O447: =IF(tblMovimientos[[#This Row],[Tipo de Movimiento]]="Egreso",tblMovimientos[[#This Row],[Monto (S/)]],"0") -> 8533.33 | P447: =IF(tblMovimientos[[#This Row],[Tipo de Movimiento]]="Ingreso",tblMovimientos[[#This Row],[Ingreso]],-tblMovimientos[[#This Row],[Egreso]]) -> -8533.33 | Q447: =_xlfn.XLOOKUP(tblMovimientos[[#This Row],[Cuenta Bancaria]],Cuentas!$C:$C,Cuentas!$A:$A,"")&"" -> SSP Group | R447: =_xlfn.XLOOKUP(tblMovimientos[[#This Row],[Cuenta Bancaria]],Cuentas!$C:$C,Cuentas!$B:$B,"",0,-1)&""
B448: 46204 | C448: =_xlfn.XLOOKUP(tblMovimientos[[#This Row],[Cuenta Bancaria]],Listas!$B:$B,Listas!$A:$A,"") -> 2515 Overbrook | D448: Bank of America - 2515 Overbrook - 9923-USD | E448: =_xlfn.XLOOKUP(tblMovimientos[[#This Row],[Cuenta Bancaria]],Listas!$B:$B,Listas!$C:$C,"") -> Bank of America | F448: Egreso | G448: Eg.Gastos Bancarios | H448: =IFERROR(_xlfn.XLOOKUP(G448,Listas!E:E,Listas!F:F,""),"") -> Operativo | I448: =IFERROR(_xlfn.XLOOKUP(G448,Listas!E:E,Listas!G:G,""),"") -> Externo | J448: 10 | K448: =IF(F448="Ingreso",J448,-J448) -> -10 | L448: 2026-07 | M448: =SUMIFS('Saldos Iniciales'!$D:$D,'Saldos Iniciales'!$A:$A,C448,'Saldos Iniciales'!$B:$B,D448)+SUMIFS($K$1:$K$1324,$C$1:$C$1324,C448,$D$1:$D$1324,D448,$B$1:$B$1324,"<="&B448) -> 320.42 | N448: =IF(tblMovimientos[[#This Row],[Tipo de Movimiento]]="Ingreso",tblMovimientos[[#This Row],[Monto (S/)]],"0") -> 0 | O448: =IF(tblMovimientos[[#This Row],[Tipo de Movimiento]]="Egreso",tblMovimientos[[#This Row],[Monto (S/)]],"0") -> 10 | P448: =IF(tblMovimientos[[#This Row],[Tipo de Movimiento]]="Ingreso",tblMovimientos[[#This Row],[Ingreso]],-tblMovimientos[[#This Row],[Egreso]]) -> -10 | Q448: =_xlfn.XLOOKUP(tblMovimientos[[#This Row],[Cuenta Bancaria]],Cuentas!$C:$C,Cuentas!$A:$A,"")&"" -> SSP Group | R448: =_xlfn.XLOOKUP(tblMovimientos[[#This Row],[Cuenta Bancaria]],Cuentas!$C:$C,Cuentas!$B:$B,"",0,-1)&""
B449: 46204 | C449: =_xlfn.XLOOKUP(tblMovimientos[[#This Row],[Cuenta Bancaria]],Listas!$B:$B,Listas!$A:$A,"") -> 112 Florida Ave | D449: Bank of America - 112 Florida Ave - 3259-USD | E449: =_xlfn.XLOOKUP(tblMovimientos[[#This Row],[Cuenta Bancaria]],Listas!$B:$B,Listas!$C:$C,"") -> Bank of America | F449: Egreso | G449: Eg.Deuda Terceros (Intereses+Capital) | H449: =IFERROR(_xlfn.XLOOKUP(G449,Listas!E:E,Listas!F:F,""),"") -> Financiamiento | I449: =IFERROR(_xlfn.XLOOKUP(G449,Listas!E:E,Listas!G:G,""),"") -> Externo | J449: 9798.63 | K449: =IF(F449="Ingreso",J449,-J449) -> -9798.63 | L449: 2026-07 | M449: =SUMIFS('Saldos Iniciales'!$D:$D,'Saldos Iniciales'!$A:$A,C449,'Saldos Iniciales'!$B:$B,D449)+SUMIFS($K$1:$K$1324,$C$1:$C$1324,C449,$D$1:$D$1324,D449,$B$1:$B$1324,"<="&B449) -> 10522.8 | N449: =IF(tblMovimientos[[#This Row],[Tipo de Movimiento]]="Ingreso",tblMovimientos[[#This Row],[Monto (S/)]],"0") -> 0 | O449: =IF(tblMovimientos[[#This Row],[Tipo de Movimiento]]="Egreso",tblMovimientos[[#This Row],[Monto (S/)]],"0") -> 9798.63 | P449: =IF(tblMovimientos[[#This Row],[Tipo de Movimiento]]="Ingreso",tblMovimientos[[#This Row],[Ingreso]],-tblMovimientos[[#This Row],[Egreso]]) -> -9798.63 | Q449: =_xlfn.XLOOKUP(tblMovimientos[[#This Row],[Cuenta Bancaria]],Cuentas!$C:$C,Cuentas!$A:$A,"")&"" -> SSP Group | R449: =_xlfn.XLOOKUP(tblMovimientos[[#This Row],[Cuenta Bancaria]],Cuentas!$C:$C,Cuentas!$B:$B,"",0,-1)&""
B450: 46204 | C450: =_xlfn.XLOOKUP(tblMovimientos[[#This Row],[Cuenta Bancaria]],Listas!$B:$B,Listas!$A:$A,"") -> 3628 Thomas Ave | D450: Bank of America - 3628 Thomas Ave - 4406-USD | E450: =_xlfn.XLOOKUP(tblMovimientos[[#This Row],[Cuenta Bancaria]],Listas!$B:$B,Listas!$C:$C,"") -> Bank of America | F450: Egreso | G450: Eg.Deuda Terceros (Intereses+Capital) | H450: =IFERROR(_xlfn.XLOOKUP(G450,Listas!E:E,Listas!F:F,""),"") -> Financiamiento | I450: =IFERROR(_xlfn.XLOOKUP(G450,Listas!E:E,Listas!G:G,""),"") -> Externo | J450: 8773.04 | K450: =IF(F450="Ingreso",J450,-J450) -> -8773.04 | L450: 2026-07 | M450: =SUMIFS('Saldos Iniciales'!$D:$D,'Saldos Iniciales'!$A:$A,C450,'Saldos Iniciales'!$B:$B,D450)+SUMIFS($K$1:$K$1324,$C$1:$C$1324,C450,$D$1:$D$1324,D450,$B$1:$B$1324,"<="&B450) -> 19685.56 | N450: =IF(tblMovimientos[[#This Row],[Tipo de Movimiento]]="Ingreso",tblMovimientos[[#This Row],[Monto (S/)]],"0") -> 0 | O450: =IF(tblMovimientos[[#This Row],[Tipo de Movimiento]]="Egreso",tblMovimientos[[#This Row],[Monto (S/)]],"0") -> 8773.04 | P450: =IF(tblMovimientos[[#This Row],[Tipo de Movimiento]]="Ingreso",tblMovimientos[[#This Row],[Ingreso]],-tblMovimientos[[#This Row],[Egreso]]) -> -8773.04 | Q450: =_xlfn.XLOOKUP(tblMovimientos[[#This Row],[Cuenta Bancaria]],Cuentas!$C:$C,Cuentas!$A:$A,"")&"" -> SSP Group | R450: =_xlfn.XLOOKUP(tblMovimientos[[#This Row],[Cuenta Bancaria]],Cuentas!$C:$C,Cuentas!$B:$B,"",0,-1)&""
B451: 46204 | C451: =_xlfn.XLOOKUP(tblMovimientos[[#This Row],[Cuenta Bancaria]],Listas!$B:$B,Listas!$A:$A,"") -> Go Blue | D451: Amerant Bank - Go Blue - 1557-USD | E451: =_xlfn.XLOOKUP(tblMovimientos[[#This Row],[Cuenta Bancaria]],Listas!$B:$B,Listas!$C:$C,"") -> Amerant Bank | F451: Egreso | G451: Eg.Gastos Operativos (Proveedor) | H451: =IFERROR(_xlfn.XLOOKUP(G451,Listas!E:E,Listas!F:F,""),"") -> Operativo | I451: =IFERROR(_xlfn.XLOOKUP(G451,Listas!E:E,Listas!G:G,""),"") -> Externo | J451: 258.5 | K451: =IF(F451="Ingreso",J451,-J451) -> -258.5 | L451: 2026-07 | M451: =SUMIFS('Saldos Iniciales'!$D:$D,'Saldos Iniciales'!$A:$A,C451,'Saldos Iniciales'!$B:$B,D451)+SUMIFS($K$1:$K$1324,$C$1:$C$1324,C451,$D$1:$D$1324,D451,$B$1:$B$1324,"<="&B451) -> 5034.85 | N451: =IF(tblMovimientos[[#This Row],[Tipo de Movimiento]]="Ingreso",tblMovimientos[[#This Row],[Monto (S/)]],"0") -> 0 | O451: =IF(tblMovimientos[[#This Row],[Tipo de Movimiento]]="Egreso",tblMovimientos[[#This Row],[Monto (S/)]],"0") -> 258.5 | P451: =IF(tblMovimientos[[#This Row],[Tipo de Movimiento]]="Ingreso",tblMovimientos[[#This Row],[Ingreso]],-tblMovimientos[[#This Row],[Egreso]]) -> -258.5 | Q451: =_xlfn.XLOOKUP(tblMovimientos[[#This Row],[Cuenta Bancaria]],Cuentas!$C:$C,Cuentas!$A:$A,"")&"" -> SSP Group | R451: =_xlfn.XLOOKUP(tblMovimientos[[#This Row],[Cuenta Bancaria]],Cuentas!$C:$C,Cuentas!$B:$B,"",0,-1)&""
B452: 46205 | C452: =_xlfn.XLOOKUP(tblMovimientos[[#This Row],[Cuenta Bancaria]],Listas!$B:$B,Listas!$A:$A,"") -> SSP Capital | D452: Bank of America - SSP Capital - 2580-USD | E452: =_xlfn.XLOOKUP(tblMovimientos[[#This Row],[Cuenta Bancaria]],Listas!$B:$B,Listas!$C:$C,"") -> Bank of America | F452: Ingreso | G452: Ing.Interes+Capital Recibido de Empresas Relacionadas | H452: =IFERROR(_xlfn.XLOOKUP(G452,Listas!E:E,Listas!F:F,""),"") -> Operativo | I452: =IFERROR(_xlfn.XLOOKUP(G452,Listas!E:E,Listas!G:G,""),"") -> Interno | J452: 15280.15 | K452: =IF(F452="Ingreso",J452,-J452) -> 15280.15 | L452: 2026-07 | M452: =SUMIFS('Saldos Iniciales'!$D:$D,'Saldos Iniciales'!$A:$A,C452,'Saldos Iniciales'!$B:$B,D452)+SUMIFS($K$1:$K$1324,$C$1:$C$1324,C452,$D$1:$D$1324,D452,$B$1:$B$1324,"<="&B452) -> 23057.39 | N452: =IF(tblMovimientos[[#This Row],[Tipo de Movimiento]]="Ingreso",tblMovimientos[[#This Row],[Monto (S/)]],"0") -> 15280.15 | O452: =IF(tblMovimientos[[#This Row],[Tipo de Movimiento]]="Egreso",tblMovimientos[[#This Row],[Monto (S/)]],"0") -> 0 | P452: =IF(tblMovimientos[[#This Row],[Tipo de Movimiento]]="Ingreso",tblMovimientos[[#This Row],[Ingreso]],-tblMovimientos[[#This Row],[Egreso]]) -> 15280.15 | Q452: =_xlfn.XLOOKUP(tblMovimientos[[#This Row],[Cuenta Bancaria]],Cuentas!$C:$C,Cuentas!$A:$A,"")&"" -> SSP Group | R452: =_xlfn.XLOOKUP(tblMovimientos[[#This Row],[Cuenta Bancaria]],Cuentas!$C:$C,Cuentas!$B:$B,"",0,-1)&""
... B477: 46205 | C477: =_xlfn.XLOOKUP(tblMovimientos[[#This Row],[Cuenta Bancaria]],Listas!$B:$B,Listas!$A:$A,"") -> Go Blue | D477: Amerant Bank - Go Blue - 8206-USD | E477: =_xlfn.XLOOKUP(tblMovimientos[[#This Row],[Cuenta Bancaria]],Listas!$B:$B,Listas!$C:$C,"") -> Amerant Bank | F477: Egreso | G477: Eg.Gastos Operativos (Proveedor) | H477: =IFERROR(_xlfn.XLOOKUP(G477,Listas!E:E,Listas!F:F,""),"") -> Operativo | I477: =IFERROR(_xlfn.XLOOKUP(G477,Listas!E:E,Listas!G:G,""),"") -> Externo | J477: 3309.58 | K477: =IF(F477="Ingreso",J477,-J477) -> -3309.58 | L477: 2026-07 | M477: =SUMIFS('Saldos Iniciales'!$D:$D,'Saldos Iniciales'!$A:$A,C477,'Saldos Iniciales'!$B:$B,D477)+SUMIFS($K$1:$K$1324,$C$1:$C$1324,C477,$D$1:$D$1324,D477,$B$1:$B$1324,"<="&B477) -> 31206.37 | N477: =IF(tblMovimientos[[#This Row],[Tipo de Movimiento]]="Ingreso",tblMovimientos[[#This Row],[Monto (S/)]],"0") -> 0 | O477: =IF(tblMovimientos[[#This Row],[Tipo de Movimiento]]="Egreso",tblMovimientos[[#This Row],[Monto (S/)]],"0") -> 3309.58 | P477: =IF(tblMovimientos[[#This Row],[Tipo de Movimiento]]="Ingreso",tblMovimientos[[#This Row],[Ingreso]],-tblMovimientos[[#This Row],[Egreso]]) -> -3309.58 | Q477: =_xlfn.XLOOKUP(tblMovimientos[[#This Row],[Cuenta Bancaria]],Cuentas!$C:$C,Cuentas!$A:$A,"")&"" -> SSP Group | R477: =_xlfn.XLOOKUP(tblMovimientos[[#This Row],[Cuenta Bancaria]],Cuentas!$C:$C,Cuentas!$B:$B,"",0,-1)&""
B478: 46205 | C478: =_xlfn.XLOOKUP(tblMovimientos[[#This Row],[Cuenta Bancaria]],Listas!$B:$B,Listas!$A:$A,"") -> 3628 Thomas Ave | D478: Bank of America - 3628 Thomas Ave - 4406-USD | E478: =_xlfn.XLOOKUP(tblMovimientos[[#This Row],[Cuenta Bancaria]],Listas!$B:$B,Listas!$C:$C,"") -> Bank of America | F478: Ingreso | G478: Ing.Cobro de Renta (Real State) | H478: Operativo | I478: Externo | J478: 4400 | K478: =IF(F478="Ingreso",J478,-J478) -> 4400 | L478: 2026-07 | M478: =SUMIFS('Saldos Iniciales'!$D:$D,'Saldos Iniciales'!$A:$A,C478,'Saldos Iniciales'!$B:$B,D478)+SUMIFS($K$1:$K$1324,$C$1:$C$1324,C478,$D$1:$D$1324,D478,$B$1:$B$1324,"<="&B478) -> 28485.56 | N478: =IF(tblMovimientos[[#This Row],[Tipo de Movimiento]]="Ingreso",tblMovimientos[[#This Row],[Monto (S/)]],"0") -> 4400 | O478: =IF(tblMovimientos[[#This Row],[Tipo de Movimiento]]="Egreso",tblMovimientos[[#This Row],[Monto (S/)]],"0") -> 0 | P478: =IF(tblMovimientos[[#This Row],[Tipo de Movimiento]]="Ingreso",tblMovimientos[[#This Row],[Ingreso]],-tblMovimientos[[#This Row],[Egreso]]) -> 4400 | Q478: =_xlfn.XLOOKUP(tblMovimientos[[#This Row],[Cuenta Bancaria]],Cuentas!$C:$C,Cuentas!$A:$A,"")&"" -> SSP Group | R478: =_xlfn.XLOOKUP(tblMovimientos[[#This Row],[Cuenta Bancaria]],Cuentas!$C:$C,Cuentas!$B:$B,"",0,-1)&""
...

Sheet SaldoBanco
A1: Banco | B1: N° Cuentas | C1: Saldo Inicial (USD) | D1: Movimientos (USD) | E1: Saldo Actual (USD)
A2: Bank of America | B2: =COUNTIF('Saldos Iniciales'!B:B,"*"&A2&"*") -> 19 | C2: =SUMIF('Saldos Iniciales'!B:B,"*"&A2&"*",'Saldos Iniciales'!D:D) -> 964069.6 | D2: =SUMIF(tblMovimientos[Banco],"*"&A2&"*",tblMovimientos[Monto con signo]) -> 807294.03 | E2: =C2+D2 -> 1771363.6
A3: Amerant Bank | B3: =COUNTIF('Saldos Iniciales'!B:B,"*"&A3&"*") -> 19 | C3: =SUMIF('Saldos Iniciales'!B:B,"*"&A3&"*",'Saldos Iniciales'!D:D) -> 1619026.1 | D3: =SUMIF(tblMovimientos[Banco],"*"&A3&"*",tblMovimientos[Monto con signo]) -> 3150572.7 | E3: =C3+D3 -> 4769598.7
A4: Northern Trust | B4: =COUNTIF('Saldos Iniciales'!B:B,"*"&A4&"*") -> 3 | C4: =SUMIF('Saldos Iniciales'!B:B,"*"&A4&"*",'Saldos Iniciales'!D:D) -> 16509.96 | D4: =SUMIF(tblMovimientos[Banco],"*"&A4&"*",tblMovimientos[Monto con signo]) -> -383.25 | E4: =C4+D4 -> 16126.71
A5: Ocean Bank | B5: =COUNTIF('Saldos Iniciales'!B:B,"*"&A5&"*") -> 1 | C5: =SUMIF('Saldos Iniciales'!B:B,"*"&A5&"*",'Saldos Iniciales'!D:D) -> 57206.89 | D5: =SUMIF(tblMovimientos[Banco],"*"&A5&"*",tblMovimientos[Monto con signo]) -> 0 | E5: =C5+D5 -> 57206.89
A6: Chase Bank | B6: =COUNTIF('Saldos Iniciales'!B:B,"*"&A6&"*") -> 1 | C6: =SUMIF('Saldos Iniciales'!B:B,"*"&A6&"*",'Saldos Iniciales'!D:D) -> 92.02 | D6: =SUMIF(tblMovimientos[Banco],"*"&A6&"*",tblMovimientos[Monto con signo]) -> 10167.16 | E6: =C6+D6 -> 10259.18
A7: Citibank | B7: =COUNTIF('Saldos Iniciales'!B:B,"*"&A7&"*") -> 1 | C7: =SUMIF('Saldos Iniciales'!B:B,"*"&A7&"*",'Saldos Iniciales'!D:D) -> 3364.94 | D7: =SUMIF(tblMovimientos[Banco],"*"&A7&"*",tblMovimientos[Monto con signo]) -> 14530.35 | E7: =C7+D7 -> 17895.29
A8: Bank Morgan Stanley | B8: =COUNTIF('Saldos Iniciales'!B:B,"*"&A8&"*") -> 1 | C8: =SUMIF('Saldos Iniciales'!B:B,"*"&A8&"*",'Saldos Iniciales'!D:D) -> 0 | D8: =SUMIF(tblMovimientos[Banco],"*"&A8&"*",tblMovimientos[Monto con signo]) -> 0 | E8: =C8+D8 -> 0
A9: EFG | B9: =COUNTIF('Saldos Iniciales'!B:B,"*"&A9&"*") -> 1 | C9: =SUMIF('Saldos Iniciales'!B:B,"*"&A9&"*",'Saldos Iniciales'!D:D) -> 0 | D9: =SUMIF(tblMovimientos[Banco],"*"&A9&"*",tblMovimientos[Monto con signo]) -> 0 | E9: =C9+D9 -> 0

Sheet Control de Saldos
A1: Fecha | B1: Empresa | C1: Cuenta | D1: Saldo Inicial 05/25 | E1: Ingresos 05/25 | F1: Egresos 05/25 | G1: Variacion 05/25 | H1: Saldo Final 05/25 | I1: Saldo Inicial 06/25 | J1: Ingresos 06/25 | K1: Egresos 06/25 | L1: Variacion 06/25 | M1: Saldo Final 06/26 | N1: Saldo Inicial 07/26 | O1: Ingresos 07/26 | P1: Egresos 07/26 | Q1: Variacion 07/26 | R1: Saldo Final 07/26 | S1: Saldo Inicial 08/26 | T1: Ingresos 08/26 | U1: Egresos 08/26 | V1: Variacion 08/26 | W1: Saldo Final 08/26 | X1: Saldo Inicial 09/26 | Y1: Ingresos 09/26 | Z1: Egresos 09/26 | AA1: Variacion 09/26 | AB1: Saldo Final 09/26
A2: 2026-05 | B2: CFT Group | C2: Bank of America - CFT Group - 4415-USD | D2: 132689.05 | E2: 994464.58 | F2: 933664.05 | G2: 60800.53 | H2: =D2+E2-F2 -> 193489.58 | I2: =H2 -> 193489.58 | J2: =SUMIFS(Movimientos!$J$1:$J$1324,Movimientos!$C$1:$C$1324,$B2,Movimientos!$D$1:$D$1324,$C2,Movimientos!$L$1:$L$1324,A$3,Movimientos!$F$1:$F$1324,"Ingreso") -> 490932.84 | K2: =SUMIFS(Movimientos!$J$1:$J$1324,Movimientos!$C$1:$C$1324,$B2,Movimientos!$D$1:$D$1324,$C2,Movimientos!$L$1:$L$1324,A$3,Movimientos!$F$1:$F$1324,"Egreso") -> 648479.06 | L2: =+J2-K2 -> -157546.22 | M2: =I2+J2-K2 -> 35943.36 | N2: =M2 -> 35943.36 | O2: =SUMIFS(Movimientos!$J$1:$J$1324,Movimientos!$C$1:$C$1324,$B2,Movimientos!$D$1:$D$1324,$C2,Movimientos!$L$1:$L$1324,A$4,Movimientos!$F$1:$F$1324,"Ingreso") -> 215870.72 | P2: =SUMIFS(Movimientos!$J$1:$J$1324,Movimientos!$C$1:$C$1324,$B2,Movimientos!$D$1:$D$1324,$C2,Movimientos!$L$1:$L$1324,A$4,Movimientos!$F$1:$F$1324,"Egreso") -> 18949.38 | Q2: =+O2-P2 -> 196921.34 | R2: =N2+O2-P2 -> 232864.7 | S2: =R2 -> 232864.7 | T2: =SUMIFS(Movimientos!$J$1:$J$1324,Movimientos!$C$1:$C$1324,$B2,Movimientos!$D$1:$D$1324,$C2,Movimientos!$L$1:$L$1324,A$5,Movimientos!$F$1:$F$1324,"Ingreso") -> 555995.58 | U2: =SUMIFS(Movimientos!$J$1:$J$1324,Movimientos!$C$1:$C$1324,$B2,Movimientos!$D$1:$D$1324,$C2,Movimientos!$L$1:$L$1324,A$5,Movimientos!$F$1:$F$1324,"Egreso") -> 353977.95 | V2: =+T2-U2 -> 202017.63 | W2: =S2+T2-U2 -> 434882.33 | X2: =W2 -> 434882.33 | Y2: =SUMIFS(Movimientos!$J$1:$J$1324,Movimientos!$C$1:$C$1324,$B2,Movimientos!$D$1:$D$1324,$C2,Movimientos!$L$1:$L$1324,A$6,Movimientos!$F$1:$F$1324,"Ingreso") -> 432537.32 | Z2: =SUMIFS(Movimientos!$J$1:$J$1324,Movimientos!$C$1:$C$1324,$B2,Movimientos!$D$1:$D$1324,$C2,Movimientos!$L$1:$L$1324,A$6,Movimientos!$F$1:$F$1324,"Egreso") -> 404200.14 | AA2: =+Y2-Z2 -> 28337.18 | AB2: =X2+Y2-Z2 -> 463219.51
A3: 2026-06 | B3: CFT Group | C3: Amerant Bank - CFT Group - 1906-USD | D3: 62799.53 | E3: 2605274 | F3: 1883425 | G3: 721849 | H3: =D3+E3-F3 -> 784648.53 | I3: =H3 -> 784648.53 | J3: =SUMIFS(Movimientos!$J$1:$J$1324,Movimientos!$C$1:$C$1324,$B3,Movimientos!$D$1:$D$1324,$C3,Movimientos!$L$1:$L$1324,A$3,Movimientos!$F$1:$F$1324,"Ingreso") -> 8947382.8 | K3: =SUMIFS(Movimientos!$J$1:$J$1324,Movimientos!$C$1:$C$1324,$B3,Movimientos!$D$1:$D$1324,$C3,Movimientos!$L$1:$L$1324,A$3,Movimientos!$F$1:$F$1324,"Egreso") -> 3477645 | L3: =+J3-K3 -> 5469737.8 | M3: =I3+J3-K3 -> 6254386.4 | N3: =M3 -> 6254386.4 | O3: =SUMIFS(Movimientos!$J$1:$J$1324,Movimientos!$C$1:$C$1324,$B3,Movimientos!$D$1:$D$1324,$C3,Movimientos!$L$1:$L$1324,A$4,Movimientos!$F$1:$F$1324,"Ingreso") -> 250000 | P3: =SUMIFS(Movimientos!$J$1:$J$1324,Movimientos!$C$1:$C$1324,$B3,Movimientos!$D$1:$D$1324,$C3,Movimientos!$L$1:$L$1324,A$4,Movimientos!$F$1:$F$1324,"Egreso") -> 4274475 | Q3: =+O3-P3 -> -4024475 | R3: =N3+O3-P3 -> 2229911.3 | S3: =R3 -> 2229911.3 | T3: =SUMIFS(Movimientos!$J$1:$J$1324,Movimientos!$C$1:$C$1324,$B3,Movimientos!$D$1:$D$1324,$C3,Movimientos!$L$1:$L$1324,A$5,Movimientos!$F$1:$F$1324,"Ingreso") -> 910061.43 | U3: =SUMIFS(Movimientos!$J$1:$J$1324,Movimientos!$C$1:$C$1324,$B3,Movimientos!$D$1:$D$1324,$C3,Movimientos!$L$1:$L$1324,A$5,Movimientos!$F$1:$F$1324,"Egreso") -> 2839639.5 | V3: =+T3-U3 -> -1929578 | W3: =S3+T3-U3 -> 300333.32 | X3: =W3 -> 300333.32 | Y3: =SUMIFS(Movimientos!$J$1:$J$1324,Movimientos!$C$1:$C$1324,$B3,Movimientos!$D$1:$D$1324,$C3,Movimientos!$L$1:$L$1324,A$6,Movimientos!$F$1:$F$1324,"Ingreso") -> 2658155.4 | Z3: =SUMIFS(Movimientos!$J$1:$J$1324,Movimientos!$C$1:$C$1324,$B3,Movimientos!$D$1:$D$1324,$C3,Movimientos!$L$1:$L$1324,A$6,Movimientos!$F$1:$F$1324,"Egreso") -> 1500103 | AA3: =+Y3-Z3 -> 1158052.4 | AB3: =X3+Y3-Z3 -> 1458385.7
A4: 2026-07 | B4: CFT Group | C4: Northern Trust - CFT Group - 1355-USD | D4: 5274.85 | E4: 0 | F4: 18.82 | G4: -18.82 | H4: =D4+E4-F4 -> 5256.03 | I4: =H4 -> 5256.03 | J4: =SUMIFS(Movimientos!$J$1:$J$1324,Movimientos!$C$1:$C$1324,$B4,Movimientos!$D$1:$D$1324,$C4,Movimientos!$L$1:$L$1324,A$3,Movimientos!$F$1:$F$1324,"Ingreso") -> 0 | K4: =SUMIFS(Movimientos!$J$1:$J$1324,Movimientos!$C$1:$C$1324,$B4,Movimientos!$D$1:$D$1324,$C4,Movimientos!$L$1:$L$1324,A$3,Movimientos!$F$1:$F$1324,"Egreso") -> 0 | L4: =+J4-K4 -> 0 | M4: =I4+J4-K4 -> 5256.03 | N4: =M4 -> 5256.03 | O4: =SUMIFS(Movimientos!$J$1:$J$1324,Movimientos!$C$1:$C$1324,$B4,Movimientos!$D$1:$D$1324,$C4,Movimientos!$L$1:$L$1324,A$4,Movimientos!$F$1:$F$1324,"Ingreso") -> 0 | P4: =SUMIFS(Movimientos!$J$1:$J$1324,Movimientos!$C$1:$C$1324,$B4,Movimientos!$D$1:$D$1324,$C4,Movimientos!$L$1:$L$1324,A$4,Movimientos!$F$1:$F$1324,"Egreso") -> 0 | Q4: =+O4-P4 -> 0 | R4: =N4+O4-P4 -> 5256.03 | S4: =R4 -> 5256.03 | T4: =SUMIFS(Movimientos!$J$1:$J$1324,Movimientos!$C$1:$C$1324,$B4,Movimientos!$D$1:$D$1324,$C4,Movimientos!$L$1:$L$1324,A$5,Movimientos!$F$1:$F$1324,"Ingreso") -> 0 | U4: =SUMIFS(Movimientos!$J$1:$J$1324,Movimientos!$C$1:$C$1324,$B4,Movimientos!$D$1:$D$1324,$C4,Movimientos!$L$1:$L$1324,A$5,Movimientos!$F$1:$F$1324,"Egreso") -> 18.8 | V4: =+T4-U4 -> -18.8 | W4: =S4+T4-U4 -> 5237.23 | X4: =W4 -> 5237.23 | Y4: =SUMIFS(Movimientos!$J$1:$J$1324,Movimientos!$C$1:$C$1324,$B4,Movimientos!$D$1:$D$1324,$C4,Movimientos!$L$1:$L$1324,A$6,Movimientos!$F$1:$F$1324,"Ingreso") -> 0 | Z4: =SUMIFS(Movimientos!$J$1:$J$1324,Movimientos!$C$1:$C$1324,$B4,Movimientos!$D$1:$D$1324,$C4,Movimientos!$L$1:$L$1324,A$6,Movimientos!$F$1:$F$1324,"Egreso") -> 18.8 | AA4: =+Y4-Z4 -> -18.8 | AB4: =X4+Y4-Z4 -> 5218.43
A5: 2026-08 | B5: M1B | C5: Amerant Bank - M1B - 0906-USD | D5: 39539.54 | E5: 1787857.7 | F5: 1770000 | G5: 17857.74 | H5: =D5+E5-F5 -> 57397.28 | I5: =H5 -> 57397.28 | J5: =SUMIFS(Movimientos!$J$1:$J$1324,Movimientos!$C$1:$C$1324,$B5,Movimientos!$D$1:$D$1324,$C5,Movimientos!$L$1:$L$1324,A$3,Movimientos!$F$1:$F$1324,"Ingreso") -> 16742.4 | K5: =SUMIFS(Movimientos!$J$1:$J$1324,Movimientos!$C$1:$C$1324,$B5,Movimientos!$D$1:$D$1324,$C5,Movimientos!$L$1:$L$1324,A$3,Movimientos!$F$1:$F$1324,"Egreso") -> 0 | L5: =+J5-K5 -> 16742.4 | M5: =I5+J5-K5 -> 74139.68 | N5: =M5 -> 74139.68 | O5: =SUMIFS(Movimientos!$J$1:$J$1324,Movimientos!$C$1:$C$1324,$B5,Movimientos!$D$1:$D$1324,$C5,Movimientos!$L$1:$L$1324,A$4,Movimientos!$F$1:$F$1324,"Ingreso") -> 10053.57 | P5: =SUMIFS(Movimientos!$J$1:$J$1324,Movimientos!$C$1:$C$1324,$B5,Movimientos!$D$1:$D$1324,$C5,Movimientos!$L$1:$L$1324,A$4,Movimientos!$F$1:$F$1324,"Egreso") -> 5982 | Q5: =+O5-P5 -> 4071.57 | R5: =N5+O5-P5 -> 78211.25 | S5: =R5 -> 78211.25 | T5: =SUMIFS(Movimientos!$J$1:$J$1324,Movimientos!$C$1:$C$1324,$B5,Movimientos!$D$1:$D$1324,$C5,Movimientos!$L$1:$L$1324,A$5,Movimientos!$F$1:$F$1324,"Ingreso") -> 10068.98 | U5: =SUMIFS(Movimientos!$J$1:$J$1324,Movimientos!$C$1:$C$1324,$B5,Movimientos!$D$1:$D$1324,$C5,Movimientos!$L$1:$L$1324,A$5,Movimientos!$F$1:$F$1324,"Egreso") -> 0 | V5: =+T5-U5 -> 10068.98 | W5: =S5+T5-U5 -> 88280.23 | X5: =W5 -> 88280.23 | Y5: =SUMIFS(Movimientos!$J$1:$J$1324,Movimientos!$C$1:$C$1324,$B5,Movimientos!$D$1:$D$1324,$C5,Movimientos!$L$1:$L$1324,A$6,Movimientos!$F$1:$F$1324,"Ingreso") -> 9843.36 | Z5: =SUMIFS(Movimientos!$J$1:$J$1324,Movimientos!$C$1:$C$1324,$B5,Movimientos!$D$1:$D$1324,$C5,Movimientos!$L$1:$L$1324,A$6,Movimientos!$F$1:$F$1324,"Egreso") -> 0 | AA5: =+Y5-Z5 -> 9843.36 | AB5: =X5+Y5-Z5 -> 98123.59
A6: 2026-09 | B6: M1B | C6: Amerant Bank DACA - M1B - 8231-USD | D6: 5000 | E6: 0 | F6: 0 | G6: 0 | H6: =D6+E6-F6 -> 5000 | I6: =H6 -> 5000 | J6: =SUMIFS(Movimientos!$J$1:$J$1324,Movimientos!$C$1:$C$1324,$B6,Movimientos!$D$1:$D$1324,$C6,Movimientos!$L$1:$L$1324,A$3,Movimientos!$F$1:$F$1324,"Ingreso") -> 0 | K6: =SUMIFS(Movimientos!$J$1:$J$1324,Movimientos!$C$1:$C$1324,$B6,Movimientos!$D$1:$D$1324,$C6,Movimientos!$L$1:$L$1324,A$3,Movimientos!$F$1:$F$1324,"Egreso") -> 0 | L6: =+J6-K6 -> 0 | M6: =I6+J6-K6 -> 5000 | N6: =M6 -> 5000 | O6: =SUMIFS(Movimientos!$J$1:$J$1324,Movimientos!$C$1:$C$1324,$B6,Movimientos!$D$1:$D$1324,$C6,Movimientos!$L$1:$L$1324,A$4,Movimientos!$F$1:$F$1324,"Ingreso") -> 0 | P6: =SUMIFS(Movimientos!$J$1:$J$1324,Movimientos!$C$1:$C$1324,$B6,Movimientos!$D$1:$D$1324,$C6,Movimientos!$L$1:$L$1324,A$4,Movimientos!$F$1:$F$1324,"Egreso") -> 0 | Q6: =+O6-P6 -> 0 | R6: =N6+O6-P6 -> 5000 | S6: =R6 -> 5000 | T6: =SUMIFS(Movimientos!$J$1:$J$1324,Movimientos!$C$1:$C$1324,$B6,Movimientos!$D$1:$D$1324,$C6,Movimientos!$L$1:$L$1324,A$5,Movimientos!$F$1:$F$1324,"Ingreso") -> 0 | U6: =SUMIFS(Movimientos!$J$1:$J$1324,Movimientos!$C$1:$C$1324,$B6,Movimientos!$D$1:$D$1324,$C6,Movimientos!$L$1:$L$1324,A$5,Movimientos!$F$1:$F$1324,"Egreso") -> 0 | V6: =+T6-U6 -> 0 | W6: =S6+T6-U6 -> 5000 | X6: =W6 -> 5000 | Y6: =SUMIFS(Movimientos!$J$1:$J$1324,Movimientos!$C$1:$C$1324,$B6,Movimientos!$D$1:$D$1324,$C6,Movimientos!$L$1:$L$1324,A$6,Movimientos!$F$1:$F$1324,"Ingreso") -> 0 | Z6: =SUMIFS(Movimientos!$J$1:$J$1324,Movimientos!$C$1:$C$1324,$B6,Movimientos!$D$1:$D$1324,$C6,Movimientos!$L$1:$L$1324,A$6,Movimientos!$F$1:$F$1324,"Egreso") -> 0 | AA6: =+Y6-Z6 -> 0 | AB6: =X6+Y6-Z6 -> 5000
A7: 2026-10 | B7: Durand | C7: Amerant Bank - Durand - 0106-USD | D7: 1669.89 | E7: 0 | F7: 0 | G7: 0 | H7: =D7+E7-F7 -> 1669.89 | I7: =H7 -> 1669.89 | J7: =SUMIFS(Movimientos!$J$1:$J$1324,Movimientos!$C$1:$C$1324,$B7,Movimientos!$D$1:$D$1324,$C7,Movimientos!$L$1:$L$1324,A$3,Movimientos!$F$1:$F$1324,"Ingreso") -> 0 | K7: =SUMIFS(Movimientos!$J$1:$J$1324,Movimientos!$C$1:$C$1324,$B7,Movimientos!$D$1:$D$1324,$C7,Movimientos!$L$1:$L$1324,A$3,Movimientos!$F$1:$F$1324,"Egreso") -> 0 | L7: =+J7-K7 -> 0 | M7: =I7+J7-K7 -> 1669.89 | N7: =M7 -> 1669.89 | O7: =SUMIFS(Movimientos!$J$1:$J$1324,Movimientos!$C$1:$C$1324,$B7,Movimientos!$D$1:$D$1324,$C7,Movimientos!$L$1:$L$1324,A$4,Movimientos!$F$1:$F$1324,"Ingreso") -> 0 | P7: =SUMIFS(Movimientos!$J$1:$J$1324,Movimientos!$C$1:$C$1324,$B7,Movimientos!$D$1:$D$1324,$C7,Movimientos!$L$1:$L$1324,A$4,Movimientos!$F$1:$F$1324,"Egreso") -> 0 | Q7: =+O7-P7 -> 0 | R7: =N7+O7-P7 -> 1669.89 | S7: =R7 -> 1669.89 | T7: =SUMIFS(Movimientos!$J$1:$J$1324,Movimientos!$C$1:$C$1324,$B7,Movimientos!$D$1:$D$1324,$C7,Movimientos!$L$1:$L$1324,A$5,Movimientos!$F$1:$F$1324,"Ingreso") -> 0 | U7: =SUMIFS(Movimientos!$J$1:$J$1324,Movimientos!$C$1:$C$1324,$B7,Movimientos!$D$1:$D$1324,$C7,Movimientos!$L$1:$L$1324,A$5,Movimientos!$F$1:$F$1324,"Egreso") -> 0 | V7: =+T7-U7 -> 0 | W7: =S7+T7-U7 -> 1669.89 | X7: =W7 -> 1669.89 | Y7: =SUMIFS(Movimientos!$J$1:$J$1324,Movimientos!$C$1:$C$1324,$B7,Movimientos!$D$1:$D$1324,$C7,Movimientos!$L$1:$L$1324,A$6,Movimientos!$F$1:$F$1324,"Ingreso") -> 0 | Z7: =SUMIFS(Movimientos!$J$1:$J$1324,Movimientos!$C$1:$C$1324,$B7,Movimientos!$D$1:$D$1324,$C7,Movimientos!$L$1:$L$1324,F$5,Movimientos!$F$1:$F$1324,"Egreso") -> 0 | AA7: =+Y7-Z7 -> 0 | AB7: =X7+Y7-Z7 -> 1669.89
A8: 2026-11 | B8: A&M Imports | C8: Bank of America - A&M Imports - 3797-USD | D8: 177088.59 | E8: 2810870.3 | F8: 2563105.8 | G8: 247764.53 | H8: =D8+E8-F8 -> 424853.12 | I8: =H8 -> 424853.12 | J8: =SUMIFS(Movimientos!$J$1:$J$1324,Movimientos!$C$1:$C$1324,$B8,Movimientos!$D$1:$D$1324,$C8,Movimientos!$L$1:$L$1324,A$3,Movimientos!$F$1:$F$1324,"Ingreso") -> 440602.39 | K8: =SUMIFS(Movimientos!$J$1:$J$1324,Movimientos!$C$1:$C$1324,$B8,Movimientos!$D$1:$D$1324,$C8,Movimientos!$L$1:$L$1324,A$3,Movimientos!$F$1:$F$1324,"Egreso") -> 375709.88 | L8: =+J8-K8 -> 64892.51 | M8: =I8+J8-K8 -> 489745.63 | N8: =M8 -> 489745.63 | O8: =SUMIFS(Movimientos!$J$1:$J$1324,Movimientos!$C$1:$C$1324,$B8,Movimientos!$D$1:$D$1324,$C8,Movimientos!$L$1:$L$1324,A$4,Movimientos!$F$1:$F$1324,"Ingreso") -> 1306812 | P8: =SUMIFS(Movimientos!$J$1:$J$1324,Movimientos!$C$1:$C$1324,$B8,Movimientos!$D$1:$D$1324,$C8,Movimientos!$L$1:$L$1324,A$4,Movimientos!$F$1:$F$1324,"Egreso") -> 338131.63 | Q8: =+O8-P8 -> 968680.41 | R8: =N8+O8-P8 -> 1458426 | S8: =R8 -> 1458426 | T8: =SUMIFS(Movimientos!$J$1:$J$1324,Movimientos!$C$1:$C$1324,$B8,Movimientos!$D$1:$D$1324,$C8,Movimientos!$L$1:$L$1324,A$5,Movimientos!$F$1:$F$1324,"Ingreso") -> 250866.9 | U8: =SUMIFS(Movimientos!$J$1:$J$1324,Movimientos!$C$1:$C$1324,$B8,Movimientos!$D$1:$D$1324,$C8,Movimientos!$L$1:$L$1324,A$5,Movimientos!$F$1:$F$1324,"Egreso") -> 289394.7 | V8: =+T8-U8 -> -38527.8 | W8: =S8+T8-U8 -> 1419898.2 | X8: =W8 -> 1419898.2 | Y8: =SUMIFS(Movimientos!$J$1:$J$1324,Movimientos!$C$1:$C$1324,$B8,Movimientos!$D$1:$D$1324,$C8,Movimientos!$L$1:$L$1324,A$6,Movimientos!$F$1:$F$1324,"Ingreso") -> 542761.8 | Z8: =SUMIFS(Movimientos!$J$1:$J$1324,Movimientos!$C$1:$C$1324,$B8,Movimientos!$D$1:$D$1324,$C8,Movimientos!$L$1:$L$1324,F$5,Movimientos!$F$1:$F$1324,"Egreso") -> 0 | AA8: =+Y8-Z8 -> 542761.8 | AB8: =X8+Y8-Z8 -> 1962660
A9: 2026-12 | B9: SSP Capital | C9: Bank of America - SSP Capital - 2580-USD | D9: 12379.18 | E9: 15321.74 | F9: 16857.71 | G9: -1535.97 | H9: =D9+E9-F9 -> 10843.21 | I9: =H9 -> 10843.21 | J9: =SUMIFS(Movimientos!$J$1:$J$1324,Movimientos!$C$1:$C$1324,$B9,Movimientos!$D$1:$D$1324,$C9,Movimientos!$L$1:$L$1324,A$3,Movimientos!$F$1:$F$1324,"Ingreso") -> 15307.88 | K9: =SUMIFS(Movimientos!$J$1:$J$1324,Movimientos!$C$1:$C$1324,$B9,Movimientos!$D$1:$D$1324,$C9,Movimientos!$L$1:$L$1324,A$3,Movimientos!$F$1:$F$1324,"Egreso") -> 18373.85 | L9: =+J9-K9 -> -3065.97 | M9: =I9+J9-K9 -> 7777.24 | N9: =M9 -> 7777.24 | O9: =SUMIFS(Movimientos!$J$1:$J$1324,Movimientos!$C$1:$C$1324,$B9,Movimientos!$D$1:$D$1324,$C9,Movimientos!$L$1:$L$1324,A$4,Movimientos!$F$1:$F$1324,"Ingreso") -> 15280.15 | P9: =SUMIFS(Movimientos!$J$1:$J$1324,Movimientos!$C$1:$C$1324,$B9,Movimientos!$D$1:$D$1324,$C9,Movimientos!$L$1:$L$1324,A$4,Movimientos!$F$1:$F$1324,"Egreso") -> 17912.62 | Q9: =+O9-P9 -> -2632.47 | R9: =N9+O9-P9 -> 5144.77 | S9: =R9 -> 5144.77 | T9: =SUMIFS(Movimientos!$J$1:$J$1324,Movimientos!$C$1:$C$1324,$B9,Movimientos!$D$1:$D$1324,$C9,Movimientos!$L$1:$L$1324,A$5,Movimientos!$F$1:$F$1324,"Ingreso") -> 35280.15 | U9: =SUMIFS(Movimientos!$J$1:$J$1324,Movimientos!$C$1:$C$1324,$B9,Movimientos!$D$1:$D$1324,$C9,Movimientos!$L$1:$L$1324,A$5,Movimientos!$F$1:$F$1324,"Egreso") -> 15210.03 | V9: =+T9-U9 -> 20070.12 | W9: =S9+T9-U9 -> 25214.89 | X9: =W9 -> 25214.89 | Y9: =SUMIFS(Movimientos!$J$1:$J$1324,Movimientos!$C$1:$C$1324,$B9,Movimientos!$D$1:$D$1324,$C9,Movimientos!$L$1:$L$1324,A$6,Movimientos!$F$1:$F$1324,"Ingreso") -> 15266.29 | Z9: =SUMIFS(Movimientos!$J$1:$J$1324,Movimientos!$C$1:$C$1324,$B9,Movimientos!$D$1:$D$1324,$C9,Movimientos!$L$1:$L$1324,F$5,Movimientos!$F$1:$F$1324,"Egreso") -> 0 | AA9: =+Y9-Z9 -> 15266.29 | AB9: =X9+Y9-Z9 -> 40481.18
B10: SSP Capital | C10: Bank of America - SSP Capital - 1655-USD | D10: 759.07 | E10: 0 | F10: 196.07 | G10: -196.07 | H10: =D10+E10-F10 -> 563 | I10: =H10 -> 563 | J10: =SUMIFS(Movimientos!$J$1:$J$1324,Movimientos!$C$1:$C$1324,$B10,Movimientos!$D$1:$D$1324,$C10,Movimientos!$L$1:$L$1324,A$3,Movimientos!$F$1:$F$1324,"Ingreso") -> 0 | K10: =SUMIFS(Movimientos!$J$1:$J$1324,Movimientos!$C$1:$C$1324,$B10,Movimientos!$D$1:$D$1324,$C10,Movimientos!$L$1:$L$1324,A$3,Movimientos!$F$1:$F$1324,"Egreso") -> 196.08 | L10: =+J10-K10 -> -196.08 | M10: =I10+J10-K10 -> 366.92 | N10: =M10 -> 366.92 | O10: =SUMIFS(Movimientos!$J$1:$J$1324,Movimientos!$C$1:$C$1324,$B10,Movimientos!$D$1:$D$1324,$C10,Movimientos!$L$1:$L$1324,A$4,Movimientos!$F$1:$F$1324,"Ingreso") -> 1000 | P10: =SUMIFS(Movimientos!$J$1:$J$1324,Movimientos!$C$1:$C$1324,$B10,Movimientos!$D$1:$D$1324,$C10,Movimientos!$L$1:$L$1324,A$4,Movimientos!$F$1:$F$1324,"Egreso") -> 196.1 | Q10: =+O10-P10 -> 803.9 | R10: =N10+O10-P10 -> 1170.82 | S10: =R10 -> 1170.82 | T10: =SUMIFS(Movimientos!$J$1:$J$1324,Movimientos!$C$1:$C$1324,$B10,Movimientos!$D$1:$D$1324,$C10,Movimientos!$L$1:$L$1324,A$5,Movimientos!$F$1:$F$1324,"Ingreso") -> 0 | U10: =SUMIFS(Movimientos!$J$1:$J$1324,Movimientos!$C$1:$C$1324,$B10,Movimientos!$D$1:$D$1324,$C10,Movimientos!$L$1:$L$1324,A$5,Movimientos!$F$1:$F$1324,"Egreso") -> 196.41 | V10: =+T10-U10 -> -196.41 | W10: =S10+T10-U10 -> 974.41 | X10: =W10 -> 974.41 | Y10: =SUMIFS(Movimientos!$J$1:$J$1324,Movimientos!$C$1:$C$1324,$B10,Movimientos!$D$1:$D$1324,$C10,Movimientos!$L$1:$L$1324,A$6,Movimientos!$F$1:$F$1324,"Ingreso") -> 0 | Z10: =SUMIFS(Movimientos!$J$1:$J$1324,Movimientos!$C$1:$C$1324,$B10,Movimientos!$D$1:$D$1324,$C10,Movimientos!$L$1:$L$1324,F$5,Movimientos!$F$1:$F$1324,"Egreso") -> 0 | AA10: =+Y10-Z10 -> 0 | AB10: =X10+Y10-Z10 -> 974.41
B11: SSP Capital | C11: EFG - SSP Capital - 21.0-USD | D11: 0 | E11: 0 | F11: 0 | G11: 0 | H11: =D11+E11-F11 -> 0 | I11: =H11 -> 0 | J11: =SUMIFS(Movimientos!$J$1:$J$1324,Movimientos!$C$1:$C$1324,$B11,Movimientos!$D$1:$D$1324,$C11,Movimientos!$L$1:$L$1324,A$3,Movimientos!$F$1:$F$1324,"Ingreso") -> 0 | K11: =SUMIFS(Movimientos!$J$1:$J$1324,Movimientos!$C$1:$C$1324,$B11,Movimientos!$D$1:$D$1324,$C11,Movimientos!$L$1:$L$1324,A$3,Movimientos!$F$1:$F$1324,"Egreso") -> 0 | L11: =+J11-K11 -> 0 | M11: =I11+J11-K11 -> 0 | N11: =M11 -> 0 | O11: =SUMIFS(Movimientos!$J$1:$J$1324,Movimientos!$C$1:$C$1324,$B11,Movimientos!$D$1:$D$1324,$C11,Movimientos!$L$1:$L$1324,A$4,Movimientos!$F$1:$F$1324,"Ingreso") -> 0 | P11: =SUMIFS(Movimientos!$J$1:$J$1324,Movimientos!$C$1:$C$1324,$B11,Movimientos!$D$1:$D$1324,$C11,Movimientos!$L$1:$L$1324,A$4,Movimientos!$F$1:$F$1324,"Egreso") -> 0 | Q11: =+O11-P11 -> 0 | R11: =N11+O11-P11 -> 0 | S11: =R11 -> 0 | T11: =SUMIFS(Movimientos!$J$1:$J$1324,Movimientos!$C$1:$C$1324,$B11,Movimientos!$D$1:$D$1324,$C11,Movimientos!$L$1:$L$1324,A$5,Movimientos!$F$1:$F$1324,"Ingreso") -> 0 | U11: =SUMIFS(Movimientos!$J$1:$J$1324,Movimientos!$C$1:$C$1324,$B11,Movimientos!$D$1:$D$1324,$C11,Movimientos!$L$1:$L$1324,A$5,Movimientos!$F$1:$F$1324,"Egreso") -> 0 | V11: =+T11-U11 -> 0 | W11: =S11+T11-U11 -> 0 | X11: =W11 -> 0 | Y11: =SUMIFS(Movimientos!$J$1:$J$1324,Movimientos!$C$1:$C$1324,$B11,Movimientos!$D$1:$D$1324,$C11,Movimientos!$L$1:$L$1324,A$6,Movimientos!$F$1:$F$1324,"Ingreso") -> 0 | Z11: =SUMIFS(Movimientos!$J$1:$J$1324,Movimientos!$C$1:$C$1324,$B11,Movimientos!$D$1:$D$1324,$C11,Movimientos!$L$1:$L$1324,F$5,Movimientos!$F$1:$F$1324,"Egreso") -> 0 | AA11: =+Y11-Z11 -> 0 | AB11: =X11+Y11-Z11 -> 0
B12: SSP Capital | C12: Amerant Bank - SSP Capital - 4706-USD | D12: 219857.82 | E12: 1689975 | F12: 1664911.5 | G12: 25063.49 | H12: =D12+E12-F12 -> 244921.31 | I12: =H12 -> 244921.31 | J12: =SUMIFS(Movimientos!$J$1:$J$1324,Movimientos!$C$1:$C$1324,$B12,Movimientos!$D$1:$D$1324,$C12,Movimientos!$L$1:$L$1324,A$3,Movimientos!$F$1:$F$1324,"Ingreso") -> 4970000 | K12: =SUMIFS(Movimientos!$J$1:$J$1324,Movimientos!$C$1:$C$1324,$B12,Movimientos!$D$1:$D$1324,$C12,Movimientos!$L$1:$L$1324,A$3,Movimientos!$F$1:$F$1324,"Egreso") -> 4343222.5 | L12: =+J12-K12 -> 626777.45 | M12: =I12+J12-K12 -> 871698.76 | N12: =M12 -> 871698.76 | O12: =SUMIFS(Movimientos!$J$1:$J$1324,Movimientos!$C$1:$C$1324,$B12,Movimientos!$D$1:$D$1324,$C12,Movimientos!$L$1:$L$1324,A$4,Movimientos!$F$1:$F$1324,"Ingreso") -> 1320000 | P12: =SUMIFS(Movimientos!$J$1:$J$1324,Movimientos!$C$1:$C$1324,$B12,Movimientos!$D$1:$D$1324,$C12,Movimientos!$L$1:$L$1324,A$4,Movimientos!$F$1:$F$1324,"Egreso") -> 1502405.7 | Q12: =+O12-P12 -> -182405.75 | R12: =N12+O12-P12 -> 689293.01 | S12: =R12 -> 689293.01 | T12: =SUMIFS(Movimientos!$J$1:$J$1324,Movimientos!$C$1:$C$1324,$B12,Movimientos!$D$1:$D$1324,$C12,Movimientos!$L$1:$L$1324,A$5,Movimientos!$F$1:$F$1324,"Ingreso") -> 1100000 | U12: =SUMIFS(Movimientos!$J$1:$J$1324,Movimientos!$C$1:$C$1324,$B12,Movimientos!$D$1:$D$1324,$C12,Movimientos!$L$1:$L$1324,A$5,Movimientos!$F$1:$F$1324,"Egreso") -> 1081074.7 | V12: =+T12-U12 -> 18925.31 | W12: =S12+T12-U12 -> 708218.32 | X12: =W12 -> 708218.32 | Y12: =SUMIFS(Movimientos!$J$1:$J$1324,Movimientos!$C$1:$C$1324,$B12,Movimientos!$D$1:$D$1324,$C12,Movimientos!$L$1:$L$1324,A$6,Movimientos!$F$1:$F$1324,"Ingreso") -> 350000 | Z12: =SUMIFS(Movimientos!$J$1:$J$1324,Movimientos!$C$1:$C$1324,$B12,Movimientos!$D$1:$D$1324,$C12,Movimientos!$L$1:$L$1324,F$5,Movimientos!$F$1:$F$1324,"Egreso") -> 0 | AA12: =+Y12-Z12 -> 350000 | AB12: =X12+Y12-Z12 -> 1058218.3
B13: SSP Capital | C13: Northern Trust - SSP Capital - 1452-USD | D13: 4870.11 | E13: 0 | F13: 108.91 | G13: -108.91 | H13: =D13+E13-F13 -> 4761.2 | I13: =H13 -> 4761.2 | J13: =SUMIFS(Movimientos!$J$1:$J$1324,Movimientos!$C$1:$C$1324,$B13,Movimientos!$D$1:$D$1324,$C13,Movimientos!$L$1:$L$1324,A$3,Movimientos!$F$1:$F$1324,"Ingreso") -> 0 | K13: =SUMIFS(Movimientos!$J$1:$J$1324,Movimientos!$C$1:$C$1324,$B13,Movimientos!$D$1:$D$1324,$C13,Movimientos!$L$1:$L$1324,A$3,Movimientos!$F$1:$F$1324,"Egreso") -> 0 | L13: =+J13-K13 -> 0 | M13: =I13+J13-K13 -> 4761.2 | N13: =M13 -> 4761.2 | O13: =SUMIFS(Movimientos!$J$1:$J$1324,Movimientos!$C$1:$C$1324,$B13,Movimientos!$D$1:$D$1324,$C13,Movimientos!$L$1:$L$1324,A$4,Movimientos!$F$1:$F$1324,"Ingreso") -> 0 | P13: =SUMIFS(Movimientos!$J$1:$J$1324,Movimientos!$C$1:$C$1324,$B13,Movimientos!$D$1:$D$1324,$C13,Movimientos!$L$1:$L$1324,A$4,Movimientos!$F$1:$F$1324,"Egreso") -> 0 | Q13: =+O13-P13 -> 0 | R13: =N13+O13-P13 -> 4761.2 | S13: =R13 -> 4761.2 | T13: =SUMIFS(Movimientos!$J$1:$J$1324,Movimientos!$C$1:$C$1324,$B13,Movimientos!$D$1:$D$1324,$C13,Movimientos!$L$1:$L$1324,A$5,Movimientos!$F$1:$F$1324,"Ingreso") -> 0 | U13: =SUMIFS(Movimientos!$J$1:$J$1324,Movimientos!$C$1:$C$1324,$B13,Movimientos!$D$1:$D$1324,$C13,Movimientos!$L$1:$L$1324,A$5,Movimientos!$F$1:$F$1324,"Egreso") -> 108.95 | V13: =+T13-U13 -> -108.95 | W13: =S13+T13-U13 -> 4652.25 | X13: =W13 -> 4652.25 | Y13: =SUMIFS(Movimientos!$J$1:$J$1324,Movimientos!$C$1:$C$1324,$B13,Movimientos!$D$1:$D$1324,$C13,Movimientos!$L$1:$L$1324,A$6,Movimientos!$F$1:$F$1324,"Ingreso") -> 0 | Z13: =SUMIFS(Movimientos!$J$1:$J$1324,Movimientos!$C$1:$C$1324,$B13,Movimientos!$D$1:$D$1324,$C13,Movimientos!$L$1:$L$1324,F$5,Movimientos!$F$1:$F$1324,"Egreso") -> 0 | AA13: =+Y13-Z13 -> 0 | AB13: =X13+Y13-Z13 -> 4652.25
B14: SSP Capital | C14: Amerant Bank Money Market - SSP Capital - 1006-USD | D14: 747521.2 | E14: 2291.75 | F14: 0 | G14: 2291.75 | H14: =D14+E14-F14 -> 749812.95 | I14: =H14 -> 749812.95 | J14: =SUMIFS(Movimientos!$J$1:$J$1324,Movimientos!$C$1:$C$1324,$B14,Movimientos!$D$1:$D$1324,$C14,Movimientos!$L$1:$L$1324,A$3,Movimientos!$F$1:$F$1324,"Ingreso") -> 56867.66 | K14: =SUMIFS(Movimientos!$J$1:$J$1324,Movimientos!$C$1:$C$1324,$B14,Movimientos!$D$1:$D$1324,$C14,Movimientos!$L$1:$L$1324,A$3,Movimientos!$F$1:$F$1324,"Egreso") -> 0 | L14: =+J14-K14 -> 56867.66 | M14: =I14+J14-K14 -> 806680.61 | N14: =M14 -> 806680.61 | O14: =SUMIFS(Movimientos!$J$1:$J$1324,Movimientos!$C$1:$C$1324,$B14,Movimientos!$D$1:$D$1324,$C14,Movimientos!$L$1:$L$1324,A$4,Movimientos!$F$1:$F$1324,"Ingreso") -> 2426.71 | P14: =SUMIFS(Movimientos!$J$1:$J$1324,Movimientos!$C$1:$C$1324,$B14,Movimientos!$D$1:$D$1324,$C14,Movimientos!$L$1:$L$1324,A$4,Movimientos!$F$1:$F$1324,"Egreso") -> 0 | Q14: =+O14-P14 -> 2426.71 | R14: =N14+O14-P14 -> 809107.32 | S14: =R14 -> 809107.32 | T14: =SUMIFS(Movimientos!$J$1:$J$1324,Movimientos!$C$1:$C$1324,$B14,Movimientos!$D$1:$D$1324,$C14,Movimientos!$L$1:$L$1324,A$5,Movimientos!$F$1:$F$1324,"Ingreso") -> 2434.02 | U14: =SUMIFS(Movimientos!$J$1:$J$1324,Movimientos!$C$1:$C$1324,$B14,Movimientos!$D$1:$D$1324,$C14,Movimientos!$L$1:$L$1324,A$5,Movimientos!$F$1:$F$1324,"Egreso") -> 0 | V14: =+T14-U14 -> 2434.02 | W14: =S14+T14-U14 -> 811541.34 | X14: =W14 -> 811541.34 | Y14: =SUMIFS(Movimientos!$J$1:$J$1324,Movimientos!$C$1:$C$1324,$B14,Movimientos!$D$1:$D$1324,$C14,Movimientos!$L$1:$L$1324,A$6,Movimientos!$F$1:$F$1324,"Ingreso") -> 2362.59 | Z14: =SUMIFS(Movimientos!$J$1:$J$1324,Movimientos!$C$1:$C$1324,$B14,Movimientos!$D$1:$D$1324,$C14,Movimientos!$L$1:$L$1324,F$5,Movimientos!$F$1:$F$1324,"Egreso") -> 0 | AA14: =+Y14-Z14 -> 2362.59 | AB14: =X14+Y14-Z14 -> 813903.93
B15: SSP Capital | C15: Amerant Bank DACA - SSP Capital - 9873-USD | D15: 5000 | E15: 0 | F15: 0 | G15: 0 | H15: =D15+E15-F15 -> 5000 | I15: =H15 -> 5000 | J15: =SUMIFS(Movimientos!$J$1:$J$1324,Movimientos!$C$1:$C$1324,$B15,Movimientos!$D$1:$D$1324,$C15,Movimientos!$L$1:$L$1324,A$3,Movimientos!$F$1:$F$1324,"Ingreso") -> 0 | K15: =SUMIFS(Movimientos!$J$1:$J$1324,Movimientos!$C$1:$C$1324,$B15,Movimientos!$D$1:$D$1324,$C15,Movimientos!$L$1:$L$1324,A$3,Movimientos!$F$1:$F$1324,"Egreso") -> 0 | L15: =+J15-K15 -> 0 | M15: =I15+J15-K15 -> 5000 | N15: =M15 -> 5000 | O15: =SUMIFS(Movimientos!$J$1:$J$1324,Movimientos!$C$1:$C$1324,$B15,Movimientos!$D$1:$D$1324,$C15,Movimientos!$L$1:$L$1324,A$4,Movimientos!$F$1:$F$1324,"Ingreso") -> 0 | P15: =SUMIFS(Movimientos!$J$1:$J$1324,Movimientos!$C$1:$C$1324,$B15,Movimientos!$D$1:$D$1324,$C15,Movimientos!$L$1:$L$1324,A$4,Movimientos!$F$1:$F$1324,"Egreso") -> 0 | Q15: =+O15-P15 -> 0 | R15: =N15+O15-P15 -> 5000 | S15: =R15 -> 5000 | T15: =SUMIFS(Movimientos!$J$1:$J$1324,Movimientos!$C$1:$C$1324,$B15,Movimientos!$D$1:$D$1324,$C15,Movimientos!$L$1:$L$1324,A$5,Movimientos!$F$1:$F$1324,"Ingreso") -> 0 | U15: =SUMIFS(Movimientos!$J$1:$J$1324,Movimientos!$C$1:$C$1324,$B15,Movimientos!$D$1:$D$1324,$C15,Movimientos!$L$1:$L$1324,A$5,Movimientos!$F$1:$F$1324,"Egreso") -> 0 | V15: =+T15-U15 -> 0 | W15: =S15+T15-U15 -> 5000 | X15: =W15 -> 5000 | Y15: =SUMIFS(Movimientos!$J$1:$J$1324,Movimientos!$C$1:$C$1324,$B15,Movimientos!$D$1:$D$1324,$C15,Movimientos!$L$1:$L$1324,A$6,Movimientos!$F$1:$F$1324,"Ingreso") -> 0 | Z15: =SUMIFS(Movimientos!$J$1:$J$1324,Movimientos!$C$1:$C$1324,$B15,Movimientos!$D$1:$D$1324,$C15,Movimientos!$L$1:$L$1324,F$5,Movimientos!$F$1:$F$1324,"Egreso") -> 0 | AA15: =+Y15-Z15 -> 0 | AB15: =X15+Y15-Z15 -> 5000
B16: Cross Family Trust | C16: Ocean Bank - Cross Family Trust - 3405-USD | D16: 57206.89 | E16: 0 | F16: 0 | G16: 0 | H16: =D16+E16-F16 -> 57206.89 | I16: =H16 -> 57206.89 | J16: =SUMIFS(Movimientos!$J$1:$J$1324,Movimientos!$C$1:$C$1324,$B16,Movimientos!$D$1:$D$1324,$C16,Movimientos!$L$1:$L$1324,A$3,Movimientos!$F$1:$F$1324,"Ingreso") -> 0 | K16: =SUMIFS(Movimientos!$J$1:$J$1324,Movimientos!$C$1:$C$1324,$B16,Movimientos!$D$1:$D$1324,$C16,Movimientos!$L$1:$L$1324,A$3,Movimientos!$F$1:$F$1324,"Egreso") -> 0 | L16: =+J16-K16 -> 0 | M16: =I16+J16-K16 -> 57206.89 | N16: =M16 -> 57206.89 | O16: =SUMIFS(Movimientos!$J$1:$J$1324,Movimientos!$C$1:$C$1324,$B16,Movimientos!$D$1:$D$1324,$C16,Movimientos!$L$1:$L$1324,A$4,Movimientos!$F$1:$F$1324,"Ingreso") -> 0 | P16: =SUMIFS(Movimientos!$J$1:$J$1324,Movimientos!$C$1:$C$1324,$B16,Movimientos!$D$1:$D$1324,$C16,Movimientos!$L$1:$L$1324,A$4,Movimientos!$F$1:$F$1324,"Egreso") -> 0 | Q16: =+O16-P16 -> 0 | R16: =N16+O16-P16 -> 57206.89 | S16: =R16 -> 57206.89 | T16: =SUMIFS(Movimientos!$J$1:$J$1324,Movimientos!$C$1:$C$1324,$B16,Movimientos!$D$1:$D$1324,$C16,Movimientos!$L$1:$L$1324,A$5,Movimientos!$F$1:$F$1324,"Ingreso") -> 0 | U16: =SUMIFS(Movimientos!$J$1:$J$1324,Movimientos!$C$1:$C$1324,$B16,Movimientos!$D$1:$D$1324,$C16,Movimientos!$L$1:$L$1324,A$5,Movimientos!$F$1:$F$1324,"Egreso") -> 0 | V16: =+T16-U16 -> 0 | W16: =S16+T16-U16 -> 57206.89 | X16: =W16 -> 57206.89 | Y16: =SUMIFS(Movimientos!$J$1:$J$1324,Movimientos!$C$1:$C$1324,$B16,Movimientos!$D$1:$D$1324,$C16,Movimientos!$L$1:$L$1324,A$6,Movimientos!$F$1:$F$1324,"Ingreso") -> 0 | Z16: =SUMIFS(Movimientos!$J$1:$J$1324,Movimientos!$C$1:$C$1324,$B16,Movimientos!$D$1:$D$1324,$C16,Movimientos!$L$1:$L$1324,F$5,Movimientos!$F$1:$F$1324,"Egreso") -> 0 | AA16: =+Y16-Z16 -> 0 | AB16: =X16+Y16-Z16 -> 57206.89
B17: Cross Family Trust | C17: Northern Trust - Cross Family Trust - 9263-USD | D17: 6365 | E17: 0 | F17: 0 | G17: 0 | H17: =D17+E17-F17 -> 6365 | I17: =H17 -> 6365 | J17: =SUMIFS(Movimientos!$J$1:$J$1324,Movimientos!$C$1:$C$1324,$B17,Movimientos!$D$1:$D$1324,$C17,Movimientos!$L$1:$L$1324,A$3,Movimientos!$F$1:$F$1324,"Ingreso") -> 0 | K17: =SUMIFS(Movimientos!$J$1:$J$1324,Movimientos!$C$1:$C$1324,$B17,Movimientos!$D$1:$D$1324,$C17,Movimientos!$L$1:$L$1324,A$3,Movimientos!$F$1:$F$1324,"Egreso") -> 0 | L17: =+J17-K17 -> 0 | M17: =I17+J17-K17 -> 6365 | N17: =M17 -> 6365 | O17: =SUMIFS(Movimientos!$J$1:$J$1324,Movimientos!$C$1:$C$1324,$B17,Movimientos!$D$1:$D$1324,$C17,Movimientos!$L$1:$L$1324,A$4,Movimientos!$F$1:$F$1324,"Ingreso") -> 0 | P17: =SUMIFS(Movimientos!$J$1:$J$1324,Movimientos!$C$1:$C$1324,$B17,Movimientos!$D$1:$D$1324,$C17,Movimientos!$L$1:$L$1324,A$4,Movimientos!$F$1:$F$1324,"Egreso") -> 0 | Q17: =+O17-P17 -> 0 | R17: =N17+O17-P17 -> 6365 | S17: =R17 -> 6365 | T17: =SUMIFS(Movimientos!$J$1:$J$1324,Movimientos!$C$1:$C$1324,$B17,Movimientos!$D$1:$D$1324,$C17,Movimientos!$L$1:$L$1324,A$5,Movimientos!$F$1:$F$1324,"Ingreso") -> 0 | U17: =SUMIFS(Movimientos!$J$1:$J$1324,Movimientos!$C$1:$C$1324,$B17,Movimientos!$D$1:$D$1324,$C17,Movimientos!$L$1:$L$1324,A$5,Movimientos!$F$1:$F$1324,"Egreso") -> 0 | V17: =+T17-U17 -> 0 | W17: =S17+T17-U17 -> 6365 | X17: =W17 -> 6365 | Y17: =SUMIFS(Movimientos!$J$1:$J$1324,Movimientos!$C$1:$C$1324,$B17,Movimientos!$D$1:$D$1324,$C17,Movimientos!$L$1:$L$1324,A$6,Movimientos!$F$1:$F$1324,"Ingreso") -> 0 | Z17: =SUMIFS(Movimientos!$J$1:$J$1324,Movimientos!$C$1:$C$1324,$B17,Movimientos!$D$1:$D$1324,$C17,Movimientos!$L$1:$L$1324,F$5,Movimientos!$F$1:$F$1324,"Egreso") -> 0 | AA17: =+Y17-Z17 -> 0 | AB17: =X17+Y17-Z17 -> 6365
B18: Cross Family Trust | C18: Bank of America - Cross Family Trust - 3124-USD | D18: 13221.89 | E18: 50000 | F18: 6015 | G18: 43985 | H18: =D18+E18-F18 -> 57206.89 | I18: =H18 -> 57206.89 | J18: =SUMIFS(Movimientos!$J$1:$J$1324,Movimientos!$C$1:$C$1324,$B18,Movimientos!$D$1:$D$1324,$C18,Movimientos!$L$1:$L$1324,A$3,Movimientos!$F$1:$F$1324,"Ingreso") -> 0 | K18: =SUMIFS(Movimientos!$J$1:$J$1324,Movimientos!$C$1:$C$1324,$B18,Movimientos!$D$1:$D$1324,$C18,Movimientos!$L$1:$L$1324,A$3,Movimientos!$F$1:$F$1324,"Egreso") -> 12000 | L18: =+J18-K18 -> -12000 | M18: =I18+J18-K18 -> 45206.89 | N18: =M18 -> 45206.89 | O18: =SUMIFS(Movimientos!$J$1:$J$1324,Movimientos!$C$1:$C$1324,$B18,Movimientos!$D$1:$D$1324,$C18,Movimientos!$L$1:$L$1324,A$4,Movimientos!$F$1:$F$1324,"Ingreso") -> 0 | P18: =SUMIFS(Movimientos!$J$1:$J$1324,Movimientos!$C$1:$C$1324,$B18,Movimientos!$D$1:$D$1324,$C18,Movimientos!$L$1:$L$1324,A$4,Movimientos!$F$1:$F$1324,"Egreso") -> 0 | Q18: =+O18-P18 -> 0 | R18: =N18+O18-P18 -> 45206.89 | S18: =R18 -> 45206.89 | T18: =SUMIFS(Movimientos!$J$1:$J$1324,Movimientos!$C$1:$C$1324,$B18,Movimientos!$D$1:$D$1324,$C18,Movimientos!$L$1:$L$1324,A$5,Movimientos!$F$1:$F$1324,"Ingreso") -> 0 | U18: =SUMIFS(Movimientos!$J$1:$J$1324,Movimientos!$C$1:$C$1324,$B18,Movimientos!$D$1:$D$1324,$C18,Movimientos!$L$1:$L$1324,A$5,Movimientos!$F$1:$F$1324,"Egreso") -> 6000 | V18: =+T18-U18 -> -6000 | W18: =S18+T18-U18 -> 39206.89 | X18: =W18 -> 39206.89 | Y18: =SUMIFS(Movimientos!$J$1:$J$1324,Movimientos!$C$1:$C$1324,$B18,Movimientos!$D$1:$D$1324,$C18,Movimientos!$L$1:$L$1324,A$6,Movimientos!$F$1:$F$1324,"Ingreso") -> 0 | Z18: =SUMIFS(Movimientos!$J$1:$J$1324,Movimientos!$C$1:$C$1324,$B18,Movimientos!$D$1:$D$1324,$C18,Movimientos!$L$1:$L$1324,F$5,Movimientos!$F$1:$F$1324,"Egreso") -> 0 | AA18: =+Y18-Z18 -> 0 | AB18: =X18+Y18-Z18 -> 39206.89
B19: Cross Family Trust | C19: Amerant Bank - Cross Family Trust - 4706-USD | D19: 65717.6 | E19: 0 | F19: 55000 | G19: -55000 | H19: =D19+E19-F19 -> 10717.6 | I19: =H19 -> 10717.6 | J19: =SUMIFS(Movimientos!$J$1:$J$1324,Movimientos!$C$1:$C$1324,$B19,Movimientos!$D$1:$D$1324,$C19,Movimientos!$L$1:$L$1324,A$3,Movimientos!$F$1:$F$1324,"Ingreso") -> 2580000 | K19: =SUMIFS(Movimientos!$J$1:$J$1324,Movimientos!$C$1:$C$1324,$B19,Movimientos!$D$1:$D$1324,$C19,Movimientos!$L$1:$L$1324,A$3,Movimientos!$F$1:$F$1324,"Egreso") -> 2309000 | L19: =+J19-K19 -> 271000 | M19: =I19+J19-K19 -> 281717.6 | N19: =M19 -> 281717.6 | O19: =SUMIFS(Movimientos!$J$1:$J$1324,Movimientos!$C$1:$C$1324,$B19,Movimientos!$D$1:$D$1324,$C19,Movimientos!$L$1:$L$1324,A$4,Movimientos!$F$1:$F$1324,"Ingreso") -> 0 | P19: =SUMIFS(Movimientos!$J$1:$J$1324,Movimientos!$C$1:$C$1324,$B19,Movimientos!$D$1:$D$1324,$C19,Movimientos!$L$1:$L$1324,A$4,Movimientos!$F$1:$F$1324,"Egreso") -> 200000 | Q19: =+O19-P19 -> -200000 | R19: =N19+O19-P19 -> 81717.6 | S19: =R19 -> 81717.6 | T19: =SUMIFS(Movimientos!$J$1:$J$1324,Movimientos!$C$1:$C$1324,$B19,Movimientos!$D$1:$D$1324,$C19,Movimientos!$L$1:$L$1324,A$5,Movimientos!$F$1:$F$1324,"Ingreso") -> 560000 | U19: =SUMIFS(Movimientos!$J$1:$J$1324,Movimientos!$C$1:$C$1324,$B19,Movimientos!$D$1:$D$1324,$C19,Movimientos!$L$1:$L$1324,A$5,Movimientos!$F$1:$F$1324,"Egreso") -> 523000 | V19: =+T19-U19 -> 37000 | W19: =S19+T19-U19 -> 118717.6 | X19: =W19 -> 118717.6 | Y19: =SUMIFS(Movimientos!$J$1:$J$1324,Movimientos!$C$1:$C$1324,$B19,Movimientos!$D$1:$D$1324,$C19,Movimientos!$L$1:$L$1324,A$6,Movimientos!$F$1:$F$1324,"Ingreso") -> 34281.76 | Z19: =SUMIFS(Movimientos!$J$1:$J$1324,Movimientos!$C$1:$C$1324,$B19,Movimientos!$D$1:$D$1324,$C19,Movimientos!$L$1:$L$1324,F$5,Movimientos!$F$1:$F$1324,"Egreso") -> 0 | AA19: =+Y19-Z19 -> 34281.76 | AB19: =X19+Y19-Z19 -> 152999.36
B20: Cross Security Trust | C20: Bank of America - Cross Security Trust - 6642-USD | D20: 13088.59 | E20: 1575001.8 | F20: 1500000 | G20: 75001.78 | H20: =D20+E20-F20 -> 88090.37 | I20: =H20 -> 88090.37 | J20: =SUMIFS(Movimientos!$J$1:$J$1324,Movimientos!$C$1:$C$1324,$B20,Movimientos!$D$1:$D$1324,$C20,Movimientos!$L$1:$L$1324,A$3,Movimientos!$F$1:$F$1324,"Ingreso") -> 310000.62 | K20: =SUMIFS(Movimientos!$J$1:$J$1324,Movimientos!$C$1:$C$1324,$B20,Movimientos!$D$1:$D$1324,$C20,Movimientos!$L$1:$L$1324,A$3,Movimientos!$F$1:$F$1324,"Egreso") -> 130587 | L20: =+J20-K20 -> 179413.62 | M20: =I20+J20-K20 -> 267503.99 | N20: =M20 -> 267503.99 | O20: =SUMIFS(Movimientos!$J$1:$J$1324,Movimientos!$C$1:$C$1324,$B20,Movimientos!$D$1:$D$1324,$C20,Movimientos!$L$1:$L$1324,A$4,Movimientos!$F$1:$F$1324,"Ingreso") -> 3.46 | P20: =SUMIFS(Movimientos!$J$1:$J$1324,Movimientos!$C$1:$C$1324,$B20,Movimientos!$D$1:$D$1324,$C20,Movimientos!$L$1:$L$1324,A$4,Movimientos!$F$1:$F$1324,"Egreso") -> 59902 | Q20: =+O20-P20 -> -59898.54 | R20: =N20+O20-P20 -> 207605.45 | S20: =R20 -> 207605.45 | T20: =SUMIFS(Movimientos!$J$1:$J$1324,Movimientos!$C$1:$C$1324,$B20,Movimientos!$D$1:$D$1324,$C20,Movimientos!$L$1:$L$1324,A$5,Movimientos!$F$1:$F$1324,"Ingreso") -> 70003.87 | U20: =SUMIFS(Movimientos!$J$1:$J$1324,Movimientos!$C$1:$C$1324,$B20,Movimientos!$D$1:$D$1324,$C20,Movimientos!$L$1:$L$1324,A$5,Movimientos!$F$1:$F$1324,"Egreso") -> 59924.98 | V20: =+T20-U20 -> 10078.89 | W20: =S20+T20-U20 -> 217684.34 | X20: =W20 -> 217684.34 | Y20: =SUMIFS(Movimientos!$J$1:$J$1324,Movimientos!$C$1:$C$1324,$B20,Movimientos!$D$1:$D$1324,$C20,Movimientos!$L$1:$L$1324,A$6,Movimientos!$F$1:$F$1324,"Ingreso") -> 4.24 | Z20: =SUMIFS(Movimientos!$J$1:$J$1324,Movimientos!$C$1:$C$1324,$B20,Movimientos!$D$1:$D$1324,$C20,Movimientos!$L$1:$L$1324,F$5,Movimientos!$F$1:$F$1324,"Egreso") -> 0 | AA20: =+Y20-Z20 -> 4.24 | AB20: =X20+Y20-Z20 -> 217688.58
B21: Electrama | C21: Chase Bank - Electrama - 6520-USD | D21: 808.83 | E21: 3000 | F21: 2580.86 | G21: 419.14 | H21: =D21+E21-F21 -> 1227.97 | I21: =H21 -> 1227.97 | J21: =SUMIFS(Movimientos!$J$1:$J$1324,Movimientos!$C$1:$C$1324,$B21,Movimientos!$D$1:$D$1324,$C21,Movimientos!$L$1:$L$1324,A$3,Movimientos!$F$1:$F$1324,"Ingreso") -> 0 | K21: =SUMIFS(Movimientos!$J$1:$J$1324,Movimientos!$C$1:$C$1324,$B21,Movimientos!$D$1:$D$1324,$C21,Movimientos!$L$1:$L$1324,A$3,Movimientos!$F$1:$F$1324,"Egreso") -> 0 | L21: =+J21-K21 -> 0 | M21: =I21+J21-K21 -> 1227.97 | N21: =M21 -> 1227.97 | O21: =SUMIFS(Movimientos!$J$1:$J$1324,Movimientos!$C$1:$C$1324,$B21,Movimientos!$D$1:$D$1324,$C21,Movimientos!$L$1:$L$1324,A$4,Movimientos!$F$1:$F$1324,"Ingreso") -> 14659.29 | P21: =SUMIFS(Movimientos!$J$1:$J$1324,Movimientos!$C$1:$C$1324,$B21,Movimientos!$D$1:$D$1324,$C21,Movimientos!$L$1:$L$1324,A$4,Movimientos!$F$1:$F$1324,"Egreso") -> 590 | Q21: =+O21-P21 -> 14069.29 | R21: =N21+O21-P21 -> 15297.26 | S21: =R21 -> 15297.26 | T21: =SUMIFS(Movimientos!$J$1:$J$1324,Movimientos!$C$1:$C$1324,$B21,Movimientos!$D$1:$D$1324,$C21,Movimientos!$L$1:$L$1324,A$5,Movimientos!$F$1:$F$1324,"Ingreso") -> 0 | U21: =SUMIFS(Movimientos!$J$1:$J$1324,Movimientos!$C$1:$C$1324,$B21,Movimientos!$D$1:$D$1324,$C21,Movimientos!$L$1:$L$1324,A$5,Movimientos!$F$1:$F$1324,"Egreso") -> 1310.43 | V21: =+T21-U21 -> -1310.43 | W21: =S21+T21-U21 -> 13986.83 | X21: =W21 -> 13986.83 | Y21: =SUMIFS(Movimientos!$J$1:$J$1324,Movimientos!$C$1:$C$1324,$B21,Movimientos!$D$1:$D$1324,$C21,Movimientos!$L$1:$L$1324,A$6,Movimientos!$F$1:$F$1324,"Ingreso") -> 0 | Z21: =SUMIFS(Movimientos!$J$1:$J$1324,Movimientos!$C$1:$C$1324,$B21,Movimientos!$D$1:$D$1324,$C21,Movimientos!$L$1:$L$1324,F$5,Movimientos!$F$1:$F$1324,"Egreso") -> 0 | AA21: =+Y21-Z21 -> 0 | AB21: =X21+Y21-Z21 -> 13986.83
... B34: Go Blue | C34: Amerant Bank - Go Blue - 8206-USD | D34: 13656.26 | E34: 55000 | F34: 59580.02 | G34: -4580.02 | H34: =D34+E34-F34 -> 9076.24 | I34: =H34 -> 9076.24 | J34: =SUMIFS(Movimientos!$J$1:$J$1324,Movimientos!$C$1:$C$1324,$B34,Movimientos!$D$1:$D$1324,$C34,Movimientos!$L$1:$L$1324,A$3,Movimientos!$F$1:$F$1324,"Ingreso") -> 59000 | K34: =SUMIFS(Movimientos!$J$1:$J$1324,Movimientos!$C$1:$C$1324,$B34,Movimientos!$D$1:$D$1324,$C34,Movimientos!$L$1:$L$1324,A$3,Movimientos!$F$1:$F$1324,"Egreso") -> 49496.81 | L34: =+J34-K34 -> 9503.19 | M34: =I34+J34-K34 -> 18579.43 | N34: =M34 -> 18579.43 | O34: =SUMIFS(Movimientos!$J$1:$J$1324,Movimientos!$C$1:$C$1324,$B34,Movimientos!$D$1:$D$1324,$C34,Movimientos!$L$1:$L$1324,A$4,Movimientos!$F$1:$F$1324,"Ingreso") -> 50000 | P34: =SUMIFS(Movimientos!$J$1:$J$1324,Movimientos!$C$1:$C$1324,$B34,Movimientos!$D$1:$D$1324,$C34,Movimientos!$L$1:$L$1324,A$4,Movimientos!$F$1:$F$1324,"Egreso") -> 59620.72 | Q34: =+O34-P34 -> -9620.72 | R34: =N34+O34-P34 -> 8958.71 | S34: =R34 -> 8958.71 | T34: =SUMIFS(Movimientos!$J$1:$J$1324,Movimientos!$C$1:$C$1324,$B34,Movimientos!$D$1:$D$1324,$C34,Movimientos!$L$1:$L$1324,A$5,Movimientos!$F$1:$F$1324,"Ingreso") -> 23000 | U34: =SUMIFS(Movimientos!$J$1:$J$1324,Movimientos!$C$1:$C$1324,$B34,Movimientos!$D$1:$D$1324,$C34,Movimientos!$L$1:$L$1324,A$5,Movimientos!$F$1:$F$1324,"Egreso") -> 24462.06 | V34: =+T34-U34 -> -1462.06 | W34: =S34+T34-U34 -> 7496.65 | X34: =W34 -> 7496.65 | Y34: =SUMIFS(Movimientos!$J$1:$J$1324,Movimientos!$C$1:$C$1324,$B34,Movimientos!$D$1:$D$1324,$C34,Movimientos!$L$1:$L$1324,A$6,Movimientos!$F$1:$F$1324,"Ingreso") -> 20000 | Z34: =SUMIFS(Movimientos!$J$1:$J$1324,Movimientos!$C$1:$C$1324,$B34,Movimientos!$D$1:$D$1324,$C34,Movimientos!$L$1:$L$1324,F$5,Movimientos!$F$1:$F$1324,"Egreso") -> 0 | AA34: =+Y34-Z34 -> 20000 | AB34: =X34+Y34-Z34 -> 27496.65
B35: Go Blue | C35: Amerant Bank - Go Blue - 1557-USD | D35: 5293.35 | H35: =D35+E35-F35 -> 5293.35 | I35: =H35 -> 5293.35 | J35: =SUMIFS(Movimientos!$J$1:$J$1324,Movimientos!$C$1:$C$1324,$B35,Movimientos!$D$1:$D$1324,$C35,Movimientos!$L$1:$L$1324,A$3,Movimientos!$F$1:$F$1324,"Ingreso") -> 0 | K35: =SUMIFS(Movimientos!$J$1:$J$1324,Movimientos!$C$1:$C$1324,$B35,Movimientos!$D$1:$D$1324,$C35,Movimientos!$L$1:$L$1324,A$3,Movimientos!$F$1:$F$1324,"Egreso") -> 0 | L35: =+J35-K35 -> 0 | M35: =I35+J35-K35 -> 5293.35 | N35: =M35 -> 5293.35 | O35: =SUMIFS(Movimientos!$J$1:$J$1324,Movimientos!$C$1:$C$1324,$B35,Movimientos!$D$1:$D$1324,$C35,Movimientos!$L$1:$L$1324,A$4,Movimientos!$F$1:$F$1324,"Ingreso") -> 15000 | P35: =SUMIFS(Movimientos!$J$1:$J$1324,Movimientos!$C$1:$C$1324,$B35,Movimientos!$D$1:$D$1324,$C35,Movimientos!$L$1:$L$1324,A$4,Movimientos!$F$1:$F$1324,"Egreso") -> 17617.13 | Q35: =+O35-P35 -> -2617.13 | R35: =N35+O35-P35 -> 2676.22 | S35: =R35 -> 2676.22 | T35: =SUMIFS(Movimientos!$J$1:$J$1324,Movimientos!$C$1:$C$1324,$B35,Movimientos!$D$1:$D$1324,$C35,Movimientos!$L$1:$L$1324,A$5,Movimientos!$F$1:$F$1324,"Ingreso") -> 0 | U35: =SUMIFS(Movimientos!$J$1:$J$1324,Movimientos!$C$1:$C$1324,$B35,Movimientos!$D$1:$D$1324,$C35,Movimientos!$L$1:$L$1324,A$5,Movimientos!$F$1:$F$1324,"Egreso") -> 612.87 | V35: =+T35-U35 -> -612.87 | W35: =S35+T35-U35 -> 2063.35 | X35: =W35 -> 2063.35 | Y35: =SUMIFS(Movimientos!$J$1:$J$1324,Movimientos!$C$1:$C$1324,$B35,Movimientos!$D$1:$D$1324,$C35,Movimientos!$L$1:$L$1324,A$6,Movimientos!$F$1:$F$1324,"Ingreso") -> 6500 | Z35: =SUMIFS(Movimientos!$J$1:$J$1324,Movimientos!$C$1:$C$1324,$B35,Movimientos!$D$1:$D$1324,$C35,Movimientos!$L$1:$L$1324,F$5,Movimientos!$F$1:$F$1324,"Egreso") -> 0 | AA35: =+Y35-Z35 -> 6500 | AB35: =X35+Y35-Z35 -> 8563.35

Sheet Saldos Diarios
A1: Día | B1: Fecha | C1: CFT Group | D1: M1B | E1: Durand | F1: A&M Imports | G1: SSP Capital | H1: Cross Family Trust | I1: Cross Security Trust | J1: Electrama | K1: Sacred Valley Capital | L1: YWC Capital | M1: Soweto | N1: Green Stone Trust | O1: EC Auto | P1: Arbor Capital Properties | Q1: 2515 Overbrook | R1: 112 Florida Ave | S1: 3628 Thomas Ave | T1: Green Harbor Trust | U1: Go Blue | V1: Pacha Ventures LLC | W1: CFT1 Residence | X1: Carmen Cross Irrevocable Trust | Y1: SIYP LLC | Z1: Prendamas SRL | AA1: 360 Harbor Lane LLC | AB1: Five Capital | AC1: Nobe Aparments | AD1: Don Cross Life | AE1: TOTAL CONSOLIDADO
A2: 1 | B2: 46143 | C2: 200763.43 | D2: 51288.03 | E2: 1669.89 | F2: 589990.3 | G2: 990387.38 | H2: 142511.38 | I2: 13088.59 | J2: 808.83 | K2: 114.3 | L2: 2267.72 | M2: 3364.94 | N2: 1968.99 | O2: 901.34 | P2: 1444.08 | Q2: 23262.6 | R2: 6853.91 | S2: 21338.39 | T2: 345 | U2: 13491.26 | V2: =IF(YEAR($B2)*100+MONTH($B2)<--SUBSTITUTE(_xlfn.XLOOKUP("Pacha Ventures LLC",'Saldos Iniciales'!$A:$A,'Saldos Iniciales'!$C:$C),"-",""),0,SUMIFS('Saldos Iniciales'!$D:$D,'Saldos Iniciales'!$A:$A,"Pacha Ventures LLC")+SUMIFS(Movimientos!$K$1:$K$1324,Movimientos!$C$1:$C$1324,"Pacha Ventures LLC",Movimientos!$B$1:$B$1324,"<="&$B2)) -> 0 | W2: =IF(YEAR($B2)*100+MONTH($B2)<--SUBSTITUTE(_xlfn.XLOOKUP("*CFT 1 residence*",'Saldos Iniciales'!$B:$B,'Saldos Iniciales'!$C:$C,,2),"-",""),0,SUMIFS('Saldos Iniciales'!$D:$D,'Saldos Iniciales'!$B:$B,"*CFT 1 residence*")+SUMIFS(Movimientos!$K$1:$K$1324,Movimientos!$C$1:$C$1324,"CFT1 Residence",Movimientos!$B$1:$B$1324,"<="&$B2)) -> 0 | X2: =IF(YEAR($B2)*100+MONTH($B2)<--SUBSTITUTE(_xlfn.XLOOKUP("Carmen Cross Irrevocable Trust",'Saldos Iniciales'!$A:$A,'Saldos Iniciales'!$C:$C),"-",""),0,SUMIFS('Saldos Iniciales'!$D:$D,'Saldos Iniciales'!$A:$A,"Carmen Cross Irrevocable Trust")+SUMIFS(Movimientos!$K$1:$K$1324,Movimientos!$C$1:$C$1324,"Carmen Cross Irrevocable Trust",Movimientos!$B$1:$B$1324,"<="&$B2)) -> 0 | Y2: =IF(YEAR($B2)*100+MONTH($B2)<--SUBSTITUTE(_xlfn.XLOOKUP("SIYP LLC",'Saldos Iniciales'!$A:$A,'Saldos Iniciales'!$C:$C),"-",""),0,SUMIFS('Saldos Iniciales'!$D:$D,'Saldos Iniciales'!$A:$A,"SIYP LLC")+SUMIFS(Movimientos!$K$1:$K$1324,Movimientos!$C$1:$C$1324,"SIYP LLC",Movimientos!$B$1:$B$1324,"<="&$B2)) -> 0 | Z2: =IF(YEAR($B2)*100+MONTH($B2)<--SUBSTITUTE(_xlfn.XLOOKUP("Prendamas SRL",'Saldos Iniciales'!$A:$A,'Saldos Iniciales'!$C:$C),"-",""),0,SUMIFS('Saldos Iniciales'!$D:$D,'Saldos Iniciales'!$A:$A,"Prendamas SRL")+SUMIFS(Movimientos!$K$1:$K$1324,Movimientos!$C$1:$C$1324,"Prendamas SRL",Movimientos!$B$1:$B$1324,"<="&$B2)) -> 0 | AA2: =IF(YEAR($B2)*100+MONTH($B2)<--SUBSTITUTE(_xlfn.XLOOKUP("360 Harbor Lane LLC",'Saldos Iniciales'!$A:$A,'Saldos Iniciales'!$C:$C),"-",""),0,SUMIFS('Saldos Iniciales'!$D:$D,'Saldos Iniciales'!$A:$A,"360 Harbor Lane LLC")+SUMIFS(Movimientos!$K$1:$K$1324,Movimientos!$C$1:$C$1324,"360 Harbor Lane LLC",Movimientos!$B$1:$B$1324,"<="&$B2)) -> 0 | AB2: =IF(YEAR($B2)*100+MONTH($B2)<--SUBSTITUTE(_xlfn.XLOOKUP("Five Capital ",'Saldos Iniciales'!$A:$A,'Saldos Iniciales'!$C:$C),"-",""),0,SUMIFS('Saldos Iniciales'!$D:$D,'Saldos Iniciales'!$A:$A,"Five Capital ")+SUMIFS(Movimientos!$K$1:$K$1324,Movimientos!$C$1:$C$1324,"Five Capital ",Movimientos!$B$1:$B$1324,"<="&$B2)) -> 0 | AC2: =IF(YEAR($B2)*100+MONTH($B2)<--SUBSTITUTE(_xlfn.XLOOKUP("Nobe Aparments",'Saldos Iniciales'!$A:$A,'Saldos Iniciales'!$C:$C),"-",""),0,SUMIFS('Saldos Iniciales'!$D:$D,'Saldos Iniciales'!$A:$A,"Nobe Aparments")+SUMIFS(Movimientos!$K$1:$K$1324,Movimientos!$C$1:$C$1324,"Nobe Aparments",Movimientos!$B$1:$B$1324,"<="&$B2)) -> 0 | AD2: =IF(YEAR($B2)*100+MONTH($B2)<--SUBSTITUTE(_xlfn.XLOOKUP("Don Cross Life",'Saldos Iniciales'!$A:$A,'Saldos Iniciales'!$C:$C),"-",""),0,SUMIFS('Saldos Iniciales'!$D:$D,'Saldos Iniciales'!$A:$A,"Don Cross Life")+SUMIFS(Movimientos!$K$1:$K$1324,Movimientos!$C$1:$C$1324,"Don Cross Life",Movimientos!$B$1:$B$1324,"<="&$B2)) -> 0 | AE2: 2065860.4
A3: =+A2+1 -> 2 | B3: 46144 | C3: 200763.43 | D3: 51288.03 | E3: 1669.89 | F3: 589990.3 | G3: 990387.38 | H3: 142511.38 | I3: 13088.59 | J3: 808.83 | K3: 114.3 | L3: 2267.72 | M3: 3364.94 | N3: 1968.99 | O3: 901.34 | P3: 1444.08 | Q3: 23262.6 | R3: 6853.91 | S3: 21338.39 | T3: 345 | U3: 13491.26 | V3: =IF(YEAR($B3)*100+MONTH($B3)<--SUBSTITUTE(_xlfn.XLOOKUP("Pacha Ventures LLC",'Saldos Iniciales'!$A:$A,'Saldos Iniciales'!$C:$C),"-",""),0,SUMIFS('Saldos Iniciales'!$D:$D,'Saldos Iniciales'!$A:$A,"Pacha Ventures LLC")+SUMIFS(Movimientos!$K$1:$K$1324,Movimientos!$C$1:$C$1324,"Pacha Ventures LLC",Movimientos!$B$1:$B$1324,"<="&$B3)) -> 0 | W3: =IF(YEAR($B3)*100+MONTH($B3)<--SUBSTITUTE(_xlfn.XLOOKUP("*CFT 1 residence*",'Saldos Iniciales'!$B:$B,'Saldos Iniciales'!$C:$C,,2),"-",""),0,SUMIFS('Saldos Iniciales'!$D:$D,'Saldos Iniciales'!$B:$B,"*CFT 1 residence*")+SUMIFS(Movimientos!$K$1:$K$1324,Movimientos!$C$1:$C$1324,"CFT1 Residence",Movimientos!$B$1:$B$1324,"<="&$B3)) -> 0 | X3: =IF(YEAR($B3)*100+MONTH($B3)<--SUBSTITUTE(_xlfn.XLOOKUP("Carmen Cross Irrevocable Trust",'Saldos Iniciales'!$A:$A,'Saldos Iniciales'!$C:$C),"-",""),0,SUMIFS('Saldos Iniciales'!$D:$D,'Saldos Iniciales'!$A:$A,"Carmen Cross Irrevocable Trust")+SUMIFS(Movimientos!$K$1:$K$1324,Movimientos!$C$1:$C$1324,"Carmen Cross Irrevocable Trust",Movimientos!$B$1:$B$1324,"<="&$B3)) -> 0 | Y3: =IF(YEAR($B3)*100+MONTH($B3)<--SUBSTITUTE(_xlfn.XLOOKUP("SIYP LLC",'Saldos Iniciales'!$A:$A,'Saldos Iniciales'!$C:$C),"-",""),0,SUMIFS('Saldos Iniciales'!$D:$D,'Saldos Iniciales'!$A:$A,"SIYP LLC")+SUMIFS(Movimientos!$K$1:$K$1324,Movimientos!$C$1:$C$1324,"SIYP LLC",Movimientos!$B$1:$B$1324,"<="&$B3)) -> 0 | Z3: =IF(YEAR($B3)*100+MONTH($B3)<--SUBSTITUTE(_xlfn.XLOOKUP("Prendamas SRL",'Saldos Iniciales'!$A:$A,'Saldos Iniciales'!$C:$C),"-",""),0,SUMIFS('Saldos Iniciales'!$D:$D,'Saldos Iniciales'!$A:$A,"Prendamas SRL")+SUMIFS(Movimientos!$K$1:$K$1324,Movimientos!$C$1:$C$1324,"Prendamas SRL",Movimientos!$B$1:$B$1324,"<="&$B3)) -> 0 | AA3: =IF(YEAR($B3)*100+MONTH($B3)<--SUBSTITUTE(_xlfn.XLOOKUP("360 Harbor Lane LLC",'Saldos Iniciales'!$A:$A,'Saldos Iniciales'!$C:$C),"-",""),0,SUMIFS('Saldos Iniciales'!$D:$D,'Saldos Iniciales'!$A:$A,"360 Harbor Lane LLC")+SUMIFS(Movimientos!$K$1:$K$1324,Movimientos!$C$1:$C$1324,"360 Harbor Lane LLC",Movimientos!$B$1:$B$1324,"<="&$B3)) -> 0 | AB3: =IF(YEAR($B3)*100+MONTH($B3)<--SUBSTITUTE(_xlfn.XLOOKUP("Five Capital ",'Saldos Iniciales'!$A:$A,'Saldos Iniciales'!$C:$C),"-",""),0,SUMIFS('Saldos Iniciales'!$D:$D,'Saldos Iniciales'!$A:$A,"Five Capital ")+SUMIFS(Movimientos!$K$1:$K$1324,Movimientos!$C$1:$C$1324,"Five Capital ",Movimientos!$B$1:$B$1324,"<="&$B3)) -> 0 | AC3: =IF(YEAR($B3)*100+MONTH($B3)<--SUBSTITUTE(_xlfn.XLOOKUP("Nobe Aparments",'Saldos Iniciales'!$A:$A,'Saldos Iniciales'!$C:$C),"-",""),0,SUMIFS('Saldos Iniciales'!$D:$D,'Saldos Iniciales'!$A:$A,"Nobe Aparments")+SUMIFS(Movimientos!$K$1:$K$1324,Movimientos!$C$1:$C$1324,"Nobe Aparments",Movimientos!$B$1:$B$1324,"<="&$B3)) -> 0 | AD3: =IF(YEAR($B3)*100+MONTH($B3)<--SUBSTITUTE(_xlfn.XLOOKUP("Don Cross Life",'Saldos Iniciales'!$A:$A,'Saldos Iniciales'!$C:$C),"-",""),0,SUMIFS('Saldos Iniciales'!$D:$D,'Saldos Iniciales'!$A:$A,"Don Cross Life")+SUMIFS(Movimientos!$K$1:$K$1324,Movimientos!$C$1:$C$1324,"Don Cross Life",Movimientos!$B$1:$B$1324,"<="&$B3)) -> 0 | AE3: 2065860.4
